Workbook

Sheet Arvind & LC Invoice Details.
A1: Arvind & Linen Club Invoice Details | G1: =SUBTOTAL(9,G3:G1001) -> 6630 | H1: =SUBTOTAL(9,H3:H1001) -> 14655490 | I1: =SUBTOTAL(9,I3:I1001) -> 22369532 | J1: Invoice Count | K1: =SUBTOTAL(3,B3:B1001) -> 67
A2: Supplier Name | B2: Invoice Number | C2: Invoice Date | D2: Month | E2: Year | F2: Brand Name | G2: Quantity | H2: Billing Amount | I2: MRP Amount | J2: Invoice Soft Copy | K2: Invoice Season | L2: Invoice Status | M2: Stock Remarks | N2: Booking Status | O2: Margin Analysis Status
A3: VISHAL MARKETING & COMPANY | B3: S/25-26/842 | C3: 45875 | D3: =IF(C3=0," ",TEXT(C3,"MMMM")) -> August | E3: =IF(C3=0," ",TEXT(C3,"YYYY")) -> 2025 | F3: U.S POLO | G3: 136 | H3: 288717 | I3: 411664 | J3: VISHAL MARKETING & CO(US POLO)-842.pdf | K3: AW'25 | L3: Uploaded In TEN | M3: TAS (HZB) Stock Transfer To JainSons (HZB). | N3: BOOKED IN VENUE. | O3: DONE.
A4: VISHAL MARKETING & COMPANY | B4: S/25-26/875 | C4: 45880 | D4: =IF(C4=0," ",TEXT(C4,"MMMM")) -> August | E4: =IF(C4=0," ",TEXT(C4,"YYYY")) -> 2025 | F4: U.S POLO | G4: 277 | H4: 641394 | I4: 914523 | J4: VISHAL MARKETING & CO(US POLO)-875.pdf | K4: AW'25 | L4: Uploaded In TEN | M4: Deoghar Stock Transfer To Patna. | N4: BOOKED IN VENUE. | O4: DONE.
A5: VISHAL MARKETING & COMPANY | B5: S/25-26/890 | C5: 45880 | D5: =IF(C5=0," ",TEXT(C5,"MMMM")) -> August | E5: =IF(C5=0," ",TEXT(C5,"YYYY")) -> 2025 | F5: ARROW | G5: 193 | H5: 337736 | I5: 494507 | J5: VISHAL MARKETING & CO(ARROW)-890.pdf | K5: AW'25 | L5: Uploaded In TEN | M5: Product Received (Lee Deoghar). | N5: BOOKED IN VENUE. | O5: DONE.
A6: VISHAL MARKETING & COMPANY | B6: S/25-26/891 | C6: 45880 | D6: =IF(C6=0," ",TEXT(C6,"MMMM")) -> August | E6: =IF(C6=0," ",TEXT(C6,"YYYY")) -> 2025 | F6: ARROW | G6: 222 | H6: 384126 | I6: 563878 | J6: VISHAL MARKETING & CO(ARROW)-891.pdf | K6: AW'25 | L6: Uploaded In TEN | M6: Product Received (Lee Deoghar). | N6: BOOKED IN VENUE. | O6: DONE.
A7: VISHAL MARKETING & COMPANY | B7: S/25-26/906 | C7: 45881 | D7: =IF(C7=0," ",TEXT(C7,"MMMM")) -> August | E7: =IF(C7=0," ",TEXT(C7,"YYYY")) -> 2025 | F7: FLYING MACHINE | G7: 270 | H7: 403814 | I7: 594830 | J7: VISHAL MARKETING & CO(FM)-906.pdf | K7: AW'25 | L7: Uploaded In TEN | M7: Product Received (Vaishnavi Deoghar). | N7: BOOKED IN VENUE. | O7: DONE.
A8: VISHAL MARKETING & COMPANY | B8: S/25-26/934 | C8: 45883 | D8: =IF(C8=0," ",TEXT(C8,"MMMM")) -> August | E8: =IF(C8=0," ",TEXT(C8,"YYYY")) -> 2025 | F8: U.S POLO KIDS | G8: 114 | H8: 166997 | I8: 238486 | J8: VISHAL MARKETING & CO(USPA KIDS)-934.pdf | K8: AW'25 | L8: Uploaded In TEN | M8: Product Received (Vaishnavi Deoghar). | N8: BOOKED IN VENUE. | O8: DONE.
A9: VISHAL MARKETING & COMPANY | B9: S/25-26/949 | C9: 45885 | D9: =IF(C9=0," ",TEXT(C9,"MMMM")) -> August | E9: =IF(C9=0," ",TEXT(C9,"YYYY")) -> 2025 | F9: U.S POLO | G9: 58 | H9: 127393 | I9: 181642 | J9: VISHAL MARKETING & CO(US POLO)-949.pdf | K9: AW'25 | L9: Uploaded In TEN | M9: TAS (HZB) Stock Transfer To JainSons (HZB). | N9: BOOKED IN VENUE. | O9: DONE.
A10: VISHAL MARKETING & COMPANY | B10: S/25-26/1023 | C10: 45888 | D10: =IF(C10=0," ",TEXT(C10,"MMMM")) -> August | E10: =IF(C10=0," ",TEXT(C10,"YYYY")) -> 2025 | F10: FLYING MACHINE | G10: 21 | H10: 25495 | I10: 37079 | J10: VISHAL MARKETING & CO(FM)-1023.pdf | K10: AW'25 | L10: Uploaded In TEN | M10: Product Received (Vaishnavi Deoghar). | N10: BOOKED IN VENUE. | O10: DONE.
A11: VISHAL MARKETING & COMPANY | B11: S/25-26/1024 | C11: 45888 | D11: =IF(C11=0," ",TEXT(C11,"MMMM")) -> August | E11: =IF(C11=0," ",TEXT(C11,"YYYY")) -> 2025 | F11: ARROW | G11: 68 | H11: 99668 | I11: 145932 | J11: VISHAL MARKETING & CO(ARROW)-1024.pdf | K11: AW'25 | L11: Uploaded In TEN | M11: Product Received (Lee Deoghar). | N11: BOOKED IN VENUE. | O11: DONE.
A12: VISHAL MARKETING & COMPANY | B12: S/25-26/999 | C12: 45888 | D12: =IF(C12=0," ",TEXT(C12,"MMMM")) -> August | E12: =IF(C12=0," ",TEXT(C12,"YYYY")) -> 2025 | F12: U.S POLO | G12: 127 | H12: 299595 | I12: 427173 | J12: VISHAL MARKETING & CO(US POLO)-999.pdf | K12: AW'25 | L12: Uploaded In TEN | M12: Deoghar Stock Transfer To Patna. | N12: BOOKED IN VENUE. | O12: DONE.
A13: VISHAL MARKETING & COMPANY | B13: S/25-26/1125 | C13: 45894 | D13: =IF(C13=0," ",TEXT(C13,"MMMM")) -> August | E13: =IF(C13=0," ",TEXT(C13,"YYYY")) -> 2025 | F13: U.S POLO | G13: 100 | H13: 235862 | I13: 336300 | J13: VISHAL MARKETING & CO(US POLO)-1125.pdf | K13: AW'25 | L13: Uploaded In TEN | M13: Product Received (Lee Deoghar). | N13: BOOKED IN "DB". | O13: PENDING.
A14: VISHAL MARKETING & COMPANY | B14: S/25-26/1126 | C14: 45894 | D14: =IF(C14=0," ",TEXT(C14,"MMMM")) -> August | E14: =IF(C14=0," ",TEXT(C14,"YYYY")) -> 2025 | F14: U.S POLO | G14: 125 | H14: 266072 | I14: 379375 | J14: VISHAL MARKETING & CO(US POLO)-1126.pdf | K14: AW'25 | L14: Uploaded In TEN | M14: Product Received (Lee Deoghar). | N14: BOOKED IN "DB". | O14: PENDING.
... A41: VISHAL MARKETING & COMPANY | B41: S/25-26/1577 | C41: 45925 | D41: =IF(C41=0," ",TEXT(C41,"MMMM")) -> September | E41: =IF(C41=0," ",TEXT(C41,"YYYY")) -> 2025 | F41: U.S POLO | G41: 131 | H41: 273563 | I41: 428940 | J41: VISHAL MARKETING & CO(US POLO)-1577.pdf | K41: AW'25 | L41: Uploaded In TEN | M41: Stock Transfered 66 Units Lee Deoghar, 28 Units USPA & SPYKAR, & 37 Units Allen Solly Gaya. | N41: BOOKED IN VENUE. | O41: PENDING.
A42: VISHAL MARKETING & COMPANY | B42: S/25-26/2122 | C42: 45954 | D42: =IF(C42=0," ",TEXT(C42,"MMMM")) -> October | E42: =IF(C42=0," ",TEXT(C42,"YYYY")) -> 2025 | F42: ARROW | G42: 78 | H42: 331393 | I42: 504793 | J42: VISHAL MARKETING & CO(ARROW)-2122.pdf | K42: AW'25 | L42: Uploaded In TEN | N42: BOOKED IN VENUE. | O42: PENDING.
A43: VISHAL MARKETING & COMPANY | B43: S/25-26/2142 | C43: 45955 | D43: =IF(C43=0," ",TEXT(C43,"MMMM")) -> October | E43: =IF(C43=0," ",TEXT(C43,"YYYY")) -> 2025 | F43: ARROW | G43: 17 | H43: 75849 | I43: 113768 | J43: VISHAL MARKETING & CO(ARROW)-2142.pdf | K43: AW'25 | L43: Uploaded In TEN | N43: BOOKED IN VENUE. | O43: PENDING.
A44: VISHAL MARKETING & COMPANY | B44: S/25-26/2329 | C44: 45788 | D44: =IF(C44=0," ",TEXT(C44,"MMMM")) -> May | E44: =IF(C44=0," ",TEXT(C44,"YYYY")) -> 2025 | F44: ARROW | G44: 53 | H44: 175689 | I44: 268394 | J44: VISHAL MARKETING & CO(ARROW)-2329.pdf | K44: AW'25 | L44: Uploaded In TEN | N44: BOOKED IN VENUE. | O44: PENDING.
A45: VISHAL MARKETING & COMPANY | B45: S/25-26/2453 | C45: 45972 | D45: =IF(C45=0," ",TEXT(C45,"MMMM")) -> November | E45: =IF(C45=0," ",TEXT(C45,"YYYY")) -> 2025 | F45: ARROW | G45: 105 | H45: 321032 | I45: 496227 | J45: VISHAL MARKETING & CO(ARROW)-2453.pdf | K45: AW'25 | L45: Uploaded In TEN | N45: BOOKED IN VENUE. | O45: PENDING.
A46: VISHAL MARKETING & COMPANY | B46: S/25-26/2622 | C46: 45982 | D46: =IF(C46=0," ",TEXT(C46,"MMMM")) -> November | E46: =IF(C46=0," ",TEXT(C46,"YYYY")) -> 2025 | F46: ARROW | G46: 92 | H46: 418516 | I46: 630993 | J46: VISHAL MARKETING & CO(ARROW)-2622.pdf | K46: AW'25 | L46: Uploaded In TEN | N46: BOOKED IN VENUE. | O46: PENDING.
A47: VISHAL MARKETING & COMPANY | B47: S/25-26/2145 | C47: 45955 | D47: =IF(C47=0," ",TEXT(C47,"MMMM")) -> October | E47: =IF(C47=0," ",TEXT(C47,"YYYY")) -> 2025 | F47: FLYING MACHINE | G47: 27 | H47: 49713 | I47: 75410 | J47: VISHAL MARKETING & CO(FM)-2145.pdf | K47: AW'25 | L47: Uploaded In TEN | M47: Product Received (Vaishnavi Deoghar). | N47: BOOKED IN VENUE. | O47: PENDING.
A48: VISHAL MARKETING & COMPANY | B48: S/25-26/2480 | C48: 45973 | D48: =IF(C48=0," ",TEXT(C48,"MMMM")) -> November | E48: =IF(C48=0," ",TEXT(C48,"YYYY")) -> 2025 | F48: FLYING MACHINE | G48: 21 | H48: 86759 | I48: 129778 | J48: VISHAL MARKETING & CO(FM)-2480.pdf | K48: AW'25 | L48: Uploaded In TEN | M48: Product Received (Vaishnavi Deoghar). | N48: BOOKED IN VENUE. | O48: PENDING.
A49: VISHAL MARKETING & COMPANY | B49: S/25-26/1578 | C49: 45925 | D49: =IF(C49=0," ",TEXT(C49,"MMMM")) -> September | E49: =IF(C49=0," ",TEXT(C49,"YYYY")) -> 2025 | F49: U.S POLO | G49: 79 | H49: 164885 | I49: 253053 | J49: VISHAL MARKETING & CO(US POLO)-1578.pdf | K49: AW'25 | L49: Uploaded In TEN | M49: Product Received (Vaishnavi Deoghar). | N49: BOOKED IN VENUE. | O49: PENDING.
A50: VISHAL MARKETING & COMPANY | B50: S/25-26/1579 | C50: 45925 | D50: =IF(C50=0," ",TEXT(C50,"MMMM")) -> September | E50: =IF(C50=0," ",TEXT(C50,"YYYY")) -> 2025 | F50: U.S POLO | G50: 94 | H50: 203236 | I50: 320182 | J50: VISHAL MARKETING & CO(US POLO)-1579.pdf | K50: AW'25 | L50: Uploaded In TEN | M50: Product Received (Vaishnavi Deoghar). | N50: BOOKED IN VENUE. | O50: PENDING.
A51: VISHAL MARKETING & COMPANY | B51: S/25-26/1786 | C51: 45818 | D51: =IF(C51=0," ",TEXT(C51,"MMMM")) -> June | E51: =IF(C51=0," ",TEXT(C51,"YYYY")) -> 2025 | F51: U.S POLO | G51: 21 | H51: 41043 | I51: 67301 | J51: VISHAL MARKETING & CO(US POLO)-1786.pdf | K51: AW'25 | L51: Uploaded In TEN | M51: Product Received (Vaishnavi Deoghar). | N51: BOOKED IN VENUE. | O51: PENDING.
A52: VISHAL MARKETING & COMPANY | B52: S/25-26/2068 | C52: 45948 | D52: =IF(C52=0," ",TEXT(C52,"MMMM")) -> October | E52: =IF(C52=0," ",TEXT(C52,"YYYY")) -> 2025 | F52: U.S POLO | G52: 38 | H52: 90981 | I52: 139434 | J52: VISHAL MARKETING & CO(US POLO)-2068.pdf | K52: AW'25 | L52: Uploaded In TEN | M52: Product Received (Vaishnavi Deoghar). | N52: BOOKED IN VENUE. | O52: PENDING.
A53: VISHAL MARKETING & COMPANY | B53: S/25-26/2070 | C53: 45948 | D53: =IF(C53=0," ",TEXT(C53,"MMMM")) -> October | E53: =IF(C53=0," ",TEXT(C53,"YYYY")) -> 2025 | F53: U.S POLO | G53: 22 | H53: 55308 | I53: 86600 | J53: VISHAL MARKETING & CO(US POLO)-2070.pdf | K53: AW'25 | L53: Uploaded In TEN | M53: Product Received (Vaishnavi Deoghar). | N53: BOOKED IN VENUE. | O53: PENDING.
A54: VISHAL MARKETING & COMPANY | B54: S/25-26/2090 | C54: 45948 | D54: =IF(C54=0," ",TEXT(C54,"MMMM")) -> October | E54: =IF(C54=0," ",TEXT(C54,"YYYY")) -> 2025 | F54: U.S POLO | G54: 82 | H54: 315698 | I54: 469764 | J54: VISHAL MARKETING & CO(US POLO)-2090.pdf | K54: AW'25 | L54: Uploaded In TEN | M54: Product Received (Vaishnavi Deoghar). | N54: BOOKED IN VENUE. | O54: PENDING.
A55: VISHAL MARKETING & COMPANY | B55: S/25-26/2144 | C55: 45955 | D55: =IF(C55=0," ",TEXT(C55,"MMMM")) -> October | E55: =IF(C55=0," ",TEXT(C55,"YYYY")) -> 2025 | F55: U.S POLO | G55: 14 | H55: 26359 | I55: 43223 | J55: VISHAL MARKETING & CO(US POLO)-2144.pdf | K55: AW'25 | L55: Uploaded In TEN | M55: Product Received (Vaishnavi Deoghar). | N55: BOOKED IN VENUE. | O55: PENDING.
A56: VISHAL MARKETING & COMPANY | B56: S/25-26/2263 | C56: 45668 | D56: =IF(C56=0," ",TEXT(C56,"MMMM")) -> January | E56: =IF(C56=0," ",TEXT(C56,"YYYY")) -> 2025 | F56: U.S POLO | G56: 151 | H56: 390079 | I56: 617444 | J56: VISHAL MARKETING & CO(US POLO)-2263.pdf | K56: AW'25 | L56: Uploaded In TEN | M56: Product Received (Vaishnavi Deoghar). | N56: BOOKED IN VENUE. | O56: PENDING.
A57: VISHAL MARKETING & COMPANY | B57: S/25-26/2264 | C57: 45668 | D57: =IF(C57=0," ",TEXT(C57,"MMMM")) -> January | E57: =IF(C57=0," ",TEXT(C57,"YYYY")) -> 2025 | F57: U.S POLO | G57: 103 | H57: 220372 | I57: 350293 | J57: VISHAL MARKETING & CO(US POLO)-2264.pdf | K57: AW'25 | L57: Uploaded In TEN | M57: Product Received (Vaishnavi Deoghar). | N57: BOOKED IN VENUE. | O57: PENDING.
A58: VISHAL MARKETING & COMPANY | B58: S/25-26/2284 | C58: 45668 | D58: =IF(C58=0," ",TEXT(C58,"MMMM")) -> January | E58: =IF(C58=0," ",TEXT(C58,"YYYY")) -> 2025 | F58: U.S POLO | G58: 33 | H58: 68625 | I58: 111121 | J58: VISHAL MARKETING & CO(US POLO)-2284.pdf | K58: AW'25 | L58: Uploaded In TEN | M58: Product Received (Vaishnavi Deoghar). | N58: BOOKED IN VENUE. | O58: PENDING.
... A69: VISHAL MARKETING & COMPANY | B69: S/302 | C69: 45980 | D69: =IF(C69=0," ",TEXT(C69,"MMMM")) -> November | E69: =IF(C69=0," ",TEXT(C69,"YYYY")) -> 2025 | F69: LINEN CLUB | G69: 21 | H69: 48327 | I69: 81102 | J69: VISHAL MARKETING & CO(LINEN CLUB)-302.pdf | K69: AW'25 | L69: Uploaded In TEN | M69: Product Received at Ranchi(WH), Stock Transfered 03 Units Vaishnavi Banka, 06 Units Vaishnavi Ratu, & 21 Units KDPS Bokaro. | N69: BOOKED IN VENUE. | O69: PENDING.
D70: =IF(C70=0," ",TEXT(C70,"MMMM")) | E70: =IF(C70=0," ",TEXT(C70,"YYYY"))
D71: =IF(C71=0," ",TEXT(C71,"MMMM")) | E71: =IF(C71=0," ",TEXT(C71,"YYYY"))
D72: =IF(C72=0," ",TEXT(C72,"MMMM")) | E72: =IF(C72=0," ",TEXT(C72,"YYYY"))
D73: =IF(C73=0," ",TEXT(C73,"MMMM")) | E73: =IF(C73=0," ",TEXT(C73,"YYYY"))
D74: =IF(C74=0," ",TEXT(C74,"MMMM")) | E74: =IF(C74=0," ",TEXT(C74,"YYYY"))
D75: =IF(C75=0," ",TEXT(C75,"MMMM")) | E75: =IF(C75=0," ",TEXT(C75,"YYYY"))
D76: =IF(C76=0," ",TEXT(C76,"MMMM")) | E76: =IF(C76=0," ",TEXT(C76,"YYYY"))
D77: =IF(C77=0," ",TEXT(C77,"MMMM")) | E77: =IF(C77=0," ",TEXT(C77,"YYYY"))
D78: =IF(C78=0," ",TEXT(C78,"MMMM")) | E78: =IF(C78=0," ",TEXT(C78,"YYYY"))
D79: =IF(C79=0," ",TEXT(C79,"MMMM")) | E79: =IF(C79=0," ",TEXT(C79,"YYYY"))
D80: =IF(C80=0," ",TEXT(C80,"MMMM")) | E80: =IF(C80=0," ",TEXT(C80,"YYYY"))
D81: =IF(C81=0," ",TEXT(C81,"MMMM")) | E81: =IF(C81=0," ",TEXT(C81,"YYYY"))
... D1001: =IF(C1001=0," ",TEXT(C1001,"MMMM")) | E1001: =IF(C1001=0," ",TEXT(C1001,"YYYY"))

Sheet OFFER DETAILS.
A1: Brand Name | B1: Offer Type | C1: Season | D1: Offer Details | E1: Offer Starting Date | F1: Offer Closing Date | G1: Offer Status | H1: Offer Artwork
A2: U. S. POLO | B2: GWP | C2: AW'25 | D2: BUY 7999/- & GET A DUFFEL BAG WORTH 4999/- FOR 499/- | E2: 45906 | F2: 45940 | G2: CLOSED | H2: US POLO AW'25 GWP OFFER ARTWORK.pdf
A3: U. S. POLO | B3: GWP | C3: AW'25 | D3: BUY 10999/- & GET A BACKPACK WORTH 6999/- FOR 699/- | E3: 45906 | F3: 45940 | G3: CLOSED
A4: U. S. POLO | B4: GWP | C4: AW'25 | D4: BUY 16999/- & GET A TROLLEY WORTH 7999/- FOR 799/- | E4: 45906 | F4: 45940 | G4: CLOSED
A5: U. S. POLO KIDS | B5: GWP | C5: AW'25 | D5: BUY 5999/- & GET A SCHOOL BAG WORTH 3995/- FOR 499/- | E5: 45906 | F5: 45940 | G5: CLOSED | H5: US POLO KIDS AW'25 GWP OFFER ARTWORK.pdf
A6: U. S. POLO KIDS | B6: GWP | C6: AW'25 | D6: BUY 7999/- & GET A SCHOOL BAG + TIFFIN CASE WORTH 4995/- FOR 699/- | E6: 45906 | F6: 45940 | G6: CLOSED
A7: U. S. POLO KIDS | B7: GWP | C7: AW'25 | D7: BUY 10999/- & GET A TROLLY WORTH 7995/- FOR 799/- | E7: 45906 | F7: 45940 | G7: CLOSED
A8: FLYING MACHINE | B8: ATV | C8: AW'25 | D8: BUY 14999/- GET 3000/- 0FF | E8: 45908 | F8: 45961 | G8: CLOSED | H8: FM ATV OFFER AW'25 ARTWORK.pdf
A9: FLYING MACHINE | B9: ATV | C9: AW'25 | D9: BUY 10999/- GET 2000/- 0FF | E9: 45908 | F9: 45961 | G9: CLOSED
A10: FLYING MACHINE | B10: ATV | C10: AW'25 | D10: BUY 5999/- GET 1000/- 0FF | E10: 45908 | F10: 45961 | G10: CLOSED
A11: ARROW | B11: ATV | C11: AW'25 | D11: BUY 16999/- GET 3000/- 0FF | E11: 45908 | F11: 45961 | G11: CLOSED | H11: ARROW ATV OFFER AW'25 ARTWORK.pdf
A12: ARROW | B12: ATV | C12: AW'25 | D12: BUY 12999/- GET 2000/- 0FF | E12: 45908 | F12: 45961 | G12: CLOSED
A13: ARROW | B13: ATV | C13: AW'25 | D13: BUY 6999/- GET 1000/- 0FF | E13: 45908 | F13: 45961 | G13: CLOSED
A14: LINEN CLUB | B14: ATV | C14: AW'25 | D14: BUY 2 GET 750/- OFF | E14: 45903 | F14: 46134 | G14: CLOSED | H14: LINEN CLUB ATV OFFER AW'25 ARTWORK.pdf
A15: LINEN CLUB | B15: ATV | C15: AW'25 | D15: BUY 3 GET 1250/- OFF | E15: 45903 | F15: 46134 | G15: CLOSED
A16: LINEN CLUB | B16: ATV | C16: AW'25 | D16: BUY 4 GET 2000/- OFF | E16: 45903 | F16: 46134 | G16: CLOSED
A17: U. S. POLO | B17: ATV | C17: AW'25 | D17: BUY 16999/- GET 3000/- 0FF | E17: 45941 | F17: 46001 | G17: CLOSED | H17: US POLO AW'25 ATV OFFER ARTWORK.pdf
A18: U. S. POLO | B18: ATV | C18: AW'25 | D18: BUY 12999/- GET 2000/- 0FF | E18: 45941 | F18: 46001 | G18: CLOSED
A19: U. S. POLO | B19: ATV | C19: AW'25 | D19: BUY 7999/- GET 1000/- 0FF | E19: 45941 | F19: 46001 | G19: CLOSED
A20: U. S. POLO KIDS | B20: ATV | C20: AW'25 | D20: BUY 10999/- GET 2000/- 0FF | E20: 45941 | F20: 45961 | G20: CLOSED | H20: US POLO KIDS AW'25 ATV OFFER ARTWORK.pdf
A21: U. S. POLO KIDS | B21: ATV | C21: AW'25 | D21: BUY 6999/- GET 1000/- 0FF | E21: 45941 | F21: 45961 | G21: CLOSED
A22: U. S. POLO KIDS | B22: ATV | C22: AW'25 | D22: BUY 3999/- GET 500/- 0FF | E22: 45941 | F22: 45961 | G22: CLOSED
A23: ARROW | B23: ATV | C23: AW'25 | D23: BUY 14999/- GET 3000/- 0FF | E23: 45962 | F23: 46001 | G23: CLOSED | H23: ARROW 2ND ATV OFFER AW'25 ARTWORK.pdf
A24: ARROW | B24: ATV | C24: AW'25 | D24: BUY 10999/- GET 2000/- 0FF | E24: 45962 | F24: 46001 | G24: CLOSED
A25: ARROW | B25: ATV | C25: AW'25 | D25: BUY 6999/- GET 1000/- 0FF | E25: 45962 | F25: 46001 | G25: CLOSED
A26: FLYING MACHINE | B26: ATV | C26: AW'25 | D26: BUY 10999/- GET 2000/- 0FF | E26: 45962 | F26: 46001 | G26: CLOSED | H26: FM ATV OFFER 2ND AW'25 ARTWORK.pdf
A27: FLYING MACHINE | B27: ATV | C27: AW'25 | D27: BUY 5999/- GET 1000/- 0FF | E27: 45962 | F27: 46001 | G27: CLOSED
A28: FLYING MACHINE | B28: ATV | C28: AW'25 | D28: BUY 3999/- GET 500/- 0FF | E28: 45962 | F28: 46001 | G28: CLOSED
A29: U. S. POLO KIDS | B29: ATV | C29: AW'25 | D29: BUY 10999/- GET 2000/- 0FF | E29: 45962 | F29: 46001 | G29: CLOSED | H29: US POLO KIDS 2ND AW'25 ATV OFFER ARTWORK.pdf
A30: U. S. POLO KIDS | B30: ATV | C30: AW'25 | D30: BUY 5999/- GET 1000/- 0FF | E30: 45962 | F30: 46001 | G30: CLOSED
A31: U. S. POLO KIDS | B31: ATV | C31: AW'25 | D31: BUY 3999/- GET 500/- 0FF | E31: 45962 | F31: 46001 | G31: CLOSED
A32: SPYKAR | B32: ATV | C32: AW'25 | D32: BUY 14999/- GET 20% 0FF , BUY 7999/- GET 15% 0FF | E32: 45924 | F32: 45988 | G32: CLOSED | H32: SPYKAR AW'25 ATV OFFER ARTWORK.pdf
A33: SPYKAR | B33: ATV | C33: AW'25 | D33: MEN'S B2G2 OR BUY 2 GET 30% OFF, BUY 1 GET 20% OFF | E33: 45989 | F33: 45991 | G33: CLOSED | H33: SPYKAR AW'25 BLACK FRIDAY MEN'S ARTWORK.pdf
A34: SPYKAR | B34: ATV | C34: AW'25 | D34: WOMEN'S B2G2 OR BUY 2 GET 30% OFF, BUY 1 GET 20% OFF | E34: 45989 | F34: 45991 | G34: CLOSED | H34: SPYKAR AW'25 BLACK FRIDAY WOMEN'S ARTWORK.pdf
A35: SPYKAR | B35: ATV | C35: AW'25 | D35: MEN'S BUY 4 GET 40% OFF, BUY 2 GET 30% OFF, BUY 1 GET 20% OFF | E35: 45992 | F35: 46001 | G35: CLOSED | H35: SPYKAR MEN'S AW'25 2ND ATV OFFER ARTWORK.pdf
A36: SPYKAR | B36: ATV | C36: AW'25 | D36: WOMEN'S BUY 4 GET 40% OFF, BUY 2 GET 30% OFF, BUY 1 GET 20% OFF | E36: 45992 | F36: 46001 | G36: CLOSED | H36: SPYKAR WOMENS AW'25 2ND ATV OFFER ARTWORK.pdf
A37: LINEN CLUB | B37: EOSS | C37: AW'25 | D37: B1-20%, B2-30%, OR B3 & ABOVE 40% | E37: 45999 | F37: 46009 | G37: CLOSED | H37: LINEN CLUB AW'25 EOSS OFFER ARTWORK..pdf
A38: FLYING MACHINE | B38: EOSS | C38: AW'25 | D38: BUY 1-20% & BUY-2-30% | E38: 46002 | F38: 46009 | G38: CLOSED | H38: FM EOSS OFFER AW'25 ARTWORK.pdf
A39: SPYKAR | B39: EOSS | C39: AW'25 | D39: MEN'S BUY 1 GET 30% OFF, BUY 2 GET 40% OFF & BUY 4 GET 50% OFF | E39: 46002 | F39: 46015 | G39: CLOSED | H39: SPYKAR MEN EOSS OFFER B4G50, B2G40, B1G30 ARTWORK.pdf
A40: SPYKAR | B40: EOSS | C40: AW'25 | D40: WOMEN'S BUY 1 GET 40% OFF, BUY 2 GET 50% OFF | E40: 46002 | F40: 46015 | G40: CLOSED | H40: SPYKAR WOMEN EOSS OFFER B2G50, B1G40 ARTWORK.pdf
A41: U. S. POLO | B41: EOSS | C41: AW'25 | D41: B1-20% & B2-30% | E41: 46003 | F41: 46009 | G41: CLOSED | H41: US POLO B1@20%, B2 @30% ARTWORK AW'25.pdf
A42: U. S. POLO KIDS | B42: EOSS | C42: AW'25 | D42: B1-20% & B2-30% | E42: 46003 | F42: 46009 | G42: CLOSED | H42: US POLO KIDS B1@20%, B2 @30% ARTWORK AW'25.pdf
A43: ARROW | B43: EOSS | C43: AW'25 | D43: B1-20% & B2-30% | E43: 46003 | F43: 46009 | G43: CLOSED | H43: ARROW B1@20%, B2 @30% ARTWORK AW'25.pdf
... A53: SPYKAR | B53: EOSS | C53: AW'25 | D53: MEN'S BUY 1 GET 40% OFF & BUY 3 GET 50% OFF | E53: 46016 | F53: 46027 | G53: CLOSED | H53: SPYKAR MEN'S EOSS OFFER B3G50, B1G40 ARTWORK..pdf
A54: LINEN CLUB | B54: EOSS | C54: AW'25 | D54: BUY 1 - 25%, BUY 2 - 40%, & BUY 3 - 50% | E54: 46016 | F54: 46055 | G54: CLOSED | H54: LINEN CLUB AW'25 EOSS 3RD OFFER ARTWORK..pdf | I54: NSV - 24lakh 1% 28lakh 2% 34lakh 3% | J54: Deo 1staff
A55: U. S. POLO | B55: EOSS | C55: AW'25 | D55: B1-20%, B2-30%, B3-40% | E55: 46026 | F55: 46030 | G55: CLOSED | H55: US POLO B1-20%, B2-30%, B3-40% ARTWORK.pdf
A56: ARROW | B56: EOSS | C56: AW'25 | D56: B1-20%, B2-30%, B3-40%, (SU#BZ Flat-30%) | E56: 46026 | F56: 46030 | G56: CLOSED | H56: ARROW B1-20%, B2-30%, B3-40% ARTWORK AW'25.pdf
A57: U. S. POLO KIDS | B57: EOSS | C57: AW'25 | D57: B1-20%, B2-30%, B3-40% | E57: 46026 | F57: 46030 | G57: CLOSED | H57: US POLO KIDS B1-20%, B2-30%, B3-40% ARTWORK.pdf
A58: FLYING MACHINE | B58: EOSS | C58: AW'25 | D58: B1-30%, B2-40% | E58: 46026 | F58: 46030 | G58: CLOSED | H58: FM B1-30%, B2-40% ARTWORK.pdf
A59: SPYKAR | B59: EOSS | C59: AW'25 | D59: MEN'S BUY 2 GET 50% OFF & BUY 1 GET 40% OFF | E59: 46028 | F59: 46050 | G59: CLOSED | H59: SPYKAR MEN'S EOSS OFFER B2G50, B1G40 ARTWORK..pdf
A60: ARROW | B60: EOSS | C60: AW'25 | D60: B1-20%, B2-30%, B2-G2 (SU#BZ Flat-30%) | E60: 46031 | F60: 46037 | G60: CLOSED | H60: ARROW B1-20%, B2-30%, B2-G2 ARTWORK AW'25..pdf
A61: FLYING MACHINE | B61: EOSS | C61: AW'25 | D61: B1 20, B1-G1 | E61: 46031 | F61: 46037 | G61: CLOSED | H61: FM B1-20%, B1-G1 AW'25 EOSS ARTWOEK..pdf
A62: U. S. POLO | B62: EOSS | C62: AW'25 | D62: B1-20%, B2-30%, B2-G2 | E62: 46031 | F62: 46037 | G62: CLOSED | H62: US POLO B1-20%, B2-30%, B2-G2 ARTWORK..pdf
A63: U. S. POLO KIDS | B63: EOSS | C63: AW'25 | D63: B1-20%, B2-30%, B3-40% | E63: 46031 | F63: 46037 | G63: CLOSED | H63: US POLO KIDS B1-20%, B2-30%, B3-40% ARTWORK.pdf
A64: ARROW | B64: EOSS | C64: AW'25 | D64: B1-30%, B2-40%, B2-G2, (SU#BZ Flat-40%) | E64: 46038 | F64: 46044 | G64: CLOSED | H64: ARROW B1-30, B2-40, B2-G2 ARTWORK..pdf
A65: FLYING MACHINE | B65: EOSS | C65: AW'25 | D65: B1 20, B1-G1 | E65: 46038 | F65: 46044 | G65: CLOSED | H65: FM B1-20%, B1-G1 AW'25 EOSS ARTWOEK..pdf
A66: U. S. POLO | B66: EOSS | C66: AW'25 | D66: B1-30%, B2-40%, B2-G2 | E66: 46038 | F66: 46044 | G66: CLOSED | H66: US POLO B1-30, B2-40, B2-G2 ARTWORK..pdf
... A91: SPYKAR | B91: ATV | C91: SS'26 | D91: WOMEN'S BUY 4999/- GET 1000/- OFF & BUY 2999/- GET 500/- OFF | E91: 46080 | F91: 46169 | G91: CLOSED | H91: SPYKAR WOMEN'S 1000 to 4999, 500 to 2999.pdf
A92: ARROW | B92: ATV | C92: SS'26 | D92: BUY 4999/- & GET 500/-, BUY 6999/- & GET 1000/-, BUY 12999/- & GET 2000/-, BUY 16999/- & GET 3000/- | E92: 46084 | F92: Not Disclosed Yet. | G92: STILL RUNNING | H92: ARROW ATV SS'26.pdf
A93: U. S. POLO | B93: GWP | C93: SS'26 | D93: BUY 8999/- & GET A BACKPACK WORTH 4999/- FOR 499/- | E93: 46129 | F93: Not Disclosed Yet. | G93: STILL RUNNING | H93: US POLO GWP OFFER SS'26.pdf
A94: U. S. POLO | B94: GWP | C94: SS'26 | D94: BUY 11999/- & GET A DUFFEL BAG WORTH 6999/- FOR 699/- | E94: 46129 | F94: Not Disclosed Yet. | G94: STILL RUNNING
A95: U. S. POLO | B95: GWP | C95: SS'26 | D95: BUY 19999/- & GET A TROLLEY WORTH 8999/- FOR 899/- | E95: 46129 | F95: Not Disclosed Yet. | G95: STILL RUNNING | H95: ARTWORK NOT RECEIVED
A96: U. S. POLO KIDS | B96: GWP | C96: SS'26 | D96: BUY 7995/- & GET A BACKPACK WORTH 4999/- FOR 599/- | E96: 46129 | F96: Not Disclosed Yet. | G96: STILL RUNNING | H96: US POLO KIDS GWP OFFER SS'26.pdf
A97: U. S. POLO KIDS | B97: GWP | C97: SS'26 | D97: BUY 12995/- & GET A TROLLEY WORTH 7999/- FOR 799/- | E97: 46129 | F97: Not Disclosed Yet. | G97: STILL RUNNING
A98: FLYING MACHINE | B98: ATV | C98: SS'26 | D98: BUY 4999/- GET 500/- OFF & BUY 6999/- GET 1000/- OFF | E98: 46129 | F98: Not Disclosed Yet. | G98: STILL RUNNING | H98: FLYING MACHINE ATV OFFER SS'26.pdf
A99: LINEN CLUB | B99: ATV | C99: SS'26 | D99: BUY 2 GET 1000/- OFF, BUY 3 GET 1500/- OFF & BUY 4 GET 2000/- OFF | E99: 46135 | F99: 46183 | G99: CLOSED | H99: LINEN CLUB SS'26 ATV OFFER ARTWORK.pdf
A100: SPYKAR | B100: ATV | C100: SS'26 | D100: BUY 3 DENIMS IN KANO/SUPPER SKINNY/SKINNY FIT (MRR RS.2999 & ABOVE) & GET RS.2000 | E100: 46157 | F100: 46169 | G100: CLOSED | H100: SPYKAR DENIM OFFER SS'26.pdf
A101: SPYKAR | B101: ATV | C101: SS'26 | D101: BUY 2 DENIMS IN KANO/SUPPER SKINNY/SKINNY FIT (MRR RS.2999 & ABOVE) & GET RS.1200 | E101: 46157 | F101: 46169 | G101: CLOSED
A102: SPYKAR | B102: ATV | C102: SS'26 | D102: BUY 1 DENIMS IN KANO/SUPPER SKINNY/SKINNY FIT (MRR RS.2999 & ABOVE) & GET RS.500 | E102: 46157 | F102: 46169 | G102: CLOSED
A103: SPYKAR | B103: EOSS | C103: SS'26 | D103: BUY 2 GET 1 FREE & BUY 1 & GET 20% OFF | E103: 46170 | F103: 46184 | G103: CLOSED | H103: SPYKAR MENS EOSS OFFER B2G1, B1@G20..pdf
A104: LINEN CLUB | B104: EOSS | C104: SS'26 | D104: BUY 1-30%,BUY 2-40% & B2G2 | E104: 46184 | F104: Not Disclosed Yet. | G104: STILL RUNNING | H104: LINEN CLUB SS'26 EOSS OFFER B2G2 & B2@40%.pdf
A105: SPYKAR | B105: EOSS | C105: SS'26 | D105: B1G1 & FLAT 40% | E105: 46184 | F105: Not Disclosed Yet. | G105: STILL RUNNING | H105: SPYKAR EOSS OFFER B1G1, Flat 40%.pdf

Sheet SUPPLIER DATA BASE
A1: PARTY NAME | B1: Location | C1: Brand Name | D1: Credit Days | E1: CD | F1: Agency Company | G1: Agent Name | H1: Agent Number | I1: Agency Accounts Name | J1: Accounts Desk Number | K1: Account Holder Name | L1: Bank Account | M1: IFSC Code
A2: A P TEXTILES | B2: - | C2: - | D2: - | E2: - | F2: - | G2: - | H2: - | I2: - | J2: - | K2: - | L2: - | M2: -
A3: AARI | B3: - | C3: - | D3: - | E3: - | F3: - | G3: - | H3: - | I3: - | J3: - | K3: - | L3: - | M3: -
A4: AARNA VENTURES PRIVATE LIMITED | B4: - | C4: - | D4: - | E4: - | F4: - | G4: - | H4: - | I4: - | J4: - | K4: - | L4: - | M4: -
A5: AAROHI FASHION | B5: - | C5: - | D5: - | E5: - | F5: - | G5: - | H5: - | I5: - | J5: - | K5: - | L5: - | M5: -
A6: AD EDGE (VH-KANK) | B6: - | C6: - | D6: - | E6: - | F6: - | G6: - | H6: - | I6: - | J6: - | K6: - | L6: - | M6: -
A7: ADITYA BIRLA | B7: - | C7: - | D7: - | E7: - | F7: - | G7: - | H7: - | I7: - | J7: - | K7: - | L7: - | M7: -
A8: ADITYA VISION LTD (JH) | B8: - | C8: - | D8: - | E8: - | F8: - | G8: - | H8: - | I8: - | J8: - | K8: - | L8: - | M8: -
A9: AGWANI FASHION | B9: - | C9: SUCCESS | D9: - | E9: - | F9: - | G9: - | H9: - | I9: - | J9: - | K9: - | L9: - | M9: -
A10: AJJAWAM DESIGNER PRIVATE LIMITED | B10: SURAT | C10: - | D10: NO | E10: - | F10: SURYAM TEXTILE AGENCY | G10: AKASH | H10: 91044 89871 | I10: - | J10: - | K10: AJJAWAM DESIGNER PRIVATE LIMITED | L10: 925020021188499 | M10: UTIB0004665
A11: ANAND FABRICS | B11: - | C11: - | D11: - | E11: - | F11: - | G11: - | H11: - | I11: - | J11: - | K11: - | L11: - | M11: -
A12: ARVIND LIMITED | B12: - | C12: - | D12: - | E12: - | F12: - | G12: - | H12: - | I12: - | J12: - | K12: - | L12: - | M12: -
... A14: ARVIND LIMITED (KAR) | B14: - | C14: - | D14: - | E14: - | F14: - | G14: - | H14: - | I14: - | J14: - | K14: - | L14: - | M14: -
A15: AS TEXTILE | B15: SURAT | C15: - | D15: 30 | E15: 0.09 | F15: SURYAM TEXTILE AGENCY | G15: AKASH | H15: 91044 89871 | I15: - | J15: - | K15: AS TEXTILE | L15: 50200012846193 | M15: HDFC0001249
A16: ASHMITA BOUTIQUE PVT. LTD. | B16: KOLKATA | C16: - | D16: 60 | E16: 0.03 | F16: NEPOLIAN | G16: MUKESH | H16: 9831451670 | I16: - | J16: - | K16: ASHMITA BOUTIQUE PVT. LTD. | L16: 627951000036 | M16: ICICI0006279
A17: B B FASHIONS | B17: - | C17: - | D17: - | E17: - | F17: - | G17: - | H17: - | I17: - | J17: - | K17: B B FASHIONS | L17: 4913058844 | M17: KKBK0004599
A18: B.K ENTERPRISES | B18: RANCHI | C18: LITTLE PINK | D18: - | E18: - | F18: - | G18: - | H18: - | I18: - | J18: - | K18: - | L18: - | M18: -
A19: B.K.SILK MILLS NX LLP | B19: SURAT | C19: - | D19: NO | E19: - | F19: SURYAM TEXTILE AGENCY | G19: AKASH | H19: 91044 89871 | I19: - | J19: - | K19: B.K.SILK MILLS NX LLP | L19: 58451000050 | M19: ICIC0000584
A20: BALTIC LEI INDIA PRIVATE LIMITED | B20: - | C20: - | D20: - | E20: - | F20: - | G20: - | H20: - | I20: - | J20: - | K20: - | L20: - | M20: -
A21: BANSAL TEXTILES | B21: - | C21: - | D21: - | E21: - | F21: - | G21: - | H21: - | I21: - | J21: - | K21: - | L21: - | M21: -
A22: BINOD KUMAR SINGHANIA | B22: - | C22: - | D22: - | E22: - | F22: - | G22: - | H22: - | I22: - | J22: - | K22: - | L22: - | M22: -
A23: BLAZO CLOTHING MANUFACTURING CO PVT LTD | B23: - | C23: BLAZO | D23: - | E23: - | F23: - | G23: - | H23: - | I23: - | J23: - | K23: - | L23: - | M23: -
A24: C2D VENTURES LLP | B24: DHANBAD | C24: WELSPUN, VAN HEUSEN | D24: 15 | E24: 5 | F24: DIRECT | G24: - | H24: - | I24: - | J24: - | K24: C2D VENTURES LLP | L24: 50484840037 | M24: IDIB000D600
A25: COMNET SOLUTIONS | B25: - | C25: - | D25: - | E25: - | F25: - | G25: - | H25: - | I25: - | J25: - | K25: - | L25: - | M25: -
A26: CRYSTAL BY TARUN DESIGN | B26: DELHI | C26: - | D26: - | E26: - | F26: - | G26: - | H26: - | I26: - | J26: - | K26: - | L26: - | M26: -
A27: D APPAREL | B27: RANCHI | C27: KHUSHAL/STATUS QUO | D27: - | E27: - | F27: - | G27: - | H27: - | I27: - | J27: - | K27: D APPAREL | L27: 722501010050397 | M27: UBIN0572250
A28: D D APPARELS | B28: RANCHI | C28: SWEET DREAMS | D28: NO | E28: - | F28: - | G28: - | H28: - | I28: - | J28: - | K28: D D APPARELS | L28: 029205007835 | M28: ICIC0000292
A29: D D DEVELOPER | B29: BHAGALPUR | C29: JOCKEY | D29: - | E29: - | F29: - | G29: - | H29: - | I29: - | J29: - | K29: - | L29: - | M29: -
A30: D D SALES CO | B30: RANCHI | C30: KILLER | D30: NO | E30: - | F30: - | G30: - | H30: - | I30: - | J30: - | K30: D D SALES CO | L30: 29205007835 | M30: ICIC0000292
A31: D S CREATION | B31: KOLKATA | C31: YES MAAM | D31: 60 | E31: 0.03 | F31: NEPOLIAN | G31: MUKESH | H31: 9831451670 | I31: - | J31: - | K31: D S CREATION | L31: 9830047013 | M31: KKBK0006562
A32: D.D.SALES CO | B32: RANCHI | C32: JOCKEY, KILLER, NEXTBIT | D32: - | E32: - | F32: - | G32: - | H32: - | I32: - | J32: - | K32: - | L32: - | M32: -
A33: D.S.CREATION | B33: - | D33: - | E33: - | F33: - | G33: - | H33: - | I33: - | J33: - | K33: - | L33: - | M33: -
A34: DAULAL NANDLAL | B34: - | C34: - | D34: - | E34: - | F34: - | G34: - | H34: - | I34: - | J34: - | K34: - | L34: - | M34: -
A35: DEVTA GARMENTS | B35: - | C35: - | D35: - | E35: - | F35: - | G35: - | H35: - | I35: - | J35: - | K35: - | L35: - | M35: -
A36: DHANVI RITIKA FASHION | B36: RANCHI | C36: SANSKAR | D36: - | E36: - | F36: - | G36: - | H36: - | I36: - | J36: - | K36: - | L36: - | M36: -
A37: DIL SE | B37: - | C37: - | D37: - | E37: - | F37: - | G37: - | H37: - | I37: - | J37: - | K37: DIL SE | L37: 11197610000574 | M37: HDFC0001119
A38: DIYA CREATION | B38: MUMBAI | C38: - | D38: 30 | E38: 0.05 | F38: - | G38: MAULIK AJMERA | H38: 9930050607 | I38: - | J38: - | K38: DIYA CREATION | L38: 199502000000874 | M38: IOBA0001995
A39: ELA DESIGNER PRIVATE LIMITED | B39: - | C39: - | D39: - | E39: - | F39: - | G39: - | H39: - | I39: - | J39: - | K39: - | L39: - | M39: -
A40: ELITE EDITION | B40: SURAT | C40: - | D40: 70 | E40: 0.1 | F40: SURYAM TEXTILE AGENCY | G40: AKASH | H40: 91044 89871 | I40: - | J40: - | K40: ELITE EDITION | L40: 183605501803 | M40: ICIC0001836
A41: EMPORIO SIDDHARTH SALES PRIVATE LIMITED | B41: PATNA | C41: GOCOLOURS | D41: 30 | E41: 0.02 | F41: - | G41: - | H41: - | I41: - | J41: - | K41: EMPORIO SIDDHARTH SALES PRIVATE LIMITED | L41: 50200111968638 | M41: HDFC000186
A42: EUROPE ONE | B42: SURAT | C42: - | D42: NO | E42: - | F42: SURYAM TEXTILE AGENCY | G42: AKASH | H42: 91044 89871 | I42: - | J42: - | K42: EUROPE ONE | L42: 5205505189 | M42: ICIC0000052
A43: EVERGREEN INDUSTRIES | B43: - | C43: - | D43: - | E43: - | F43: - | G43: - | H43: - | I43: - | J43: - | K43: - | L43: - | M43: -
A44: FASHION EARTH GARMENTS PVT LTD | B44: MUMBAI | C44: SEWBERRY | D44: - | E44: - | F44: - | G44: - | H44: - | I44: - | J44: - | K44: FASHION EARTH GARMENTS PVT LTD | L44: 59209830559685 | M44: HDFC0000219
A45: FASHION MARKETING | B45: - | C45: - | D45: - | E45: - | F45: - | G45: - | H45: - | I45: - | J45: - | K45: - | L45: - | M45: -
A46: FASHION STUDIO | B46: DEOGARH | C46: FS-DEO | D46: - | E46: - | F46: - | G46: - | H46: - | I46: - | J46: - | K46: - | L46: - | M46: -
A47: FASHION WORLD | B47: SURAT | C47: - | D47: - | E47: - | F47: SURYAM TEXTILE AGENCY | G47: AKASH | H47: 91044 89871 | I47: - | J47: - | K47: FASHION WORLD | L47: 9111902302 | M47: KKBK000284
A48: FASHION WORLD GARMENTS PVT LTD | B48: KOLKATA | C48: FW | D48: 60 | E48: 0.03 | F48: NEPOLIAN | G48: MUKESH | H48: 9831451670 | I48: - | J48: - | K48: FASHION WORLD GARMENTS PVT LTD | L48: 3613991079 | M48: KKBK0006584
A49: FINE TOUCH | B49: - | C49: - | D49: - | E49: - | F49: - | G49: - | H49: - | I49: - | J49: - | K49: - | L49: - | M49: -
A50: FIRE TRACE ENGINEERS | B50: - | C50: - | D50: - | E50: - | F50: - | G50: - | H50: - | I50: - | J50: - | K50: - | L50: - | M50: -
A51: FLAIR KIDS CAMP | B51: RANCHI | C51: PRETTY GIRL | D51: - | E51: - | F51: - | G51: - | H51: - | I51: - | J51: - | K51: FLAIR KIDS CAMP | L51: - | M51: -
A52: GAJENDRA OVERSEAS | B52: SURAT | C52: - | D52: NO | E52: - | F52: SURYAM TEXTILE AGENCY | G52: AKASH | H52: 91044 89871 | I52: - | J52: - | K52: GAJENDRA OVERSEAS | L52: 777705312611 | M52: ICIC0001387
A53: GALA CREATION | B53: - | C53: - | D53: - | E53: - | F53: - | G53: - | H53: - | I53: - | J53: - | K53: - | L53: - | M53: -
A54: GEETANSHI APPARELS | B54: RANCHI | C54: PEPPER MINT | D54: - | E54: - | F54: - | G54: - | H54: - | I54: - | J54: - | K54: GEETANSHI APPARELS | L54: 50200083410855 | M54: HDFC0005189
A55: GHARAUNDA | B55: - | C55: - | D55: - | E55: - | F55: - | G55: - | H55: - | I55: - | J55: - | K55: - | L55: - | M55: -
A56: GHASIRAM TEXTOFIN PVT LTD | B56: KOLKATA | C56: - | D56: - | E56: - | F56: - | G56: - | H56: - | I56: - | J56: - | K56: - | L56: - | M56: -
A57: GHASIRAMTEX | B57: - | C57: - | D57: - | E57: - | F57: - | G57: - | H57: - | I57: - | J57: - | K57: - | L57: - | M57: -
A58: GODDA CONSTRUCTION TILES | B58: - | C58: - | D58: - | E58: - | F58: - | G58: - | H58: - | I58: - | J58: - | K58: - | L58: - | M58: -
A59: GOMTEE FASHIONS LLP | B59: - | C59: - | D59: - | E59: - | F59: - | G59: - | H59: - | I59: - | J59: - | K59: - | L59: - | M59: -
A60: GTN ENGINEERING INDIA LTD | B60: - | C60: - | D60: - | E60: - | F60: - | G60: - | H60: - | I60: - | J60: - | K60: GTN ENGINEERING INDIA LTD | L60: 4437002100000153 | M60: PUNB0020700
... A64: INDRA VALUES | B64: - | C64: - | D64: - | E64: - | F64: - | G64: - | H64: - | I64: - | J64: - | K64: - | L64: - | M64: -
A65: ISHANA FASHION LLP | B65: KOLKATA | C65: ISHANA | D65: 60 | E65: 0.03 | F65: NEPOLIAN | G65: MUKESH | H65: 9831451670 | I65: - | J65: - | K65: ISHANA FASHION LLP | L65: 99999830093861 | M65: HDFC0000219
A66: J.V. PLASTIC INDUSTRIES INDIA PVT LTD | B66: - | C66: - | D66: - | E66: - | F66: - | G66: - | H66: - | I66: - | J66: - | K66: - | L66: - | M66: -
A67: JAI MATA DI FASHION | B67: - | C67: - | D67: - | E67: - | F67: - | G67: - | H67: - | I67: - | J67: - | K67: - | L67: - | M67: -
A68: JAIN ADISHWAR HOSIERY WORKS LLP | B68: RANCHI | C68: - | D68: - | E68: - | F68: - | G68: - | H68: - | I68: - | J68: - | K68: JAIN ADISHWAR HOSIERY WORKS LLP | L68: 99917644444444 | M68: HDFC0002063
A69: JAIN RETAIL | B69: - | C69: - | D69: - | E69: - | F69: - | G69: - | H69: - | I69: - | J69: - | K69: - | L69: - | M69: -
A70: JAY AMBEY SAREES | B70: SURAT | C70: - | D70: NO | E70: - | F70: SURYAM TEXTILE AGENCY | G70: AKASH | H70: 91044 89871 | I70: - | J70: - | K70: JAY AMBEY SAREES | L70: 50200027562802 | M70: HDFC0009027
A71: JAY AMBEY SILK MILLS | B71: SURAT | C71: - | D71: 70 | E71: 5% IN BILL | F71: SURYAM TEXTILE AGENCY | G71: AKASH | H71: 91044 89871 | I71: - | J71: - | K71: JAY AMBEY SILK MILLS | L71: 655705504287 | M71: ICIC0006557
A72: JAY AMBEY TEXTILE | B72: SURAT | C72: - | D72: - | E72: - | F72: SURYAM TEXTILE AGENCY | G72: AKASH | H72: 91044 89871 | I72: - | J72: - | K72: JAY AMBEY TEXTILE | L72: 9725605738 | M72: KKBK0002847
A73: JB ENTERPRISES | B73: - | C73: - | D73: - | E73: - | F73: - | G73: - | H73: - | I73: - | J73: - | K73: - | L73: - | M73: -
A74: KAKAMAA BUSINESS HOUSE PVT LTD (RANCHI) | B74: - | C74: - | D74: - | E74: - | F74: - | G74: - | H74: - | I74: - | J74: - | K74: - | L74: - | M74: -
A75: KASHNI | B75: MUMBAI | C75: - | D75: - | E75: - | F75: - | G75: - | H75: - | I75: - | J75: - | K75: KASHNI | L75: 99999326997373 | M75: HDFC0001119
A76: KAUSTUKI | B76: - | C76: - | D76: - | E76: - | F76: - | G76: - | H76: - | I76: - | J76: - | K76: - | L76: - | M76: -
A77: KHATUDHISH SAREES | B77: - | C77: - | D77: - | E77: - | F77: - | G77: - | H77: - | I77: - | J77: - | K77: - | L77: - | M77: -
A78: KHYAATI LEATHER INNOVATIONS PRIVATE LIMITED | B78: - | C78: - | D78: - | E78: - | F78: - | G78: - | H78: - | I78: - | J78: - | K78: - | L78: - | M78: -
A79: KIDCITY SOLUTIONS PRIVATE LIMITED | B79: - | C79: - | D79: - | E79: - | F79: - | G79: - | H79: - | I79: - | J79: - | K79: - | L79: - | M79: -
A80: KIMORA FASHION PVT LTD | B80: SURAT | C80: - | D80: 60 | E80: 0.05 | F80: SURYAM TEXTILE AGENCY | G80: AKASH | H80: 91044 89871 | I80: - | J80: - | K80: KIMORA FASHION PVT LTD | L80: 138751000019 | M80: ICIC0001387
A81: KIRAN CREATION | B81: - | C81: - | D81: - | E81: - | F81: - | G81: - | H81: - | I81: - | J81: - | K81: KIRAN CREATION | L81: 50200007524171 | M81: HDFC0000765
A82: KISHORI TRADELINK | B82: KOLKATA | C82: WITHOUT BRAND | D82: 60 | E82: 0.05 | F82: NEPOLIAN | G82: MUKESH | H82: 9831451670 | I82: - | J82: - | K82: KISHORI TRADELINK | L82: 5449027625 | M82: KKBK0006739
A83: KRUTHI CREATIONS | B83: - | C83: - | D83: - | E83: - | F83: - | G83: - | H83: - | I83: - | J83: - | K83: - | L83: - | M83: -
A84: LADDU PRINTS | B84: KOLKATA | C84: - | D84: 60 | E84: NET | F84: NEPOLIAN | G84: MUKESH | H84: 9831451670 | I84: - | J84: - | K84: LADDU PRINTS | L84: 915020029941646 | M84: UTIB0000236
A85: LAKHMI CHAND TEJOO MAL | B85: - | C85: - | D85: - | E85: - | F85: - | G85: - | H85: - | I85: - | J85: - | K85: - | L85: - | M85: -
A86: LALIT ENTERPRISES | B86: - | C86: - | D86: - | E86: - | F86: - | G86: - | H86: - | I86: - | J86: - | K86: - | L86: - | M86: -
A87: LAVANYA | B87: - | C87: - | D87: - | E87: - | F87: - | G87: - | H87: - | I87: - | J87: - | K87: LAVANYA | L87: 624605503579 | M87: ICICI0006246
A88: LITES N MORE | B88: - | C88: - | D88: - | E88: - | F88: - | G88: - | H88: - | I88: - | J88: - | K88: - | L88: - | M88: -
A89: M B ENTERPRISES | B89: RANCHI | C89: - | D89: 60 | E89: 0.1 | F89: - | G89: - | H89: - | I89: - | J89: - | K89: M B ENTERPRISES | L89: 50200035172636 | M89: HDFC0002834
A90: M NIRMAL KUMAR PRIVATE LIMITED | B90: - | C90: - | D90: - | E90: - | F90: - | G90: - | H90: - | I90: - | J90: - | K90: - | L90: - | M90: -
A91: M. N. GARMENTS | B91: RANCHI | C91: TWILLS | D91: - | E91: - | F91: - | G91: - | H91: - | I91: - | J91: - | K91: M. N. GARMENTS | L91: 50200058436598 | M91: HDFC0001470
A92: M.B. ENTERPRISES | B92: - | C92: - | D92: - | E92: - | F92: - | G92: - | H92: - | I92: - | J92: - | K92: - | L92: - | M92: -
A93: M/S A.R. MEDIA | B93: - | C93: - | D93: - | E93: - | F93: - | G93: - | H93: - | I93: - | J93: - | K93: - | L93: - | M93: -
A94: M/S ARIHANT TRADING AGENCY | B94: - | C94: - | D94: - | E94: - | F94: - | G94: - | H94: - | I94: - | J94: - | K94: - | L94: - | M94: -
A95: M/S JAI MATA JEANS CENTRE | B95: - | C95: - | D95: - | E95: - | F95: - | G95: - | H95: - | I95: - | J95: - | K95: - | L95: - | M95: -
A96: NARAYANI DISTRIBUTORS | B96: RANCHI | C96: - | D96: - | E96: - | F96: - | G96: - | H96: - | I96: - | J96: - | K96: NARAYANI DISTRIBUTORS | L96: 926030011158790 | M96: UTIB0004102
A97: MAAHIMA FASHIONS PRIVATE LIMITED | B97: - | C97: - | D97: - | E97: - | F97: - | G97: - | H97: - | I97: - | J97: - | K97: - | L97: - | M97: -
A98: MAHAVIR TEX TREND | B98: - | C98: - | D98: - | E98: - | F98: - | G98: - | H98: - | I98: - | J98: - | K98: - | L98: - | M98: -
A99: MAHIMA FASHIONS PVT LTD | B99: - | C99: - | D99: - | E99: - | F99: - | G99: - | H99: - | I99: - | J99: - | K99: - | L99: - | M99: -
A100: MALHOTRA GARMENTS | B100: - | C100: - | D100: - | E100: - | F100: - | G100: - | H100: - | I100: - | J100: - | K100: - | L100: - | M100: -
A101: MALHOTRA MARKETING | B101: - | C101: - | D101: - | E101: - | F101: - | G101: - | H101: - | I101: - | J101: - | K101: - | L101: - | M101: -
A102: MANIYAR SYNTHETICS PRIVATE LIMITED | B102: - | C102: - | D102: - | E102: - | F102: - | G102: - | H102: - | I102: - | J102: - | K102: - | L102: - | M102: -
A103: MANOHAR SONS | B103: SURAT | C103: - | D103: 60 | E103: 0.03 | F103: SURYAM TEXTILE AGENCY | G103: AKASH | H103: 91044 89871 | I103: - | J103: - | K103: MANOHAR SONS | L103: 50200032851542 | M103: HDFC0001416
A104: MEEVA | B104: SURAT | C104: - | D104: NO | E104: - | F104: SURYAM TEXTILE AGENCY | G104: AKASH | H104: 91044 89871 | I104: - | J104: - | K104: MEEVA | L104: 510909010155384 | M104: CIUB0000100
...

Sheet INVOICE DETAILS.
A1: Other Invoice Details | F1: =SUBTOTAL(3,F3:F1994) -> 1259 | G1: TOTAL INVOICE COUNT | H1: =IF(SUBTOTAL(9,H3:H1994)=0," ",SUBTOTAL(9,H3:H1994)) -> 54487 | I1: =IF(SUBTOTAL(9,I3:I1994)=0," ",SUBTOTAL(9,I3:I1994)) -> 67763896 | J1: =IF(SUBTOTAL(3,J3:J1994)-F1>0,"NEED TO UPDATE: " & (SUBTOTAL(3,J3:J1994)-F1),"LAST UPDATE: " & TEXT(MAX(G3:G1994),"dd-mmmm-yyyy")) -> NEED TO UPDATE: 219 | Q1: =IF(SUBTOTAL(9,Q3:Q994)=0," ",SUBTOTAL(9,Q3:Q994)) -> 2350486 | S1: =IF(SUBTOTAL(9,S3:S994)=0," ",SUBTOTAL(9,S3:S994)) -> 96300.6 | T1: =IF(SUBTOTAL(9,T3:T994)=0," ",SUBTOTAL(9,T3:T994)) -> 2145
A2: Supplier Name | B2: Brand Name | C2: Agency Company | D2: Credit Days | E2: CD % | F2: Invoice No | G2: Invoice Date | H2: Invoice Qty | I2: Invoice Value | J2: Invoice Soft Copy | K2: PT File Excel Sheet | L2: TEN Uploaded Date | M2: Invoice Ageing | N2: Bank Name | O2: Bank Account | P2: IFSC Code | Q2: Payment Amount | R2: Payment Date | S2: CD Amount | T2: GR Amount | U2: Remarks | V2: Accounting Year
A3: D D SALES CO | B3: =IF($A$3=" "," ", IFERROR( VLOOKUP($A3,'SUPPLIER DATA BASE'!$A$2:$M$936,3,0),"")) -> KILLER | C3: =IF($A$3=" "," ", IFERROR( VLOOKUP($A3,'SUPPLIER DATA BASE'!$A$2:$F$936,6,0),"")) -> - | D3: =IF($A$3=" "," ", IFERROR( VLOOKUP($A3,'SUPPLIER DATA BASE'!$A$2:$G$936,4,0),"")) -> NO | E3: =IF($A$3=" "," ", IFERROR( VLOOKUP($A3,'SUPPLIER DATA BASE'!$A$2:$H$936,5,0),"")) -> - | F3: JKL-159 | G3: 45593 | H3: 22 | I3: 36223 | J3: DD SALES -159.pdf | K3: - | L3: - | M3: =IF(G3="", "", (TODAY() - G3) & " Days") -> 595 Days | N3: =IF($A$3=" "," ", IFERROR( VLOOKUP($A3,'SUPPLIER DATA BASE'!$A$2:$O$936,11,0),"")) -> D D SALES CO | O3: =IF($A$3=" "," ", IFERROR( VLOOKUP($A3,'SUPPLIER DATA BASE'!$A$2:$O$936,12,0),"")) -> 29205007835 | P3: =IF($A$3=" "," ", IFERROR( VLOOKUP($A3,'SUPPLIER DATA BASE'!$A$2:$O$936,13,0),"")) -> ICIC0000292 | V3: =IF(G3="","", IF(AND(G3>=DATE(2024,4,1),G3<=DATE(2025,3,31)),"FY 24-25", IF(AND(G3>=DATE(2025,4,1),G3<=DATE(2026,3,31)),"FY 25-26",IF(AND(G3>=DATE(2026,4,1),G3<=DATE(2027,3,31)),"FY 26-27","")))) -> FY 24-25
A4: ADITYA BIRLA | B4: =IF($A$3=" "," ", IFERROR( VLOOKUP($A4,'SUPPLIER DATA BASE'!$A$2:$M$936,3,0),"")) -> - | C4: =IF($A$3=" "," ", IFERROR( VLOOKUP($A4,'SUPPLIER DATA BASE'!$A$2:$F$936,6,0),"")) -> - | D4: =IF($A$3=" "," ", IFERROR( VLOOKUP($A4,'SUPPLIER DATA BASE'!$A$2:$G$936,4,0),"")) -> - | E4: =IF($A$3=" "," ", IFERROR( VLOOKUP($A4,'SUPPLIER DATA BASE'!$A$2:$H$936,5,0),"")) -> - | F4: MSF2252000010422 | G4: 45876 | H4: 3 | I4: 6074.1 | J4: ADITYA BIRLA -MSF2252000010422.pdf | K4: - | L4: - | M4: =IF(G4="", "", (TODAY() - G4) & " Days") -> 312 Days | N4: =IF($A$3=" "," ", IFERROR( VLOOKUP($A4,'SUPPLIER DATA BASE'!$A$2:$O$936,11,0),"")) -> - | O4: =IF($A$3=" "," ", IFERROR( VLOOKUP($A4,'SUPPLIER DATA BASE'!$A$2:$O$936,12,0),"")) -> - | P4: =IF($A$3=" "," ", IFERROR( VLOOKUP($A4,'SUPPLIER DATA BASE'!$A$2:$O$936,13,0),"")) -> - | V4: =IF(G4="","", IF(AND(G4>=DATE(2024,4,1),G4<=DATE(2025,3,31)),"FY 24-25", IF(AND(G4>=DATE(2025,4,1),G4<=DATE(2026,3,31)),"FY 25-26",IF(AND(G4>=DATE(2026,4,1),G4<=DATE(2027,3,31)),"FY 26-27","")))) -> FY 25-26
A5: ADITYA BIRLA | B5: =IF($A$3=" "," ", IFERROR( VLOOKUP($A5,'SUPPLIER DATA BASE'!$A$2:$M$936,3,0),"")) -> - | C5: =IF($A$3=" "," ", IFERROR( VLOOKUP($A5,'SUPPLIER DATA BASE'!$A$2:$F$936,6,0),"")) -> - | D5: =IF($A$3=" "," ", IFERROR( VLOOKUP($A5,'SUPPLIER DATA BASE'!$A$2:$G$936,4,0),"")) -> - | E5: =IF($A$3=" "," ", IFERROR( VLOOKUP($A5,'SUPPLIER DATA BASE'!$A$2:$H$936,5,0),"")) -> - | F5: MSF2251000012742 | G5: 45913 | H5: 7 | I5: 13088.75 | J5: ADITYA BIRLA -MSF2251000012742.PDF | K5: - | L5: - | M5: =IF(G5="", "", (TODAY() - G5) & " Days") -> 275 Days | N5: =IF($A$3=" "," ", IFERROR( VLOOKUP($A5,'SUPPLIER DATA BASE'!$A$2:$O$936,11,0),"")) -> - | O5: =IF($A$3=" "," ", IFERROR( VLOOKUP($A5,'SUPPLIER DATA BASE'!$A$2:$O$936,12,0),"")) -> - | P5: =IF($A$3=" "," ", IFERROR( VLOOKUP($A5,'SUPPLIER DATA BASE'!$A$2:$O$936,13,0),"")) -> - | V5: =IF(G5="","", IF(AND(G5>=DATE(2024,4,1),G5<=DATE(2025,3,31)),"FY 24-25", IF(AND(G5>=DATE(2025,4,1),G5<=DATE(2026,3,31)),"FY 25-26",IF(AND(G5>=DATE(2026,4,1),G5<=DATE(2027,3,31)),"FY 26-27","")))) -> FY 25-26
A6: ROOP LAXMI SAREES (P) LTD | B6: =IF($A$3=" "," ", IFERROR( VLOOKUP($A6,'SUPPLIER DATA BASE'!$A$2:$M$936,3,0),"")) -> रूप लक्ष्मी | C6: =IF($A$3=" "," ", IFERROR( VLOOKUP($A6,'SUPPLIER DATA BASE'!$A$2:$F$936,6,0),"")) -> - | D6: =IF($A$3=" "," ", IFERROR( VLOOKUP($A6,'SUPPLIER DATA BASE'!$A$2:$G$936,4,0),"")) -> - | E6: =IF($A$3=" "," ", IFERROR( VLOOKUP($A6,'SUPPLIER DATA BASE'!$A$2:$H$936,5,0),"")) -> - | F6: RL/8362/25-26 | G6: 45948 | H6: 18 | I6: 23877 | J6: Room Laxmi sarees 8362 (1).pdf | K6: - | L6: - | M6: =IF(G6="", "", (TODAY() - G6) & " Days") -> 240 Days | N6: =IF($A$3=" "," ", IFERROR( VLOOKUP($A6,'SUPPLIER DATA BASE'!$A$2:$O$936,11,0),"")) -> ROOP LAXMI SAREES (P) LTD | O6: =IF($A$3=" "," ", IFERROR( VLOOKUP($A6,'SUPPLIER DATA BASE'!$A$2:$O$936,12,0),"")) -> 0221083000003432 | P6: =IF($A$3=" "," ", IFERROR( VLOOKUP($A6,'SUPPLIER DATA BASE'!$A$2:$O$936,13,0),"")) -> SIBL0000221 | V6: =IF(G6="","", IF(AND(G6>=DATE(2024,4,1),G6<=DATE(2025,3,31)),"FY 24-25", IF(AND(G6>=DATE(2025,4,1),G6<=DATE(2026,3,31)),"FY 25-26",IF(AND(G6>=DATE(2026,4,1),G6<=DATE(2027,3,31)),"FY 26-27","")))) -> FY 25-26
A7: ROOP LAXMI SAREES (P) LTD | B7: =IF($A$3=" "," ", IFERROR( VLOOKUP($A7,'SUPPLIER DATA BASE'!$A$2:$M$936,3,0),"")) -> रूप लक्ष्मी | C7: =IF($A$3=" "," ", IFERROR( VLOOKUP($A7,'SUPPLIER DATA BASE'!$A$2:$F$936,6,0),"")) -> - | D7: =IF($A$3=" "," ", IFERROR( VLOOKUP($A7,'SUPPLIER DATA BASE'!$A$2:$G$936,4,0),"")) -> - | E7: =IF($A$3=" "," ", IFERROR( VLOOKUP($A7,'SUPPLIER DATA BASE'!$A$2:$H$936,5,0),"")) -> - | F7: RL/8360/25-26 | G7: 45948 | H7: 16 | I7: 67137 | J7: Roop laxmi sarees 8360 (1).pdf | K7: - | L7: - | M7: =IF(G7="", "", (TODAY() - G7) & " Days") -> 240 Days | N7: =IF($A$3=" "," ", IFERROR( VLOOKUP($A7,'SUPPLIER DATA BASE'!$A$2:$O$936,11,0),"")) -> ROOP LAXMI SAREES (P) LTD | O7: =IF($A$3=" "," ", IFERROR( VLOOKUP($A7,'SUPPLIER DATA BASE'!$A$2:$O$936,12,0),"")) -> 0221083000003432 | P7: =IF($A$3=" "," ", IFERROR( VLOOKUP($A7,'SUPPLIER DATA BASE'!$A$2:$O$936,13,0),"")) -> SIBL0000221 | V7: =IF(G7="","", IF(AND(G7>=DATE(2024,4,1),G7<=DATE(2025,3,31)),"FY 24-25", IF(AND(G7>=DATE(2025,4,1),G7<=DATE(2026,3,31)),"FY 25-26",IF(AND(G7>=DATE(2026,4,1),G7<=DATE(2027,3,31)),"FY 26-27","")))) -> FY 25-26
A8: D APPAREL | B8: =IF($A$3=" "," ", IFERROR( VLOOKUP($A8,'SUPPLIER DATA BASE'!$A$2:$M$936,3,0),"")) -> KHUSHAL/STATUS QUO | C8: =IF($A$3=" "," ", IFERROR( VLOOKUP($A8,'SUPPLIER DATA BASE'!$A$2:$F$936,6,0),"")) -> - | D8: =IF($A$3=" "," ", IFERROR( VLOOKUP($A8,'SUPPLIER DATA BASE'!$A$2:$G$936,4,0),"")) -> - | E8: =IF($A$3=" "," ", IFERROR( VLOOKUP($A8,'SUPPLIER DATA BASE'!$A$2:$H$936,5,0),"")) -> - | F8: DA/25-26/0605 | G8: 45952 | H8: 6 | I8: 25693 | J8: D APPAREL(KHUSHAAL)_INV0605_JSL.pdf | K8: - | L8: - | M8: =IF(G8="", "", (TODAY() - G8) & " Days") -> 236 Days | N8: =IF($A$3=" "," ", IFERROR( VLOOKUP($A8,'SUPPLIER DATA BASE'!$A$2:$O$936,11,0),"")) -> D APPAREL | O8: =IF($A$3=" "," ", IFERROR( VLOOKUP($A8,'SUPPLIER DATA BASE'!$A$2:$O$936,12,0),"")) -> 722501010050397 | P8: =IF($A$3=" "," ", IFERROR( VLOOKUP($A8,'SUPPLIER DATA BASE'!$A$2:$O$936,13,0),"")) -> UBIN0572250 | V8: =IF(G8="","", IF(AND(G8>=DATE(2024,4,1),G8<=DATE(2025,3,31)),"FY 24-25", IF(AND(G8>=DATE(2025,4,1),G8<=DATE(2026,3,31)),"FY 25-26",IF(AND(G8>=DATE(2026,4,1),G8<=DATE(2027,3,31)),"FY 26-27","")))) -> FY 25-26
A9: VISHAL MARKETING & CO. | B9: =IF($A$3=" "," ", IFERROR( VLOOKUP($A9,'SUPPLIER DATA BASE'!$A$2:$M$936,3,0),"")) -> - | C9: =IF($A$3=" "," ", IFERROR( VLOOKUP($A9,'SUPPLIER DATA BASE'!$A$2:$F$936,6,0),"")) -> - | D9: =IF($A$3=" "," ", IFERROR( VLOOKUP($A9,'SUPPLIER DATA BASE'!$A$2:$G$936,4,0),"")) -> - | E9: =IF($A$3=" "," ", IFERROR( VLOOKUP($A9,'SUPPLIER DATA BASE'!$A$2:$H$936,5,0),"")) -> - | F9: D/1212 | G9: 45986 | H9: 18 | I9: 59696 | J9: VISHAL MARKETING & CO(SPYKAR)_1212_2025-26.pdf | K9: - | L9: - | M9: =IF(G9="", "", (TODAY() - G9) & " Days") -> 202 Days | N9: =IF($A$3=" "," ", IFERROR( VLOOKUP($A9,'SUPPLIER DATA BASE'!$A$2:$O$936,11,0),"")) -> VISHAL MARKETING & CO. | O9: =IF($A$3=" "," ", IFERROR( VLOOKUP($A9,'SUPPLIER DATA BASE'!$A$2:$O$936,12,0),"")) -> 1091008700001025 | P9: =IF($A$3=" "," ", IFERROR( VLOOKUP($A9,'SUPPLIER DATA BASE'!$A$2:$O$936,13,0),"")) -> PUNB0109100 | V9: =IF(G9="","", IF(AND(G9>=DATE(2024,4,1),G9<=DATE(2025,3,31)),"FY 24-25", IF(AND(G9>=DATE(2025,4,1),G9<=DATE(2026,3,31)),"FY 25-26",IF(AND(G9>=DATE(2026,4,1),G9<=DATE(2027,3,31)),"FY 26-27","")))) -> FY 25-26
A10: ADITYA BIRLA | B10: =IF($A$3=" "," ", IFERROR( VLOOKUP($A10,'SUPPLIER DATA BASE'!$A$2:$M$936,3,0),"")) -> - | C10: =IF($A$3=" "," ", IFERROR( VLOOKUP($A10,'SUPPLIER DATA BASE'!$A$2:$F$936,6,0),"")) -> - | D10: =IF($A$3=" "," ", IFERROR( VLOOKUP($A10,'SUPPLIER DATA BASE'!$A$2:$G$936,4,0),"")) -> - | E10: =IF($A$3=" "," ", IFERROR( VLOOKUP($A10,'SUPPLIER DATA BASE'!$A$2:$H$936,5,0),"")) -> - | F10: MSF2251000022820 | G10: 46001 | H10: 7 | I10: 38685.2 | J10: ADITYA BIRLA -MSF2251000022820.pdf | K10: - | L10: - | M10: =IF(G10="", "", (TODAY() - G10) & " Days") -> 187 Days | N10: =IF($A$3=" "," ", IFERROR( VLOOKUP($A10,'SUPPLIER DATA BASE'!$A$2:$O$936,11,0),"")) -> - | O10: =IF($A$3=" "," ", IFERROR( VLOOKUP($A10,'SUPPLIER DATA BASE'!$A$2:$O$936,12,0),"")) -> - | P10: =IF($A$3=" "," ", IFERROR( VLOOKUP($A10,'SUPPLIER DATA BASE'!$A$2:$O$936,13,0),"")) -> - | V10: =IF(G10="","", IF(AND(G10>=DATE(2024,4,1),G10<=DATE(2025,3,31)),"FY 24-25", IF(AND(G10>=DATE(2025,4,1),G10<=DATE(2026,3,31)),"FY 25-26",IF(AND(G10>=DATE(2026,4,1),G10<=DATE(2027,3,31)),"FY 26-27","")))) -> FY 25-26
A11: ADITYA BIRLA | B11: =IF($A$3=" "," ", IFERROR( VLOOKUP($A11,'SUPPLIER DATA BASE'!$A$2:$M$936,3,0),"")) -> - | C11: =IF($A$3=" "," ", IFERROR( VLOOKUP($A11,'SUPPLIER DATA BASE'!$A$2:$F$936,6,0),"")) -> - | D11: =IF($A$3=" "," ", IFERROR( VLOOKUP($A11,'SUPPLIER DATA BASE'!$A$2:$G$936,4,0),"")) -> - | E11: =IF($A$3=" "," ", IFERROR( VLOOKUP($A11,'SUPPLIER DATA BASE'!$A$2:$H$936,5,0),"")) -> - | F11: MSF2251000022940 | G11: 46002 | H11: 23 | I11: 97197.17 | J11: ADITYA BIRLA -MSF2251000022940.pdf | K11: - | L11: - | M11: =IF(G11="", "", (TODAY() - G11) & " Days") -> 186 Days | N11: =IF($A$3=" "," ", IFERROR( VLOOKUP($A11,'SUPPLIER DATA BASE'!$A$2:$O$936,11,0),"")) -> - | O11: =IF($A$3=" "," ", IFERROR( VLOOKUP($A11,'SUPPLIER DATA BASE'!$A$2:$O$936,12,0),"")) -> - | P11: =IF($A$3=" "," ", IFERROR( VLOOKUP($A11,'SUPPLIER DATA BASE'!$A$2:$O$936,13,0),"")) -> - | V11: =IF(G11="","", IF(AND(G11>=DATE(2024,4,1),G11<=DATE(2025,3,31)),"FY 24-25", IF(AND(G11>=DATE(2025,4,1),G11<=DATE(2026,3,31)),"FY 25-26",IF(AND(G11>=DATE(2026,4,1),G11<=DATE(2027,3,31)),"FY 26-27","")))) -> FY 25-26
A12: ADITYA BIRLA | B12: =IF($A$3=" "," ", IFERROR( VLOOKUP($A12,'SUPPLIER DATA BASE'!$A$2:$M$936,3,0),"")) -> - | C12: =IF($A$3=" "," ", IFERROR( VLOOKUP($A12,'SUPPLIER DATA BASE'!$A$2:$F$936,6,0),"")) -> - | D12: =IF($A$3=" "," ", IFERROR( VLOOKUP($A12,'SUPPLIER DATA BASE'!$A$2:$G$936,4,0),"")) -> - | E12: =IF($A$3=" "," ", IFERROR( VLOOKUP($A12,'SUPPLIER DATA BASE'!$A$2:$H$936,5,0),"")) -> - | F12: MSF2251000923014 | G12: 46002 | H12: 22 | I12: 42886.53 | J12: ADITYA BIRLA -MSF2251000923014.pdf | K12: - | L12: - | M12: =IF(G12="", "", (TODAY() - G12) & " Days") -> 186 Days | N12: =IF($A$3=" "," ", IFERROR( VLOOKUP($A12,'SUPPLIER DATA BASE'!$A$2:$O$936,11,0),"")) -> - | O12: =IF($A$3=" "," ", IFERROR( VLOOKUP($A12,'SUPPLIER DATA BASE'!$A$2:$O$936,12,0),"")) -> - | P12: =IF($A$3=" "," ", IFERROR( VLOOKUP($A12,'SUPPLIER DATA BASE'!$A$2:$O$936,13,0),"")) -> - | V12: =IF(G12="","", IF(AND(G12>=DATE(2024,4,1),G12<=DATE(2025,3,31)),"FY 24-25", IF(AND(G12>=DATE(2025,4,1),G12<=DATE(2026,3,31)),"FY 25-26",IF(AND(G12>=DATE(2026,4,1),G12<=DATE(2027,3,31)),"FY 26-27","")))) -> FY 25-26
A13: ADITYA BIRLA | B13: =IF($A$3=" "," ", IFERROR( VLOOKUP($A13,'SUPPLIER DATA BASE'!$A$2:$M$936,3,0),"")) -> - | C13: =IF($A$3=" "," ", IFERROR( VLOOKUP($A13,'SUPPLIER DATA BASE'!$A$2:$F$936,6,0),"")) -> - | D13: =IF($A$3=" "," ", IFERROR( VLOOKUP($A13,'SUPPLIER DATA BASE'!$A$2:$G$936,4,0),"")) -> - | E13: =IF($A$3=" "," ", IFERROR( VLOOKUP($A13,'SUPPLIER DATA BASE'!$A$2:$H$936,5,0),"")) -> - | F13: MSF2252000024323 | G13: 46013 | H13: 85 | I13: 157878.07 | J13: ADITYA BIRLA -MSF2252000024323.pdf | K13: - | L13: - | M13: =IF(G13="", "", (TODAY() - G13) & " Days") -> 175 Days | N13: =IF($A$3=" "," ", IFERROR( VLOOKUP($A13,'SUPPLIER DATA BASE'!$A$2:$O$936,11,0),"")) -> - | O13: =IF($A$3=" "," ", IFERROR( VLOOKUP($A13,'SUPPLIER DATA BASE'!$A$2:$O$936,12,0),"")) -> - | P13: =IF($A$3=" "," ", IFERROR( VLOOKUP($A13,'SUPPLIER DATA BASE'!$A$2:$O$936,13,0),"")) -> - | V13: =IF(G13="","", IF(AND(G13>=DATE(2024,4,1),G13<=DATE(2025,3,31)),"FY 24-25", IF(AND(G13>=DATE(2025,4,1),G13<=DATE(2026,3,31)),"FY 25-26",IF(AND(G13>=DATE(2026,4,1),G13<=DATE(2027,3,31)),"FY 26-27","")))) -> FY 25-26
A14: SOUL INDIA | B14: =IF($A$3=" "," ", IFERROR( VLOOKUP($A14,'SUPPLIER DATA BASE'!$A$2:$M$936,3,0),"")) -> - | C14: =IF($A$3=" "," ", IFERROR( VLOOKUP($A14,'SUPPLIER DATA BASE'!$A$2:$F$936,6,0),"")) -> - | D14: =IF($A$3=" "," ", IFERROR( VLOOKUP($A14,'SUPPLIER DATA BASE'!$A$2:$G$936,4,0),"")) -> - | E14: =IF($A$3=" "," ", IFERROR( VLOOKUP($A14,'SUPPLIER DATA BASE'!$A$2:$H$936,5,0),"")) -> - | F14: EOS1-48 | G14: 46017 | H14: 103 | I14: 149799.69 | J14: SOUL INDIA EOS1-48.pdf | K14: - | L14: - | M14: =IF(G14="", "", (TODAY() - G14) & " Days") -> 171 Days | N14: =IF($A$3=" "," ", IFERROR( VLOOKUP($A14,'SUPPLIER DATA BASE'!$A$2:$O$936,11,0),"")) -> SOUL INDIA | O14: =IF($A$3=" "," ", IFERROR( VLOOKUP($A14,'SUPPLIER DATA BASE'!$A$2:$O$936,12,0),"")) -> 250705501258 | P14: =IF($A$3=" "," ", IFERROR( VLOOKUP($A14,'SUPPLIER DATA BASE'!$A$2:$O$936,13,0),"")) -> ICIC0002507 | V14: =IF(G14="","", IF(AND(G14>=DATE(2024,4,1),G14<=DATE(2025,3,31)),"FY 24-25", IF(AND(G14>=DATE(2025,4,1),G14<=DATE(2026,3,31)),"FY 25-26",IF(AND(G14>=DATE(2026,4,1),G14<=DATE(2027,3,31)),"FY 26-27","")))) -> FY 25-26
... A17: D S CREATION | B17: =IF($A$3=" "," ", IFERROR( VLOOKUP($A17,'SUPPLIER DATA BASE'!$A$2:$M$936,3,0),"")) -> YES MAAM | C17: =IF($A$3=" "," ", IFERROR( VLOOKUP($A17,'SUPPLIER DATA BASE'!$A$2:$F$936,6,0),"")) -> NEPOLIAN | D17: =IF($A$3=" "," ", IFERROR( VLOOKUP($A17,'SUPPLIER DATA BASE'!$A$2:$G$936,4,0),"")) -> 60 | E17: =IF($A$3=" "," ", IFERROR( VLOOKUP($A17,'SUPPLIER DATA BASE'!$A$2:$H$936,5,0),"")) -> 0.03 | F17: DS/5296/25-26 | G17: 46020 | H17: 1 | I17: 4065 | J17: D S creation 5296.pdf | K17: - | L17: - | M17: =IF(G17="", "", (TODAY() - G17) & " Days") -> 168 Days | N17: =IF($A$3=" "," ", IFERROR( VLOOKUP($A17,'SUPPLIER DATA BASE'!$A$2:$O$936,11,0),"")) -> D S CREATION | O17: =IF($A$3=" "," ", IFERROR( VLOOKUP($A17,'SUPPLIER DATA BASE'!$A$2:$O$936,12,0),"")) -> 9830047013 | P17: =IF($A$3=" "," ", IFERROR( VLOOKUP($A17,'SUPPLIER DATA BASE'!$A$2:$O$936,13,0),"")) -> KKBK0006562 | V17: =IF(G17="","", IF(AND(G17>=DATE(2024,4,1),G17<=DATE(2025,3,31)),"FY 24-25", IF(AND(G17>=DATE(2025,4,1),G17<=DATE(2026,3,31)),"FY 25-26",IF(AND(G17>=DATE(2026,4,1),G17<=DATE(2027,3,31)),"FY 26-27","")))) -> FY 25-26
A18: PLAZER FABRICS | B18: =IF($A$3=" "," ", IFERROR( VLOOKUP($A18,'SUPPLIER DATA BASE'!$A$2:$M$936,3,0),"")) -> - | C18: =IF($A$3=" "," ", IFERROR( VLOOKUP($A18,'SUPPLIER DATA BASE'!$A$2:$F$936,6,0),"")) -> - | D18: =IF($A$3=" "," ", IFERROR( VLOOKUP($A18,'SUPPLIER DATA BASE'!$A$2:$G$936,4,0),"")) -> - | E18: =IF($A$3=" "," ", IFERROR( VLOOKUP($A18,'SUPPLIER DATA BASE'!$A$2:$H$936,5,0),"")) -> - | F18: 2265 | G18: 46024 | H18: 11 | I18: 8377 | J18: PLAZER FABRICS -2265.pdf | K18: - | L18: - | M18: =IF(G18="", "", (TODAY() - G18) & " Days") -> 164 Days | N18: =IF($A$3=" "," ", IFERROR( VLOOKUP($A18,'SUPPLIER DATA BASE'!$A$2:$O$936,11,0),"")) -> PLAZER FABRICS | O18: =IF($A$3=" "," ", IFERROR( VLOOKUP($A18,'SUPPLIER DATA BASE'!$A$2:$O$936,12,0),"")) -> 50200014256984 | P18: =IF($A$3=" "," ", IFERROR( VLOOKUP($A18,'SUPPLIER DATA BASE'!$A$2:$O$936,13,0),"")) -> HDFC0002834 | V18: =IF(G18="","", IF(AND(G18>=DATE(2024,4,1),G18<=DATE(2025,3,31)),"FY 24-25", IF(AND(G18>=DATE(2025,4,1),G18<=DATE(2026,3,31)),"FY 25-26",IF(AND(G18>=DATE(2026,4,1),G18<=DATE(2027,3,31)),"FY 26-27","")))) -> FY 25-26
A19: P R MODI AND SONS | B19: =IF($A$3=" "," ", IFERROR( VLOOKUP($A19,'SUPPLIER DATA BASE'!$A$2:$M$936,3,0),"")) -> - | C19: =IF($A$3=" "," ", IFERROR( VLOOKUP($A19,'SUPPLIER DATA BASE'!$A$2:$F$936,6,0),"")) -> - | D19: =IF($A$3=" "," ", IFERROR( VLOOKUP($A19,'SUPPLIER DATA BASE'!$A$2:$G$936,4,0),"")) -> - | E19: =IF($A$3=" "," ", IFERROR( VLOOKUP($A19,'SUPPLIER DATA BASE'!$A$2:$H$936,5,0),"")) -> - | F19: 19221 | G19: 46024 | H19: 15 | I19: 21920 | J19: P R MODI AND SON'S -19221.pdf | K19: - | L19: - | M19: =IF(G19="", "", (TODAY() - G19) & " Days") -> 164 Days | N19: =IF($A$3=" "," ", IFERROR( VLOOKUP($A19,'SUPPLIER DATA BASE'!$A$2:$O$936,11,0),"")) -> P R MODI AND SONS | O19: =IF($A$3=" "," ", IFERROR( VLOOKUP($A19,'SUPPLIER DATA BASE'!$A$2:$O$936,12,0),"")) -> 490930150000030 | P19: =IF($A$3=" "," ", IFERROR( VLOOKUP($A19,'SUPPLIER DATA BASE'!$A$2:$O$936,13,0),"")) -> BKID0004909 | V19: =IF(G19="","", IF(AND(G19>=DATE(2024,4,1),G19<=DATE(2025,3,31)),"FY 24-25", IF(AND(G19>=DATE(2025,4,1),G19<=DATE(2026,3,31)),"FY 25-26",IF(AND(G19>=DATE(2026,4,1),G19<=DATE(2027,3,31)),"FY 26-27","")))) -> FY 25-26
A20: P R MODI AND SONS | B20: =IF($A$3=" "," ", IFERROR( VLOOKUP($A20,'SUPPLIER DATA BASE'!$A$2:$M$936,3,0),"")) -> - | C20: =IF($A$3=" "," ", IFERROR( VLOOKUP($A20,'SUPPLIER DATA BASE'!$A$2:$F$936,6,0),"")) -> - | D20: =IF($A$3=" "," ", IFERROR( VLOOKUP($A20,'SUPPLIER DATA BASE'!$A$2:$G$936,4,0),"")) -> - | E20: =IF($A$3=" "," ", IFERROR( VLOOKUP($A20,'SUPPLIER DATA BASE'!$A$2:$H$936,5,0),"")) -> - | F20: 19222 | G20: 46024 | H20: 12 | I20: 12231 | J20: P R MODI AND SON'S -19222.pdf | K20: - | L20: - | M20: =IF(G20="", "", (TODAY() - G20) & " Days") -> 164 Days | N20: =IF($A$3=" "," ", IFERROR( VLOOKUP($A20,'SUPPLIER DATA BASE'!$A$2:$O$936,11,0),"")) -> P R MODI AND SONS | O20: =IF($A$3=" "," ", IFERROR( VLOOKUP($A20,'SUPPLIER DATA BASE'!$A$2:$O$936,12,0),"")) -> 490930150000030 | P20: =IF($A$3=" "," ", IFERROR( VLOOKUP($A20,'SUPPLIER DATA BASE'!$A$2:$O$936,13,0),"")) -> BKID0004909 | V20: =IF(G20="","", IF(AND(G20>=DATE(2024,4,1),G20<=DATE(2025,3,31)),"FY 24-25", IF(AND(G20>=DATE(2025,4,1),G20<=DATE(2026,3,31)),"FY 25-26",IF(AND(G20>=DATE(2026,4,1),G20<=DATE(2027,3,31)),"FY 26-27","")))) -> FY 25-26
A21: P R MODI AND SONS | B21: =IF($A$3=" "," ", IFERROR( VLOOKUP($A21,'SUPPLIER DATA BASE'!$A$2:$M$936,3,0),"")) -> - | C21: =IF($A$3=" "," ", IFERROR( VLOOKUP($A21,'SUPPLIER DATA BASE'!$A$2:$F$936,6,0),"")) -> - | D21: =IF($A$3=" "," ", IFERROR( VLOOKUP($A21,'SUPPLIER DATA BASE'!$A$2:$G$936,4,0),"")) -> - | E21: =IF($A$3=" "," ", IFERROR( VLOOKUP($A21,'SUPPLIER DATA BASE'!$A$2:$H$936,5,0),"")) -> - | F21: 19220 | G21: 46024 | H21: 62 | I21: 59442 | J21: P R MODI AND SON'S -19220.pdf | K21: - | L21: - | M21: =IF(G21="", "", (TODAY() - G21) & " Days") -> 164 Days | N21: =IF($A$3=" "," ", IFERROR( VLOOKUP($A21,'SUPPLIER DATA BASE'!$A$2:$O$936,11,0),"")) -> P R MODI AND SONS | O21: =IF($A$3=" "," ", IFERROR( VLOOKUP($A21,'SUPPLIER DATA BASE'!$A$2:$O$936,12,0),"")) -> 490930150000030 | P21: =IF($A$3=" "," ", IFERROR( VLOOKUP($A21,'SUPPLIER DATA BASE'!$A$2:$O$936,13,0),"")) -> BKID0004909 | V21: =IF(G21="","", IF(AND(G21>=DATE(2024,4,1),G21<=DATE(2025,3,31)),"FY 24-25", IF(AND(G21>=DATE(2025,4,1),G21<=DATE(2026,3,31)),"FY 25-26",IF(AND(G21>=DATE(2026,4,1),G21<=DATE(2027,3,31)),"FY 26-27","")))) -> FY 25-26
A22: P R MODI AND SONS | B22: =IF($A$3=" "," ", IFERROR( VLOOKUP($A22,'SUPPLIER DATA BASE'!$A$2:$M$936,3,0),"")) -> - | C22: =IF($A$3=" "," ", IFERROR( VLOOKUP($A22,'SUPPLIER DATA BASE'!$A$2:$F$936,6,0),"")) -> - | D22: =IF($A$3=" "," ", IFERROR( VLOOKUP($A22,'SUPPLIER DATA BASE'!$A$2:$G$936,4,0),"")) -> - | E22: =IF($A$3=" "," ", IFERROR( VLOOKUP($A22,'SUPPLIER DATA BASE'!$A$2:$H$936,5,0),"")) -> - | F22: 19240 | G22: 46025 | H22: 2 | I22: 7236 | J22: P R MODI AND SON'S -19240.pdf | K22: - | L22: - | M22: =IF(G22="", "", (TODAY() - G22) & " Days") -> 163 Days | N22: =IF($A$3=" "," ", IFERROR( VLOOKUP($A22,'SUPPLIER DATA BASE'!$A$2:$O$936,11,0),"")) -> P R MODI AND SONS | O22: =IF($A$3=" "," ", IFERROR( VLOOKUP($A22,'SUPPLIER DATA BASE'!$A$2:$O$936,12,0),"")) -> 490930150000030 | P22: =IF($A$3=" "," ", IFERROR( VLOOKUP($A22,'SUPPLIER DATA BASE'!$A$2:$O$936,13,0),"")) -> BKID0004909 | V22: =IF(G22="","", IF(AND(G22>=DATE(2024,4,1),G22<=DATE(2025,3,31)),"FY 24-25", IF(AND(G22>=DATE(2025,4,1),G22<=DATE(2026,3,31)),"FY 25-26",IF(AND(G22>=DATE(2026,4,1),G22<=DATE(2027,3,31)),"FY 26-27","")))) -> FY 25-26
A23: C2D VENTURES LLP | B23: =IF($A$3=" "," ", IFERROR( VLOOKUP($A23,'SUPPLIER DATA BASE'!$A$2:$M$936,3,0),"")) -> WELSPUN, VAN HEUSEN | C23: =IF($A$3=" "," ", IFERROR( VLOOKUP($A23,'SUPPLIER DATA BASE'!$A$2:$F$936,6,0),"")) -> DIRECT | D23: =IF($A$3=" "," ", IFERROR( VLOOKUP($A23,'SUPPLIER DATA BASE'!$A$2:$G$936,4,0),"")) -> 15 | E23: =IF($A$3=" "," ", IFERROR( VLOOKUP($A23,'SUPPLIER DATA BASE'!$A$2:$H$936,5,0),"")) -> 5 | F23: IH/25-26/965 | G23: 46027 | H23: 93 | I23: 26019 | J23: C2D VENTURES -965.pdf | K23: - | L23: - | M23: =IF(G23="", "", (TODAY() - G23) & " Days") -> 161 Days | N23: =IF($A$3=" "," ", IFERROR( VLOOKUP($A23,'SUPPLIER DATA BASE'!$A$2:$O$936,11,0),"")) -> C2D VENTURES LLP | O23: =IF($A$3=" "," ", IFERROR( VLOOKUP($A23,'SUPPLIER DATA BASE'!$A$2:$O$936,12,0),"")) -> 50484840037 | P23: =IF($A$3=" "," ", IFERROR( VLOOKUP($A23,'SUPPLIER DATA BASE'!$A$2:$O$936,13,0),"")) -> IDIB000D600 | V23: =IF(G23="","", IF(AND(G23>=DATE(2024,4,1),G23<=DATE(2025,3,31)),"FY 24-25", IF(AND(G23>=DATE(2025,4,1),G23<=DATE(2026,3,31)),"FY 25-26",IF(AND(G23>=DATE(2026,4,1),G23<=DATE(2027,3,31)),"FY 26-27","")))) -> FY 25-26
A24: C2D VENTURES LLP | B24: =IF($A$3=" "," ", IFERROR( VLOOKUP($A24,'SUPPLIER DATA BASE'!$A$2:$M$936,3,0),"")) -> WELSPUN, VAN HEUSEN | C24: =IF($A$3=" "," ", IFERROR( VLOOKUP($A24,'SUPPLIER DATA BASE'!$A$2:$F$936,6,0),"")) -> DIRECT | D24: =IF($A$3=" "," ", IFERROR( VLOOKUP($A24,'SUPPLIER DATA BASE'!$A$2:$G$936,4,0),"")) -> 15 | E24: =IF($A$3=" "," ", IFERROR( VLOOKUP($A24,'SUPPLIER DATA BASE'!$A$2:$H$936,5,0),"")) -> 5 | F24: IH/25-26/964 | G24: 46027 | H24: 158 | I24: 89116 | J24: C2D VENTURES -964.pdf | K24: - | L24: - | M24: =IF(G24="", "", (TODAY() - G24) & " Days") -> 161 Days | N24: =IF($A$3=" "," ", IFERROR( VLOOKUP($A24,'SUPPLIER DATA BASE'!$A$2:$O$936,11,0),"")) -> C2D VENTURES LLP | O24: =IF($A$3=" "," ", IFERROR( VLOOKUP($A24,'SUPPLIER DATA BASE'!$A$2:$O$936,12,0),"")) -> 50484840037 | P24: =IF($A$3=" "," ", IFERROR( VLOOKUP($A24,'SUPPLIER DATA BASE'!$A$2:$O$936,13,0),"")) -> IDIB000D600 | V24: =IF(G24="","", IF(AND(G24>=DATE(2024,4,1),G24<=DATE(2025,3,31)),"FY 24-25", IF(AND(G24>=DATE(2025,4,1),G24<=DATE(2026,3,31)),"FY 25-26",IF(AND(G24>=DATE(2026,4,1),G24<=DATE(2027,3,31)),"FY 26-27","")))) -> FY 25-26
A25: DIL SE | B25: =IF($A$3=" "," ", IFERROR( VLOOKUP($A25,'SUPPLIER DATA BASE'!$A$2:$M$936,3,0),"")) -> - | C25: =IF($A$3=" "," ", IFERROR( VLOOKUP($A25,'SUPPLIER DATA BASE'!$A$2:$F$936,6,0),"")) -> - | D25: =IF($A$3=" "," ", IFERROR( VLOOKUP($A25,'SUPPLIER DATA BASE'!$A$2:$G$936,4,0),"")) -> - | E25: =IF($A$3=" "," ", IFERROR( VLOOKUP($A25,'SUPPLIER DATA BASE'!$A$2:$H$936,5,0),"")) -> - | F25: 2025-26/1316 | G25: 46028 | H25: 1 | I25: 3245 | J25: Dil se 1316.pdf | K25: - | L25: - | M25: =IF(G25="", "", (TODAY() - G25) & " Days") -> 160 Days | N25: =IF($A$3=" "," ", IFERROR( VLOOKUP($A25,'SUPPLIER DATA BASE'!$A$2:$O$936,11,0),"")) -> DIL SE | O25: =IF($A$3=" "," ", IFERROR( VLOOKUP($A25,'SUPPLIER DATA BASE'!$A$2:$O$936,12,0),"")) -> 11197610000574 | P25: =IF($A$3=" "," ", IFERROR( VLOOKUP($A25,'SUPPLIER DATA BASE'!$A$2:$O$936,13,0),"")) -> HDFC0001119 | V25: =IF(G25="","", IF(AND(G25>=DATE(2024,4,1),G25<=DATE(2025,3,31)),"FY 24-25", IF(AND(G25>=DATE(2025,4,1),G25<=DATE(2026,3,31)),"FY 25-26",IF(AND(G25>=DATE(2026,4,1),G25<=DATE(2027,3,31)),"FY 26-27","")))) -> FY 25-26
A26: SARAOGI SUPER SALES PVT LTD | B26: =IF($A$3=" "," ", IFERROR( VLOOKUP($A26,'SUPPLIER DATA BASE'!$A$2:$M$936,3,0),"")) -> - | C26: =IF($A$3=" "," ", IFERROR( VLOOKUP($A26,'SUPPLIER DATA BASE'!$A$2:$F$936,6,0),"")) -> - | D26: =IF($A$3=" "," ", IFERROR( VLOOKUP($A26,'SUPPLIER DATA BASE'!$A$2:$G$936,4,0),"")) -> - | E26: =IF($A$3=" "," ", IFERROR( VLOOKUP($A26,'SUPPLIER DATA BASE'!$A$2:$H$936,5,0),"")) -> - | F26: 25-26/BBS13151 | G26: 46030 | H26: 4 | I26: 7049 | J26: Saraogi Super Sales 13151.pdf | K26: - | L26: - | M26: =IF(G26="", "", (TODAY() - G26) & " Days") -> 158 Days | N26: =IF($A$3=" "," ", IFERROR( VLOOKUP($A26,'SUPPLIER DATA BASE'!$A$2:$O$936,11,0),"")) -> SARAOGI SUPER SALES PVT LTD | O26: =IF($A$3=" "," ", IFERROR( VLOOKUP($A26,'SUPPLIER DATA BASE'!$A$2:$O$936,12,0),"")) -> SASUSP011006 | P26: =IF($A$3=" "," ", IFERROR( VLOOKUP($A26,'SUPPLIER DATA BASE'!$A$2:$O$936,13,0),"")) -> ICIC0000106 | V26: =IF(G26="","", IF(AND(G26>=DATE(2024,4,1),G26<=DATE(2025,3,31)),"FY 24-25", IF(AND(G26>=DATE(2025,4,1),G26<=DATE(2026,3,31)),"FY 25-26",IF(AND(G26>=DATE(2026,4,1),G26<=DATE(2027,3,31)),"FY 26-27","")))) -> FY 25-26
A27: KIRAN CREATION | B27: =IF($A$3=" "," ", IFERROR( VLOOKUP($A27,'SUPPLIER DATA BASE'!$A$2:$M$936,3,0),"")) -> - | C27: =IF($A$3=" "," ", IFERROR( VLOOKUP($A27,'SUPPLIER DATA BASE'!$A$2:$F$936,6,0),"")) -> - | D27: =IF($A$3=" "," ", IFERROR( VLOOKUP($A27,'SUPPLIER DATA BASE'!$A$2:$G$936,4,0),"")) -> - | E27: =IF($A$3=" "," ", IFERROR( VLOOKUP($A27,'SUPPLIER DATA BASE'!$A$2:$H$936,5,0),"")) -> - | F27: SOCCRS25/770 | G27: 46032 | H27: 104 | I27: 11152 | J27: KIRAN CREATION -770.pdf | K27: - | L27: - | M27: =IF(G27="", "", (TODAY() - G27) & " Days") -> 156 Days | N27: =IF($A$3=" "," ", IFERROR( VLOOKUP($A27,'SUPPLIER DATA BASE'!$A$2:$O$936,11,0),"")) -> KIRAN CREATION | O27: =IF($A$3=" "," ", IFERROR( VLOOKUP($A27,'SUPPLIER DATA BASE'!$A$2:$O$936,12,0),"")) -> 50200007524171 | P27: =IF($A$3=" "," ", IFERROR( VLOOKUP($A27,'SUPPLIER DATA BASE'!$A$2:$O$936,13,0),"")) -> HDFC0000765 | V27: =IF(G27="","", IF(AND(G27>=DATE(2024,4,1),G27<=DATE(2025,3,31)),"FY 24-25", IF(AND(G27>=DATE(2025,4,1),G27<=DATE(2026,3,31)),"FY 25-26",IF(AND(G27>=DATE(2026,4,1),G27<=DATE(2027,3,31)),"FY 26-27","")))) -> FY 25-26
A28: C2D VENTURES LLP | B28: =IF($A$3=" "," ", IFERROR( VLOOKUP($A28,'SUPPLIER DATA BASE'!$A$2:$M$936,3,0),"")) -> WELSPUN, VAN HEUSEN | C28: =IF($A$3=" "," ", IFERROR( VLOOKUP($A28,'SUPPLIER DATA BASE'!$A$2:$F$936,6,0),"")) -> DIRECT | D28: =IF($A$3=" "," ", IFERROR( VLOOKUP($A28,'SUPPLIER DATA BASE'!$A$2:$G$936,4,0),"")) -> 15 | E28: =IF($A$3=" "," ", IFERROR( VLOOKUP($A28,'SUPPLIER DATA BASE'!$A$2:$H$936,5,0),"")) -> 5 | F28: IH/25-26/984 | G28: 46034 | H28: 60 | I28: 20604 | J28: C2D VENTURES -984.pdf | K28: - | L28: - | M28: =IF(G28="", "", (TODAY() - G28) & " Days") -> 154 Days | N28: =IF($A$3=" "," ", IFERROR( VLOOKUP($A28,'SUPPLIER DATA BASE'!$A$2:$O$936,11,0),"")) -> C2D VENTURES LLP | O28: =IF($A$3=" "," ", IFERROR( VLOOKUP($A28,'SUPPLIER DATA BASE'!$A$2:$O$936,12,0),"")) -> 50484840037 | P28: =IF($A$3=" "," ", IFERROR( VLOOKUP($A28,'SUPPLIER DATA BASE'!$A$2:$O$936,13,0),"")) -> IDIB000D600 | V28: =IF(G28="","", IF(AND(G28>=DATE(2024,4,1),G28<=DATE(2025,3,31)),"FY 24-25", IF(AND(G28>=DATE(2025,4,1),G28<=DATE(2026,3,31)),"FY 25-26",IF(AND(G28>=DATE(2026,4,1),G28<=DATE(2027,3,31)),"FY 26-27","")))) -> FY 25-26
A29: SHRIJEE ENTERPRISES | B29: =IF($A$3=" "," ", IFERROR( VLOOKUP($A29,'SUPPLIER DATA BASE'!$A$2:$M$936,3,0),"")) -> - | C29: =IF($A$3=" "," ", IFERROR( VLOOKUP($A29,'SUPPLIER DATA BASE'!$A$2:$F$936,6,0),"")) -> - | D29: =IF($A$3=" "," ", IFERROR( VLOOKUP($A29,'SUPPLIER DATA BASE'!$A$2:$G$936,4,0),"")) -> - | E29: =IF($A$3=" "," ", IFERROR( VLOOKUP($A29,'SUPPLIER DATA BASE'!$A$2:$H$936,5,0),"")) -> - | F29: THCRS25/430 | G29: 46034 | H29: 45 | I29: 27257 | J29: SHRIJEE ENTERPRISES -430.pdf | K29: - | L29: - | M29: =IF(G29="", "", (TODAY() - G29) & " Days") -> 154 Days | N29: =IF($A$3=" "," ", IFERROR( VLOOKUP($A29,'SUPPLIER DATA BASE'!$A$2:$O$936,11,0),"")) -> SHRIJEE ENTERPRISES | O29: =IF($A$3=" "," ", IFERROR( VLOOKUP($A29,'SUPPLIER DATA BASE'!$A$2:$O$936,12,0),"")) -> 31849543930 | P29: =IF($A$3=" "," ", IFERROR( VLOOKUP($A29,'SUPPLIER DATA BASE'!$A$2:$O$936,13,0),"")) -> SBIN0001521 | V29: =IF(G29="","", IF(AND(G29>=DATE(2024,4,1),G29<=DATE(2025,3,31)),"FY 24-25", IF(AND(G29>=DATE(2025,4,1),G29<=DATE(2026,3,31)),"FY 25-26",IF(AND(G29>=DATE(2026,4,1),G29<=DATE(2027,3,31)),"FY 26-27","")))) -> FY 25-26
A30: TATHASTU ENTERPRISE | B30: =IF($A$3=" "," ", IFERROR( VLOOKUP($A30,'SUPPLIER DATA BASE'!$A$2:$M$936,3,0),"")) -> - | C30: =IF($A$3=" "," ", IFERROR( VLOOKUP($A30,'SUPPLIER DATA BASE'!$A$2:$F$936,6,0),"")) -> SURYAM TEXTILE AGENCY | D30: =IF($A$3=" "," ", IFERROR( VLOOKUP($A30,'SUPPLIER DATA BASE'!$A$2:$G$936,4,0),"")) -> 50 | E30: =IF($A$3=" "," ", IFERROR( VLOOKUP($A30,'SUPPLIER DATA BASE'!$A$2:$H$936,5,0),"")) -> 10% IN BILL | F30: 8579 | G30: 46034 | H30: 25 | I30: 81731 | J30: Tathastu enterprise 8579.pdf | K30: - | L30: - | M30: =IF(G30="", "", (TODAY() - G30) & " Days") -> 154 Days | N30: =IF($A$3=" "," ", IFERROR( VLOOKUP($A30,'SUPPLIER DATA BASE'!$A$2:$O$936,11,0),"")) -> TATHASTU ENTERPRISE | O30: =IF($A$3=" "," ", IFERROR( VLOOKUP($A30,'SUPPLIER DATA BASE'!$A$2:$O$936,12,0),"")) -> 50200043443581 | P30: =IF($A$3=" "," ", IFERROR( VLOOKUP($A30,'SUPPLIER DATA BASE'!$A$2:$O$936,13,0),"")) -> HDFC0001704 | Q30: 81731 | R30: 46080 | V30: =IF(G30="","", IF(AND(G30>=DATE(2024,4,1),G30<=DATE(2025,3,31)),"FY 24-25", IF(AND(G30>=DATE(2025,4,1),G30<=DATE(2026,3,31)),"FY 25-26",IF(AND(G30>=DATE(2026,4,1),G30<=DATE(2027,3,31)),"FY 26-27","")))) -> FY 25-26
A31: JAIN ADISHWAR HOSIERY WORKS LLP | B31: =IF($A$3=" "," ", IFERROR( VLOOKUP($A31,'SUPPLIER DATA BASE'!$A$2:$M$936,3,0),"")) -> - | C31: =IF($A$3=" "," ", IFERROR( VLOOKUP($A31,'SUPPLIER DATA BASE'!$A$2:$F$936,6,0),"")) -> - | D31: =IF($A$3=" "," ", IFERROR( VLOOKUP($A31,'SUPPLIER DATA BASE'!$A$2:$G$936,4,0),"")) -> - | E31: =IF($A$3=" "," ", IFERROR( VLOOKUP($A31,'SUPPLIER DATA BASE'!$A$2:$H$936,5,0),"")) -> - | F31: J/25-26/10186 | G31: 46035 | H31: 72 | I31: 208983 | J31: JAIN ADISHWAR -10186.pdf | K31: - | L31: - | M31: =IF(G31="", "", (TODAY() - G31) & " Days") -> 153 Days | N31: =IF($A$3=" "," ", IFERROR( VLOOKUP($A31,'SUPPLIER DATA BASE'!$A$2:$O$936,11,0),"")) -> JAIN ADISHWAR HOSIERY WORKS LLP | O31: =IF($A$3=" "," ", IFERROR( VLOOKUP($A31,'SUPPLIER DATA BASE'!$A$2:$O$936,12,0),"")) -> 99917644444444 | P31: =IF($A$3=" "," ", IFERROR( VLOOKUP($A31,'SUPPLIER DATA BASE'!$A$2:$O$936,13,0),"")) -> HDFC0002063 | V31: =IF(G31="","", IF(AND(G31>=DATE(2024,4,1),G31<=DATE(2025,3,31)),"FY 24-25", IF(AND(G31>=DATE(2025,4,1),G31<=DATE(2026,3,31)),"FY 25-26",IF(AND(G31>=DATE(2026,4,1),G31<=DATE(2027,3,31)),"FY 26-27","")))) -> FY 25-26
A32: SHRITHIK DESIGNER LLP | B32: =IF($A$3=" "," ", IFERROR( VLOOKUP($A32,'SUPPLIER DATA BASE'!$A$2:$M$936,3,0),"")) -> - | C32: =IF($A$3=" "," ", IFERROR( VLOOKUP($A32,'SUPPLIER DATA BASE'!$A$2:$F$936,6,0),"")) -> SURYAM TEXTILE AGENCY | D32: =IF($A$3=" "," ", IFERROR( VLOOKUP($A32,'SUPPLIER DATA BASE'!$A$2:$G$936,4,0),"")) -> NO | E32: =IF($A$3=" "," ", IFERROR( VLOOKUP($A32,'SUPPLIER DATA BASE'!$A$2:$H$936,5,0),"")) -> - | F32: 19541 | G32: 46035 | H32: 62 | I32: 54167 | J32: SHRITHIK DESIGNER -1953.pdf | K32: - | L32: - | M32: =IF(G32="", "", (TODAY() - G32) & " Days") -> 153 Days | N32: =IF($A$3=" "," ", IFERROR( VLOOKUP($A32,'SUPPLIER DATA BASE'!$A$2:$O$936,11,0),"")) -> SHRITHIK DESIGNER LLP | O32: =IF($A$3=" "," ", IFERROR( VLOOKUP($A32,'SUPPLIER DATA BASE'!$A$2:$O$936,12,0),"")) -> 339805000598 | P32: =IF($A$3=" "," ", IFERROR( VLOOKUP($A32,'SUPPLIER DATA BASE'!$A$2:$O$936,13,0),"")) -> ICIC0003398 | Q32: 54167 | R32: 46131 | V32: =IF(G32="","", IF(AND(G32>=DATE(2024,4,1),G32<=DATE(2025,3,31)),"FY 24-25", IF(AND(G32>=DATE(2025,4,1),G32<=DATE(2026,3,31)),"FY 25-26",IF(AND(G32>=DATE(2026,4,1),G32<=DATE(2027,3,31)),"FY 26-27","")))) -> FY 25-26
A33: UNNATI CREATION | B33: =IF($A$3=" "," ", IFERROR( VLOOKUP($A33,'SUPPLIER DATA BASE'!$A$2:$M$936,3,0),"")) -> - | C33: =IF($A$3=" "," ", IFERROR( VLOOKUP($A33,'SUPPLIER DATA BASE'!$A$2:$F$936,6,0),"")) -> SURYAM TEXTILE AGENCY | D33: =IF($A$3=" "," ", IFERROR( VLOOKUP($A33,'SUPPLIER DATA BASE'!$A$2:$G$936,4,0),"")) -> 60 | E33: =IF($A$3=" "," ", IFERROR( VLOOKUP($A33,'SUPPLIER DATA BASE'!$A$2:$H$936,5,0),"")) -> 5% IN BILL | F33: 416/PF | G33: 46035 | H33: 29 | I33: 51401 | J33: Unnati creation 416.pdf | K33: - | L33: - | M33: =IF(G33="", "", (TODAY() - G33) & " Days") -> 153 Days | N33: =IF($A$3=" "," ", IFERROR( VLOOKUP($A33,'SUPPLIER DATA BASE'!$A$2:$O$936,11,0),"")) -> UNNATI CREATION | O33: =IF($A$3=" "," ", IFERROR( VLOOKUP($A33,'SUPPLIER DATA BASE'!$A$2:$O$936,12,0),"")) -> 99992001015861 | P33: =IF($A$3=" "," ", IFERROR( VLOOKUP($A33,'SUPPLIER DATA BASE'!$A$2:$O$936,13,0),"")) -> GSCB0ASCB02 | Q33: 51401 | R33: 46080 | V33: =IF(G33="","", IF(AND(G33>=DATE(2024,4,1),G33<=DATE(2025,3,31)),"FY 24-25", IF(AND(G33>=DATE(2025,4,1),G33<=DATE(2026,3,31)),"FY 25-26",IF(AND(G33>=DATE(2026,4,1),G33<=DATE(2027,3,31)),"FY 26-27","")))) -> FY 25-26
A34: AS TEXTILE | B34: =IF($A$3=" "," ", IFERROR( VLOOKUP($A34,'SUPPLIER DATA BASE'!$A$2:$M$936,3,0),"")) -> - | C34: =IF($A$3=" "," ", IFERROR( VLOOKUP($A34,'SUPPLIER DATA BASE'!$A$2:$F$936,6,0),"")) -> SURYAM TEXTILE AGENCY | D34: =IF($A$3=" "," ", IFERROR( VLOOKUP($A34,'SUPPLIER DATA BASE'!$A$2:$G$936,4,0),"")) -> 30 | E34: =IF($A$3=" "," ", IFERROR( VLOOKUP($A34,'SUPPLIER DATA BASE'!$A$2:$H$936,5,0),"")) -> 0.09 | F34: 131 | G34: 46035 | H34: 2 | I34: 17388 | J34: A S Textile 131.pdf | K34: - | L34: - | M34: =IF(G34="", "", (TODAY() - G34) & " Days") -> 153 Days | N34: =IF($A$3=" "," ", IFERROR( VLOOKUP($A34,'SUPPLIER DATA BASE'!$A$2:$O$936,11,0),"")) -> AS TEXTILE | O34: =IF($A$3=" "," ", IFERROR( VLOOKUP($A34,'SUPPLIER DATA BASE'!$A$2:$O$936,12,0),"")) -> 50200012846193 | P34: =IF($A$3=" "," ", IFERROR( VLOOKUP($A34,'SUPPLIER DATA BASE'!$A$2:$O$936,13,0),"")) -> HDFC0001249 | Q34: 17388 | R34: 46064 | V34: =IF(G34="","", IF(AND(G34>=DATE(2024,4,1),G34<=DATE(2025,3,31)),"FY 24-25", IF(AND(G34>=DATE(2025,4,1),G34<=DATE(2026,3,31)),"FY 25-26",IF(AND(G34>=DATE(2026,4,1),G34<=DATE(2027,3,31)),"FY 26-27","")))) -> FY 25-26
A35: AS TEXTILE | B35: =IF($A$3=" "," ", IFERROR( VLOOKUP($A35,'SUPPLIER DATA BASE'!$A$2:$M$936,3,0),"")) -> - | C35: =IF($A$3=" "," ", IFERROR( VLOOKUP($A35,'SUPPLIER DATA BASE'!$A$2:$F$936,6,0),"")) -> SURYAM TEXTILE AGENCY | D35: =IF($A$3=" "," ", IFERROR( VLOOKUP($A35,'SUPPLIER DATA BASE'!$A$2:$G$936,4,0),"")) -> 30 | E35: =IF($A$3=" "," ", IFERROR( VLOOKUP($A35,'SUPPLIER DATA BASE'!$A$2:$H$936,5,0),"")) -> 0.09 | F35: 132 | G35: 46035 | H35: 2 | I35: 17388 | J35: A S Textile 132.pdf | K35: - | L35: - | M35: =IF(G35="", "", (TODAY() - G35) & " Days") -> 153 Days | N35: =IF($A$3=" "," ", IFERROR( VLOOKUP($A35,'SUPPLIER DATA BASE'!$A$2:$O$936,11,0),"")) -> AS TEXTILE | O35: =IF($A$3=" "," ", IFERROR( VLOOKUP($A35,'SUPPLIER DATA BASE'!$A$2:$O$936,12,0),"")) -> 50200012846193 | P35: =IF($A$3=" "," ", IFERROR( VLOOKUP($A35,'SUPPLIER DATA BASE'!$A$2:$O$936,13,0),"")) -> HDFC0001249 | Q35: 17388 | R35: 46064 | V35: =IF(G35="","", IF(AND(G35>=DATE(2024,4,1),G35<=DATE(2025,3,31)),"FY 24-25", IF(AND(G35>=DATE(2025,4,1),G35<=DATE(2026,3,31)),"FY 25-26",IF(AND(G35>=DATE(2026,4,1),G35<=DATE(2027,3,31)),"FY 26-27","")))) -> FY 25-26
A36: AS TEXTILE | B36: =IF($A$3=" "," ", IFERROR( VLOOKUP($A36,'SUPPLIER DATA BASE'!$A$2:$M$936,3,0),"")) -> - | C36: =IF($A$3=" "," ", IFERROR( VLOOKUP($A36,'SUPPLIER DATA BASE'!$A$2:$F$936,6,0),"")) -> SURYAM TEXTILE AGENCY | D36: =IF($A$3=" "," ", IFERROR( VLOOKUP($A36,'SUPPLIER DATA BASE'!$A$2:$G$936,4,0),"")) -> 30 | E36: =IF($A$3=" "," ", IFERROR( VLOOKUP($A36,'SUPPLIER DATA BASE'!$A$2:$H$936,5,0),"")) -> 0.09 | F36: 125 | G36: 46035 | H36: 2 | I36: 15215 | J36: A S Textile 125.pdf | K36: - | L36: - | M36: =IF(G36="", "", (TODAY() - G36) & " Days") -> 153 Days | N36: =IF($A$3=" "," ", IFERROR( VLOOKUP($A36,'SUPPLIER DATA BASE'!$A$2:$O$936,11,0),"")) -> AS TEXTILE | O36: =IF($A$3=" "," ", IFERROR( VLOOKUP($A36,'SUPPLIER DATA BASE'!$A$2:$O$936,12,0),"")) -> 50200012846193 | P36: =IF($A$3=" "," ", IFERROR( VLOOKUP($A36,'SUPPLIER DATA BASE'!$A$2:$O$936,13,0),"")) -> HDFC0001249 | Q36: 15215 | R36: 46064 | V36: =IF(G36="","", IF(AND(G36>=DATE(2024,4,1),G36<=DATE(2025,3,31)),"FY 24-25", IF(AND(G36>=DATE(2025,4,1),G36<=DATE(2026,3,31)),"FY 25-26",IF(AND(G36>=DATE(2026,4,1),G36<=DATE(2027,3,31)),"FY 26-27","")))) -> FY 25-26
A37: AS TEXTILE | B37: =IF($A$3=" "," ", IFERROR( VLOOKUP($A37,'SUPPLIER DATA BASE'!$A$2:$M$936,3,0),"")) -> - | C37: =IF($A$3=" "," ", IFERROR( VLOOKUP($A37,'SUPPLIER DATA BASE'!$A$2:$F$936,6,0),"")) -> SURYAM TEXTILE AGENCY | D37: =IF($A$3=" "," ", IFERROR( VLOOKUP($A37,'SUPPLIER DATA BASE'!$A$2:$G$936,4,0),"")) -> 30 | E37: =IF($A$3=" "," ", IFERROR( VLOOKUP($A37,'SUPPLIER DATA BASE'!$A$2:$H$936,5,0),"")) -> 0.09 | F37: 122 | G37: 46035 | H37: 4 | I37: 10601 | J37: A S Textile 122.pdf | K37: - | L37: - | M37: =IF(G37="", "", (TODAY() - G37) & " Days") -> 153 Days | N37: =IF($A$3=" "," ", IFERROR( VLOOKUP($A37,'SUPPLIER DATA BASE'!$A$2:$O$936,11,0),"")) -> AS TEXTILE | O37: =IF($A$3=" "," ", IFERROR( VLOOKUP($A37,'SUPPLIER DATA BASE'!$A$2:$O$936,12,0),"")) -> 50200012846193 | P37: =IF($A$3=" "," ", IFERROR( VLOOKUP($A37,'SUPPLIER DATA BASE'!$A$2:$O$936,13,0),"")) -> HDFC0001249 | Q37: 10601 | R37: 46064 | V37: =IF(G37="","", IF(AND(G37>=DATE(2024,4,1),G37<=DATE(2025,3,31)),"FY 24-25", IF(AND(G37>=DATE(2025,4,1),G37<=DATE(2026,3,31)),"FY 25-26",IF(AND(G37>=DATE(2026,4,1),G37<=DATE(2027,3,31)),"FY 26-27","")))) -> FY 25-26
A38: AS TEXTILE | B38: =IF($A$3=" "," ", IFERROR( VLOOKUP($A38,'SUPPLIER DATA BASE'!$A$2:$M$936,3,0),"")) -> - | C38: =IF($A$3=" "," ", IFERROR( VLOOKUP($A38,'SUPPLIER DATA BASE'!$A$2:$F$936,6,0),"")) -> SURYAM TEXTILE AGENCY | D38: =IF($A$3=" "," ", IFERROR( VLOOKUP($A38,'SUPPLIER DATA BASE'!$A$2:$G$936,4,0),"")) -> 30 | E38: =IF($A$3=" "," ", IFERROR( VLOOKUP($A38,'SUPPLIER DATA BASE'!$A$2:$H$936,5,0),"")) -> 0.09 | F38: 135 | G38: 46035 | H38: 3 | I38: 23643 | J38: A S Textile 135.pdf | K38: - | L38: - | M38: =IF(G38="", "", (TODAY() - G38) & " Days") -> 153 Days | N38: =IF($A$3=" "," ", IFERROR( VLOOKUP($A38,'SUPPLIER DATA BASE'!$A$2:$O$936,11,0),"")) -> AS TEXTILE | O38: =IF($A$3=" "," ", IFERROR( VLOOKUP($A38,'SUPPLIER DATA BASE'!$A$2:$O$936,12,0),"")) -> 50200012846193 | P38: =IF($A$3=" "," ", IFERROR( VLOOKUP($A38,'SUPPLIER DATA BASE'!$A$2:$O$936,13,0),"")) -> HDFC0001249 | Q38: 3396 | R38: 46064 | S38: 20247 | V38: =IF(G38="","", IF(AND(G38>=DATE(2024,4,1),G38<=DATE(2025,3,31)),"FY 24-25", IF(AND(G38>=DATE(2025,4,1),G38<=DATE(2026,3,31)),"FY 25-26",IF(AND(G38>=DATE(2026,4,1),G38<=DATE(2027,3,31)),"FY 26-27","")))) -> FY 25-26
A39: AS TEXTILE | B39: =IF($A$3=" "," ", IFERROR( VLOOKUP($A39,'SUPPLIER DATA BASE'!$A$2:$M$936,3,0),"")) -> - | C39: =IF($A$3=" "," ", IFERROR( VLOOKUP($A39,'SUPPLIER DATA BASE'!$A$2:$F$936,6,0),"")) -> SURYAM TEXTILE AGENCY | D39: =IF($A$3=" "," ", IFERROR( VLOOKUP($A39,'SUPPLIER DATA BASE'!$A$2:$G$936,4,0),"")) -> 30 | E39: =IF($A$3=" "," ", IFERROR( VLOOKUP($A39,'SUPPLIER DATA BASE'!$A$2:$H$936,5,0),"")) -> 0.09 | F39: 134 | G39: 46035 | H39: 2 | I39: 13402 | J39: A S Textile 134.pdf | K39: - | L39: - | M39: =IF(G39="", "", (TODAY() - G39) & " Days") -> 153 Days | N39: =IF($A$3=" "," ", IFERROR( VLOOKUP($A39,'SUPPLIER DATA BASE'!$A$2:$O$936,11,0),"")) -> AS TEXTILE | O39: =IF($A$3=" "," ", IFERROR( VLOOKUP($A39,'SUPPLIER DATA BASE'!$A$2:$O$936,12,0),"")) -> 50200012846193 | P39: =IF($A$3=" "," ", IFERROR( VLOOKUP($A39,'SUPPLIER DATA BASE'!$A$2:$O$936,13,0),"")) -> HDFC0001249 | Q39: 13402 | R39: 46064 | V39: =IF(G39="","", IF(AND(G39>=DATE(2024,4,1),G39<=DATE(2025,3,31)),"FY 24-25", IF(AND(G39>=DATE(2025,4,1),G39<=DATE(2026,3,31)),"FY 25-26",IF(AND(G39>=DATE(2026,4,1),G39<=DATE(2027,3,31)),"FY 26-27","")))) -> FY 25-26
A40: AS TEXTILE | B40: =IF($A$3=" "," ", IFERROR( VLOOKUP($A40,'SUPPLIER DATA BASE'!$A$2:$M$936,3,0),"")) -> - | C40: =IF($A$3=" "," ", IFERROR( VLOOKUP($A40,'SUPPLIER DATA BASE'!$A$2:$F$936,6,0),"")) -> SURYAM TEXTILE AGENCY | D40: =IF($A$3=" "," ", IFERROR( VLOOKUP($A40,'SUPPLIER DATA BASE'!$A$2:$G$936,4,0),"")) -> 30 | E40: =IF($A$3=" "," ", IFERROR( VLOOKUP($A40,'SUPPLIER DATA BASE'!$A$2:$H$936,5,0),"")) -> 0.09 | F40: 120 | G40: 46035 | H40: 4 | I40: 14200 | J40: A S Textile 120.pdf | K40: - | L40: - | M40: =IF(G40="", "", (TODAY() - G40) & " Days") -> 153 Days | N40: =IF($A$3=" "," ", IFERROR( VLOOKUP($A40,'SUPPLIER DATA BASE'!$A$2:$O$936,11,0),"")) -> AS TEXTILE | O40: =IF($A$3=" "," ", IFERROR( VLOOKUP($A40,'SUPPLIER DATA BASE'!$A$2:$O$936,12,0),"")) -> 50200012846193 | P40: =IF($A$3=" "," ", IFERROR( VLOOKUP($A40,'SUPPLIER DATA BASE'!$A$2:$O$936,13,0),"")) -> HDFC0001249 | Q40: 14200 | R40: 46064 | V40: =IF(G40="","", IF(AND(G40>=DATE(2024,4,1),G40<=DATE(2025,3,31)),"FY 24-25", IF(AND(G40>=DATE(2025,4,1),G40<=DATE(2026,3,31)),"FY 25-26",IF(AND(G40>=DATE(2026,4,1),G40<=DATE(2027,3,31)),"FY 26-27","")))) -> FY 25-26
A41: AS TEXTILE | B41: =IF($A$3=" "," ", IFERROR( VLOOKUP($A41,'SUPPLIER DATA BASE'!$A$2:$M$936,3,0),"")) -> - | C41: =IF($A$3=" "," ", IFERROR( VLOOKUP($A41,'SUPPLIER DATA BASE'!$A$2:$F$936,6,0),"")) -> SURYAM TEXTILE AGENCY | D41: =IF($A$3=" "," ", IFERROR( VLOOKUP($A41,'SUPPLIER DATA BASE'!$A$2:$G$936,4,0),"")) -> 30 | E41: =IF($A$3=" "," ", IFERROR( VLOOKUP($A41,'SUPPLIER DATA BASE'!$A$2:$H$936,5,0),"")) -> 0.09 | F41: 121 | G41: 46035 | H41: 4 | I41: 9416 | J41: A S Textile 121.pdf | K41: - | L41: - | M41: =IF(G41="", "", (TODAY() - G41) & " Days") -> 153 Days | N41: =IF($A$3=" "," ", IFERROR( VLOOKUP($A41,'SUPPLIER DATA BASE'!$A$2:$O$936,11,0),"")) -> AS TEXTILE | O41: =IF($A$3=" "," ", IFERROR( VLOOKUP($A41,'SUPPLIER DATA BASE'!$A$2:$O$936,12,0),"")) -> 50200012846193 | P41: =IF($A$3=" "," ", IFERROR( VLOOKUP($A41,'SUPPLIER DATA BASE'!$A$2:$O$936,13,0),"")) -> HDFC0001249 | Q41: 9416 | R41: 46064 | V41: =IF(G41="","", IF(AND(G41>=DATE(2024,4,1),G41<=DATE(2025,3,31)),"FY 24-25", IF(AND(G41>=DATE(2025,4,1),G41<=DATE(2026,3,31)),"FY 25-26",IF(AND(G41>=DATE(2026,4,1),G41<=DATE(2027,3,31)),"FY 26-27","")))) -> FY 25-26
A42: AS TEXTILE | B42: =IF($A$3=" "," ", IFERROR( VLOOKUP($A42,'SUPPLIER DATA BASE'!$A$2:$M$936,3,0),"")) -> - | C42: =IF($A$3=" "," ", IFERROR( VLOOKUP($A42,'SUPPLIER DATA BASE'!$A$2:$F$936,6,0),"")) -> SURYAM TEXTILE AGENCY | D42: =IF($A$3=" "," ", IFERROR( VLOOKUP($A42,'SUPPLIER DATA BASE'!$A$2:$G$936,4,0),"")) -> 30 | E42: =IF($A$3=" "," ", IFERROR( VLOOKUP($A42,'SUPPLIER DATA BASE'!$A$2:$H$936,5,0),"")) -> 0.09 | F42: 119 | G42: 46035 | H42: 4 | I42: 11592 | J42: A S Textile 119.pdf | K42: - | L42: - | M42: =IF(G42="", "", (TODAY() - G42) & " Days") -> 153 Days | N42: =IF($A$3=" "," ", IFERROR( VLOOKUP($A42,'SUPPLIER DATA BASE'!$A$2:$O$936,11,0),"")) -> AS TEXTILE | O42: =IF($A$3=" "," ", IFERROR( VLOOKUP($A42,'SUPPLIER DATA BASE'!$A$2:$O$936,12,0),"")) -> 50200012846193 | P42: =IF($A$3=" "," ", IFERROR( VLOOKUP($A42,'SUPPLIER DATA BASE'!$A$2:$O$936,13,0),"")) -> HDFC0001249 | Q42: 11592 | R42: 46064 | V42: =IF(G42="","", IF(AND(G42>=DATE(2024,4,1),G42<=DATE(2025,3,31)),"FY 24-25", IF(AND(G42>=DATE(2025,4,1),G42<=DATE(2026,3,31)),"FY 25-26",IF(AND(G42>=DATE(2026,4,1),G42<=DATE(2027,3,31)),"FY 26-27","")))) -> FY 25-26
A43: AS TEXTILE | B43: =IF($A$3=" "," ", IFERROR( VLOOKUP($A43,'SUPPLIER DATA BASE'!$A$2:$M$936,3,0),"")) -> - | C43: =IF($A$3=" "," ", IFERROR( VLOOKUP($A43,'SUPPLIER DATA BASE'!$A$2:$F$936,6,0),"")) -> SURYAM TEXTILE AGENCY | D43: =IF($A$3=" "," ", IFERROR( VLOOKUP($A43,'SUPPLIER DATA BASE'!$A$2:$G$936,4,0),"")) -> 30 | E43: =IF($A$3=" "," ", IFERROR( VLOOKUP($A43,'SUPPLIER DATA BASE'!$A$2:$H$936,5,0),"")) -> 0.09 | F43: 118 | G43: 46035 | H43: 4 | I43: 11084 | J43: A S Textile 118.pdf | K43: - | L43: - | M43: =IF(G43="", "", (TODAY() - G43) & " Days") -> 153 Days | N43: =IF($A$3=" "," ", IFERROR( VLOOKUP($A43,'SUPPLIER DATA BASE'!$A$2:$O$936,11,0),"")) -> AS TEXTILE | O43: =IF($A$3=" "," ", IFERROR( VLOOKUP($A43,'SUPPLIER DATA BASE'!$A$2:$O$936,12,0),"")) -> 50200012846193 | P43: =IF($A$3=" "," ", IFERROR( VLOOKUP($A43,'SUPPLIER DATA BASE'!$A$2:$O$936,13,0),"")) -> HDFC0001249 | Q43: 11084 | R43: 46064 | V43: =IF(G43="","", IF(AND(G43>=DATE(2024,4,1),G43<=DATE(2025,3,31)),"FY 24-25", IF(AND(G43>=DATE(2025,4,1),G43<=DATE(2026,3,31)),"FY 25-26",IF(AND(G43>=DATE(2026,4,1),G43<=DATE(2027,3,31)),"FY 26-27","")))) -> FY 25-26
A44: AS TEXTILE | B44: =IF($A$3=" "," ", IFERROR( VLOOKUP($A44,'SUPPLIER DATA BASE'!$A$2:$M$936,3,0),"")) -> - | C44: =IF($A$3=" "," ", IFERROR( VLOOKUP($A44,'SUPPLIER DATA BASE'!$A$2:$F$936,6,0),"")) -> SURYAM TEXTILE AGENCY | D44: =IF($A$3=" "," ", IFERROR( VLOOKUP($A44,'SUPPLIER DATA BASE'!$A$2:$G$936,4,0),"")) -> 30 | E44: =IF($A$3=" "," ", IFERROR( VLOOKUP($A44,'SUPPLIER DATA BASE'!$A$2:$H$936,5,0),"")) -> 0.09 | F44: 133 | G44: 46035 | H44: 2 | I44: 16300 | J44: A S Textile 133.pdf | K44: - | L44: - | M44: =IF(G44="", "", (TODAY() - G44) & " Days") -> 153 Days | N44: =IF($A$3=" "," ", IFERROR( VLOOKUP($A44,'SUPPLIER DATA BASE'!$A$2:$O$936,11,0),"")) -> AS TEXTILE | O44: =IF($A$3=" "," ", IFERROR( VLOOKUP($A44,'SUPPLIER DATA BASE'!$A$2:$O$936,12,0),"")) -> 50200012846193 | P44: =IF($A$3=" "," ", IFERROR( VLOOKUP($A44,'SUPPLIER DATA BASE'!$A$2:$O$936,13,0),"")) -> HDFC0001249 | Q44: 16300 | R44: 46064 | V44: =IF(G44="","", IF(AND(G44>=DATE(2024,4,1),G44<=DATE(2025,3,31)),"FY 24-25", IF(AND(G44>=DATE(2025,4,1),G44<=DATE(2026,3,31)),"FY 25-26",IF(AND(G44>=DATE(2026,4,1),G44<=DATE(2027,3,31)),"FY 26-27","")))) -> FY 25-26
A45: AS TEXTILE | B45: =IF($A$3=" "," ", IFERROR( VLOOKUP($A45,'SUPPLIER DATA BASE'!$A$2:$M$936,3,0),"")) -> - | C45: =IF($A$3=" "," ", IFERROR( VLOOKUP($A45,'SUPPLIER DATA BASE'!$A$2:$F$936,6,0),"")) -> SURYAM TEXTILE AGENCY | D45: =IF($A$3=" "," ", IFERROR( VLOOKUP($A45,'SUPPLIER DATA BASE'!$A$2:$G$936,4,0),"")) -> 30 | E45: =IF($A$3=" "," ", IFERROR( VLOOKUP($A45,'SUPPLIER DATA BASE'!$A$2:$H$936,5,0),"")) -> 0.09 | F45: 124 | G45: 46035 | H45: 4 | I45: 6279 | J45: A S Textile 124.pdf | K45: - | L45: - | M45: =IF(G45="", "", (TODAY() - G45) & " Days") -> 153 Days | N45: =IF($A$3=" "," ", IFERROR( VLOOKUP($A45,'SUPPLIER DATA BASE'!$A$2:$O$936,11,0),"")) -> AS TEXTILE | O45: =IF($A$3=" "," ", IFERROR( VLOOKUP($A45,'SUPPLIER DATA BASE'!$A$2:$O$936,12,0),"")) -> 50200012846193 | P45: =IF($A$3=" "," ", IFERROR( VLOOKUP($A45,'SUPPLIER DATA BASE'!$A$2:$O$936,13,0),"")) -> HDFC0001249 | Q45: 6279 | R45: 46064 | V45: =IF(G45="","", IF(AND(G45>=DATE(2024,4,1),G45<=DATE(2025,3,31)),"FY 24-25", IF(AND(G45>=DATE(2025,4,1),G45<=DATE(2026,3,31)),"FY 25-26",IF(AND(G45>=DATE(2026,4,1),G45<=DATE(2027,3,31)),"FY 26-27","")))) -> FY 25-26
A46: AS TEXTILE | B46: =IF($A$3=" "," ", IFERROR( VLOOKUP($A46,'SUPPLIER DATA BASE'!$A$2:$M$936,3,0),"")) -> - | C46: =IF($A$3=" "," ", IFERROR( VLOOKUP($A46,'SUPPLIER DATA BASE'!$A$2:$F$936,6,0),"")) -> SURYAM TEXTILE AGENCY | D46: =IF($A$3=" "," ", IFERROR( VLOOKUP($A46,'SUPPLIER DATA BASE'!$A$2:$G$936,4,0),"")) -> 30 | E46: =IF($A$3=" "," ", IFERROR( VLOOKUP($A46,'SUPPLIER DATA BASE'!$A$2:$H$936,5,0),"")) -> 0.09 | F46: 123 | G46: 46035 | H46: 4 | I46: 10601 | J46: A S Textile 123.pdf | K46: - | L46: - | M46: =IF(G46="", "", (TODAY() - G46) & " Days") -> 153 Days | N46: =IF($A$3=" "," ", IFERROR( VLOOKUP($A46,'SUPPLIER DATA BASE'!$A$2:$O$936,11,0),"")) -> AS TEXTILE | O46: =IF($A$3=" "," ", IFERROR( VLOOKUP($A46,'SUPPLIER DATA BASE'!$A$2:$O$936,12,0),"")) -> 50200012846193 | P46: =IF($A$3=" "," ", IFERROR( VLOOKUP($A46,'SUPPLIER DATA BASE'!$A$2:$O$936,13,0),"")) -> HDFC0001249 | Q46: 10601 | R46: 46064 | V46: =IF(G46="","", IF(AND(G46>=DATE(2024,4,1),G46<=DATE(2025,3,31)),"FY 24-25", IF(AND(G46>=DATE(2025,4,1),G46<=DATE(2026,3,31)),"FY 25-26",IF(AND(G46>=DATE(2026,4,1),G46<=DATE(2027,3,31)),"FY 26-27","")))) -> FY 25-26
A47: AS TEXTILE | B47: =IF($A$3=" "," ", IFERROR( VLOOKUP($A47,'SUPPLIER DATA BASE'!$A$2:$M$936,3,0),"")) -> - | C47: =IF($A$3=" "," ", IFERROR( VLOOKUP($A47,'SUPPLIER DATA BASE'!$A$2:$F$936,6,0),"")) -> SURYAM TEXTILE AGENCY | D47: =IF($A$3=" "," ", IFERROR( VLOOKUP($A47,'SUPPLIER DATA BASE'!$A$2:$G$936,4,0),"")) -> 30 | E47: =IF($A$3=" "," ", IFERROR( VLOOKUP($A47,'SUPPLIER DATA BASE'!$A$2:$H$936,5,0),"")) -> 0.09 | F47: 130 | G47: 46035 | H47: 12 | I47: 9349 | J47: A S Textile 130.pdf | K47: - | L47: - | M47: =IF(G47="", "", (TODAY() - G47) & " Days") -> 153 Days | N47: =IF($A$3=" "," ", IFERROR( VLOOKUP($A47,'SUPPLIER DATA BASE'!$A$2:$O$936,11,0),"")) -> AS TEXTILE | O47: =IF($A$3=" "," ", IFERROR( VLOOKUP($A47,'SUPPLIER DATA BASE'!$A$2:$O$936,12,0),"")) -> 50200012846193 | P47: =IF($A$3=" "," ", IFERROR( VLOOKUP($A47,'SUPPLIER DATA BASE'!$A$2:$O$936,13,0),"")) -> HDFC0001249 | Q47: 9349 | R47: 46064 | V47: =IF(G47="","", IF(AND(G47>=DATE(2024,4,1),G47<=DATE(2025,3,31)),"FY 24-25", IF(AND(G47>=DATE(2025,4,1),G47<=DATE(2026,3,31)),"FY 25-26",IF(AND(G47>=DATE(2026,4,1),G47<=DATE(2027,3,31)),"FY 26-27","")))) -> FY 25-26
A48: AS TEXTILE | B48: =IF($A$3=" "," ", IFERROR( VLOOKUP($A48,'SUPPLIER DATA BASE'!$A$2:$M$936,3,0),"")) -> - | C48: =IF($A$3=" "," ", IFERROR( VLOOKUP($A48,'SUPPLIER DATA BASE'!$A$2:$F$936,6,0),"")) -> SURYAM TEXTILE AGENCY | D48: =IF($A$3=" "," ", IFERROR( VLOOKUP($A48,'SUPPLIER DATA BASE'!$A$2:$G$936,4,0),"")) -> 30 | E48: =IF($A$3=" "," ", IFERROR( VLOOKUP($A48,'SUPPLIER DATA BASE'!$A$2:$H$936,5,0),"")) -> 0.09 | F48: 126 | G48: 46035 | H48: 4 | I48: 11348 | J48: A S Textile 126.pdf | K48: - | L48: - | M48: =IF(G48="", "", (TODAY() - G48) & " Days") -> 153 Days | N48: =IF($A$3=" "," ", IFERROR( VLOOKUP($A48,'SUPPLIER DATA BASE'!$A$2:$O$936,11,0),"")) -> AS TEXTILE | O48: =IF($A$3=" "," ", IFERROR( VLOOKUP($A48,'SUPPLIER DATA BASE'!$A$2:$O$936,12,0),"")) -> 50200012846193 | P48: =IF($A$3=" "," ", IFERROR( VLOOKUP($A48,'SUPPLIER DATA BASE'!$A$2:$O$936,13,0),"")) -> HDFC0001249 | Q48: 11348 | R48: 46064 | V48: =IF(G48="","", IF(AND(G48>=DATE(2024,4,1),G48<=DATE(2025,3,31)),"FY 24-25", IF(AND(G48>=DATE(2025,4,1),G48<=DATE(2026,3,31)),"FY 25-26",IF(AND(G48>=DATE(2026,4,1),G48<=DATE(2027,3,31)),"FY 26-27","")))) -> FY 25-26
A49: AS TEXTILE | B49: =IF($A$3=" "," ", IFERROR( VLOOKUP($A49,'SUPPLIER DATA BASE'!$A$2:$M$936,3,0),"")) -> - | C49: =IF($A$3=" "," ", IFERROR( VLOOKUP($A49,'SUPPLIER DATA BASE'!$A$2:$F$936,6,0),"")) -> SURYAM TEXTILE AGENCY | D49: =IF($A$3=" "," ", IFERROR( VLOOKUP($A49,'SUPPLIER DATA BASE'!$A$2:$G$936,4,0),"")) -> 30 | E49: =IF($A$3=" "," ", IFERROR( VLOOKUP($A49,'SUPPLIER DATA BASE'!$A$2:$H$936,5,0),"")) -> 0.09 | F49: 128 | G49: 46035 | H49: 4 | I49: 6254 | J49: A s textile 128.pdf | K49: - | L49: - | M49: =IF(G49="", "", (TODAY() - G49) & " Days") -> 153 Days | N49: =IF($A$3=" "," ", IFERROR( VLOOKUP($A49,'SUPPLIER DATA BASE'!$A$2:$O$936,11,0),"")) -> AS TEXTILE | O49: =IF($A$3=" "," ", IFERROR( VLOOKUP($A49,'SUPPLIER DATA BASE'!$A$2:$O$936,12,0),"")) -> 50200012846193 | P49: =IF($A$3=" "," ", IFERROR( VLOOKUP($A49,'SUPPLIER DATA BASE'!$A$2:$O$936,13,0),"")) -> HDFC0001249 | Q49: 6254 | R49: 46064 | V49: =IF(G49="","", IF(AND(G49>=DATE(2024,4,1),G49<=DATE(2025,3,31)),"FY 24-25", IF(AND(G49>=DATE(2025,4,1),G49<=DATE(2026,3,31)),"FY 25-26",IF(AND(G49>=DATE(2026,4,1),G49<=DATE(2027,3,31)),"FY 26-27","")))) -> FY 25-26
A50: AS TEXTILE | B50: =IF($A$3=" "," ", IFERROR( VLOOKUP($A50,'SUPPLIER DATA BASE'!$A$2:$M$936,3,0),"")) -> - | C50: =IF($A$3=" "," ", IFERROR( VLOOKUP($A50,'SUPPLIER DATA BASE'!$A$2:$F$936,6,0),"")) -> SURYAM TEXTILE AGENCY | D50: =IF($A$3=" "," ", IFERROR( VLOOKUP($A50,'SUPPLIER DATA BASE'!$A$2:$G$936,4,0),"")) -> 30 | E50: =IF($A$3=" "," ", IFERROR( VLOOKUP($A50,'SUPPLIER DATA BASE'!$A$2:$H$936,5,0),"")) -> 0.09 | F50: 129 | G50: 46035 | H50: 20 | I50: 16674 | J50: A S Textile 129.pdf | K50: - | L50: - | M50: =IF(G50="", "", (TODAY() - G50) & " Days") -> 153 Days | N50: =IF($A$3=" "," ", IFERROR( VLOOKUP($A50,'SUPPLIER DATA BASE'!$A$2:$O$936,11,0),"")) -> AS TEXTILE | O50: =IF($A$3=" "," ", IFERROR( VLOOKUP($A50,'SUPPLIER DATA BASE'!$A$2:$O$936,12,0),"")) -> 50200012846193 | P50: =IF($A$3=" "," ", IFERROR( VLOOKUP($A50,'SUPPLIER DATA BASE'!$A$2:$O$936,13,0),"")) -> HDFC0001249 | Q50: 16674 | R50: 46064 | V50: =IF(G50="","", IF(AND(G50>=DATE(2024,4,1),G50<=DATE(2025,3,31)),"FY 24-25", IF(AND(G50>=DATE(2025,4,1),G50<=DATE(2026,3,31)),"FY 25-26",IF(AND(G50>=DATE(2026,4,1),G50<=DATE(2027,3,31)),"FY 26-27","")))) -> FY 25-26
... A52: WILSON PRINTS | B52: =IF($A$3=" "," ", IFERROR( VLOOKUP($A52,'SUPPLIER DATA BASE'!$A$2:$M$936,3,0),"")) -> - | C52: =IF($A$3=" "," ", IFERROR( VLOOKUP($A52,'SUPPLIER DATA BASE'!$A$2:$F$936,6,0),"")) -> SURYAM TEXTILE AGENCY | D52: =IF($A$3=" "," ", IFERROR( VLOOKUP($A52,'SUPPLIER DATA BASE'!$A$2:$G$936,4,0),"")) -> NO | E52: =IF($A$3=" "," ", IFERROR( VLOOKUP($A52,'SUPPLIER DATA BASE'!$A$2:$H$936,5,0),"")) -> - | F52: 2581 | G52: 46037 | H52: 54 | I52: 52736 | J52: Wilson prints 2581.pdf | K52: - | L52: - | M52: =IF(G52="", "", (TODAY() - G52) & " Days") -> 151 Days | N52: =IF($A$3=" "," ", IFERROR( VLOOKUP($A52,'SUPPLIER DATA BASE'!$A$2:$O$936,11,0),"")) -> WILSON PRINTS | O52: =IF($A$3=" "," ", IFERROR( VLOOKUP($A52,'SUPPLIER DATA BASE'!$A$2:$O$936,12,0),"")) -> 510044017719 | P52: =IF($A$3=" "," ", IFERROR( VLOOKUP($A52,'SUPPLIER DATA BASE'!$A$2:$O$936,13,0),"")) -> KKBK0002852 | Q52: 52736 | R52: 46131 | V52: =IF(G52="","", IF(AND(G52>=DATE(2024,4,1),G52<=DATE(2025,3,31)),"FY 24-25", IF(AND(G52>=DATE(2025,4,1),G52<=DATE(2026,3,31)),"FY 25-26",IF(AND(G52>=DATE(2026,4,1),G52<=DATE(2027,3,31)),"FY 26-27","")))) -> FY 25-26
A53: NARVADA TEXTILES | B53: =IF($A$3=" "," ", IFERROR( VLOOKUP($A53,'SUPPLIER DATA BASE'!$A$2:$M$936,3,0),"")) -> JOCKEY | C53: =IF($A$3=" "," ", IFERROR( VLOOKUP($A53,'SUPPLIER DATA BASE'!$A$2:$F$936,6,0),"")) -> DIRECT | D53: =IF($A$3=" "," ", IFERROR( VLOOKUP($A53,'SUPPLIER DATA BASE'!$A$2:$G$936,4,0),"")) -> 21 | E53: =IF($A$3=" "," ", IFERROR( VLOOKUP($A53,'SUPPLIER DATA BASE'!$A$2:$H$936,5,0),"")) -> 0.02 | F53: SCRS25/1953 | G53: 46038 | H53: 100 | I53: 11619 | J53: Narvada Textile -1953.pdf | K53: - | L53: - | M53: =IF(G53="", "", (TODAY() - G53) & " Days") -> 150 Days | N53: =IF($A$3=" "," ", IFERROR( VLOOKUP($A53,'SUPPLIER DATA BASE'!$A$2:$O$936,11,0),"")) -> NARVADA TEXTILES | O53: =IF($A$3=" "," ", IFERROR( VLOOKUP($A53,'SUPPLIER DATA BASE'!$A$2:$O$936,12,0),"")) -> 72610200000442 | P53: =IF($A$3=" "," ", IFERROR( VLOOKUP($A53,'SUPPLIER DATA BASE'!$A$2:$O$936,13,0),"")) -> BARB0DBRANC | V53: =IF(G53="","", IF(AND(G53>=DATE(2024,4,1),G53<=DATE(2025,3,31)),"FY 24-25", IF(AND(G53>=DATE(2025,4,1),G53<=DATE(2026,3,31)),"FY 25-26",IF(AND(G53>=DATE(2026,4,1),G53<=DATE(2027,3,31)),"FY 26-27","")))) -> FY 25-26
A54: V N TEXTILE | B54: =IF($A$3=" "," ", IFERROR( VLOOKUP($A54,'SUPPLIER DATA BASE'!$A$2:$M$936,3,0),"")) -> JOCKEY | C54: =IF($A$3=" "," ", IFERROR( VLOOKUP($A54,'SUPPLIER DATA BASE'!$A$2:$F$936,6,0),"")) -> DIRECT | D54: =IF($A$3=" "," ", IFERROR( VLOOKUP($A54,'SUPPLIER DATA BASE'!$A$2:$G$936,4,0),"")) -> 21 | E54: =IF($A$3=" "," ", IFERROR( VLOOKUP($A54,'SUPPLIER DATA BASE'!$A$2:$H$936,5,0),"")) -> 0.02 | F54: VN/G/25/2489 | G54: 46038 | H54: 15 | I54: 8477 | J54: V N textile 2489.pdf | K54: - | L54: - | M54: =IF(G54="", "", (TODAY() - G54) & " Days") -> 150 Days | N54: =IF($A$3=" "," ", IFERROR( VLOOKUP($A54,'SUPPLIER DATA BASE'!$A$2:$O$936,11,0),"")) -> V N TEXTILE | O54: =IF($A$3=" "," ", IFERROR( VLOOKUP($A54,'SUPPLIER DATA BASE'!$A$2:$O$936,12,0),"")) -> 252005000323 | P54: =IF($A$3=" "," ", IFERROR( VLOOKUP($A54,'SUPPLIER DATA BASE'!$A$2:$O$936,13,0),"")) -> ICIC0002520 | Q54: 21920 | R54: 46069 | S54: NIL | V54: =IF(G54="","", IF(AND(G54>=DATE(2024,4,1),G54<=DATE(2025,3,31)),"FY 24-25", IF(AND(G54>=DATE(2025,4,1),G54<=DATE(2026,3,31)),"FY 25-26",IF(AND(G54>=DATE(2026,4,1),G54<=DATE(2027,3,31)),"FY 26-27","")))) -> FY 25-26
A55: SHREE NARAYANI ENTERPRISE | B55: =IF($A$3=" "," ", IFERROR( VLOOKUP($A55,'SUPPLIER DATA BASE'!$A$2:$M$936,3,0),"")) -> JOCKEY | C55: =IF($A$3=" "," ", IFERROR( VLOOKUP($A55,'SUPPLIER DATA BASE'!$A$2:$F$936,6,0),"")) -> DIRECT | D55: =IF($A$3=" "," ", IFERROR( VLOOKUP($A55,'SUPPLIER DATA BASE'!$A$2:$G$936,4,0),"")) -> 30 | E55: =IF($A$3=" "," ", IFERROR( VLOOKUP($A55,'SUPPLIER DATA BASE'!$A$2:$H$936,5,0),"")) -> 2 | F55: P2CRS25/2606 | G55: 46038 | H55: 85 | I55: 30472 | J55: Shree Narayani Enterprises 2606.pdf | K55: - | L55: - | M55: =IF(G55="", "", (TODAY() - G55) & " Days") -> 150 Days | N55: =IF($A$3=" "," ", IFERROR( VLOOKUP($A55,'SUPPLIER DATA BASE'!$A$2:$O$936,11,0),"")) -> SHREE NARAYANI ENTERPRISE | O55: =IF($A$3=" "," ", IFERROR( VLOOKUP($A55,'SUPPLIER DATA BASE'!$A$2:$O$936,12,0),"")) -> 29205005382 | P55: =IF($A$3=" "," ", IFERROR( VLOOKUP($A55,'SUPPLIER DATA BASE'!$A$2:$O$936,13,0),"")) -> ICIC0000292 | V55: =IF(G55="","", IF(AND(G55>=DATE(2024,4,1),G55<=DATE(2025,3,31)),"FY 24-25", IF(AND(G55>=DATE(2025,4,1),G55<=DATE(2026,3,31)),"FY 25-26",IF(AND(G55>=DATE(2026,4,1),G55<=DATE(2027,3,31)),"FY 26-27","")))) -> FY 25-26
A56: SHREE NARAYANI ENTERPRISE | B56: =IF($A$3=" "," ", IFERROR( VLOOKUP($A56,'SUPPLIER DATA BASE'!$A$2:$M$936,3,0),"")) -> JOCKEY | C56: =IF($A$3=" "," ", IFERROR( VLOOKUP($A56,'SUPPLIER DATA BASE'!$A$2:$F$936,6,0),"")) -> DIRECT | D56: =IF($A$3=" "," ", IFERROR( VLOOKUP($A56,'SUPPLIER DATA BASE'!$A$2:$G$936,4,0),"")) -> 30 | E56: =IF($A$3=" "," ", IFERROR( VLOOKUP($A56,'SUPPLIER DATA BASE'!$A$2:$H$936,5,0),"")) -> 2 | F56: P2CRS25/2605 | G56: 46038 | H56: 89 | I56: 33532 | J56: SHREE NARAYANI ENTERPRISE-2605.pdf | K56: - | L56: - | M56: =IF(G56="", "", (TODAY() - G56) & " Days") -> 150 Days | N56: =IF($A$3=" "," ", IFERROR( VLOOKUP($A56,'SUPPLIER DATA BASE'!$A$2:$O$936,11,0),"")) -> SHREE NARAYANI ENTERPRISE | O56: =IF($A$3=" "," ", IFERROR( VLOOKUP($A56,'SUPPLIER DATA BASE'!$A$2:$O$936,12,0),"")) -> 29205005382 | P56: =IF($A$3=" "," ", IFERROR( VLOOKUP($A56,'SUPPLIER DATA BASE'!$A$2:$O$936,13,0),"")) -> ICIC0000292 | V56: =IF(G56="","", IF(AND(G56>=DATE(2024,4,1),G56<=DATE(2025,3,31)),"FY 24-25", IF(AND(G56>=DATE(2025,4,1),G56<=DATE(2026,3,31)),"FY 25-26",IF(AND(G56>=DATE(2026,4,1),G56<=DATE(2027,3,31)),"FY 26-27","")))) -> FY 25-26
A57: JAY AMBEY SAREES | B57: =IF($A$3=" "," ", IFERROR( VLOOKUP($A57,'SUPPLIER DATA BASE'!$A$2:$M$936,3,0),"")) -> - | C57: =IF($A$3=" "," ", IFERROR( VLOOKUP($A57,'SUPPLIER DATA BASE'!$A$2:$F$936,6,0),"")) -> SURYAM TEXTILE AGENCY | D57: =IF($A$3=" "," ", IFERROR( VLOOKUP($A57,'SUPPLIER DATA BASE'!$A$2:$G$936,4,0),"")) -> NO | E57: =IF($A$3=" "," ", IFERROR( VLOOKUP($A57,'SUPPLIER DATA BASE'!$A$2:$H$936,5,0),"")) -> - | F57: 6635 | G57: 46038 | H57: 7 | I57: 28088 | J57: Jay ambey sarees 6635.pdf | K57: - | L57: - | M57: =IF(G57="", "", (TODAY() - G57) & " Days") -> 150 Days | N57: =IF($A$3=" "," ", IFERROR( VLOOKUP($A57,'SUPPLIER DATA BASE'!$A$2:$O$936,11,0),"")) -> JAY AMBEY SAREES | O57: =IF($A$3=" "," ", IFERROR( VLOOKUP($A57,'SUPPLIER DATA BASE'!$A$2:$O$936,12,0),"")) -> 50200027562802 | P57: =IF($A$3=" "," ", IFERROR( VLOOKUP($A57,'SUPPLIER DATA BASE'!$A$2:$O$936,13,0),"")) -> HDFC0009027 | Q57: 28088 | R57: 46131 | V57: =IF(G57="","", IF(AND(G57>=DATE(2024,4,1),G57<=DATE(2025,3,31)),"FY 24-25", IF(AND(G57>=DATE(2025,4,1),G57<=DATE(2026,3,31)),"FY 25-26",IF(AND(G57>=DATE(2026,4,1),G57<=DATE(2027,3,31)),"FY 26-27","")))) -> FY 25-26
A58: JAY AMBEY SAREES | B58: =IF($A$3=" "," ", IFERROR( VLOOKUP($A58,'SUPPLIER DATA BASE'!$A$2:$M$936,3,0),"")) -> - | C58: =IF($A$3=" "," ", IFERROR( VLOOKUP($A58,'SUPPLIER DATA BASE'!$A$2:$F$936,6,0),"")) -> SURYAM TEXTILE AGENCY | D58: =IF($A$3=" "," ", IFERROR( VLOOKUP($A58,'SUPPLIER DATA BASE'!$A$2:$G$936,4,0),"")) -> NO | E58: =IF($A$3=" "," ", IFERROR( VLOOKUP($A58,'SUPPLIER DATA BASE'!$A$2:$H$936,5,0),"")) -> - | F58: 6636 | G58: 46038 | H58: 6 | I58: 23447 | J58: Jay ambey sarees 6636.pdf | K58: - | L58: - | M58: =IF(G58="", "", (TODAY() - G58) & " Days") -> 150 Days | N58: =IF($A$3=" "," ", IFERROR( VLOOKUP($A58,'SUPPLIER DATA BASE'!$A$2:$O$936,11,0),"")) -> JAY AMBEY SAREES | O58: =IF($A$3=" "," ", IFERROR( VLOOKUP($A58,'SUPPLIER DATA BASE'!$A$2:$O$936,12,0),"")) -> 50200027562802 | P58: =IF($A$3=" "," ", IFERROR( VLOOKUP($A58,'SUPPLIER DATA BASE'!$A$2:$O$936,13,0),"")) -> HDFC0009027 | Q58: 23447 | R58: 46131 | V58: =IF(G58="","", IF(AND(G58>=DATE(2024,4,1),G58<=DATE(2025,3,31)),"FY 24-25", IF(AND(G58>=DATE(2025,4,1),G58<=DATE(2026,3,31)),"FY 25-26",IF(AND(G58>=DATE(2026,4,1),G58<=DATE(2027,3,31)),"FY 26-27","")))) -> FY 25-26
A59: AS TEXTILE | B59: =IF($A$3=" "," ", IFERROR( VLOOKUP($A59,'SUPPLIER DATA BASE'!$A$2:$M$936,3,0),"")) -> - | C59: =IF($A$3=" "," ", IFERROR( VLOOKUP($A59,'SUPPLIER DATA BASE'!$A$2:$F$936,6,0),"")) -> SURYAM TEXTILE AGENCY | D59: =IF($A$3=" "," ", IFERROR( VLOOKUP($A59,'SUPPLIER DATA BASE'!$A$2:$G$936,4,0),"")) -> 30 | E59: =IF($A$3=" "," ", IFERROR( VLOOKUP($A59,'SUPPLIER DATA BASE'!$A$2:$H$936,5,0),"")) -> 0.09 | F59: 162 | G59: 46038 | H59: 4 | I59: 11567 | J59: A S Textile 162.pdf | K59: - | L59: - | M59: =IF(G59="", "", (TODAY() - G59) & " Days") -> 150 Days | N59: =IF($A$3=" "," ", IFERROR( VLOOKUP($A59,'SUPPLIER DATA BASE'!$A$2:$O$936,11,0),"")) -> AS TEXTILE | O59: =IF($A$3=" "," ", IFERROR( VLOOKUP($A59,'SUPPLIER DATA BASE'!$A$2:$O$936,12,0),"")) -> 50200012846193 | P59: =IF($A$3=" "," ", IFERROR( VLOOKUP($A59,'SUPPLIER DATA BASE'!$A$2:$O$936,13,0),"")) -> HDFC0001249 | Q59: 10575 | R59: 46085 | S59: 991.44 | V59: =IF(G59="","", IF(AND(G59>=DATE(2024,4,1),G59<=DATE(2025,3,31)),"FY 24-25", IF(AND(G59>=DATE(2025,4,1),G59<=DATE(2026,3,31)),"FY 25-26",IF(AND(G59>=DATE(2026,4,1),G59<=DATE(2027,3,31)),"FY 26-27","")))) -> FY 25-26
A60: AS TEXTILE | B60: =IF($A$3=" "," ", IFERROR( VLOOKUP($A60,'SUPPLIER DATA BASE'!$A$2:$M$936,3,0),"")) -> - | C60: =IF($A$3=" "," ", IFERROR( VLOOKUP($A60,'SUPPLIER DATA BASE'!$A$2:$F$936,6,0),"")) -> SURYAM TEXTILE AGENCY | D60: =IF($A$3=" "," ", IFERROR( VLOOKUP($A60,'SUPPLIER DATA BASE'!$A$2:$G$936,4,0),"")) -> 30 | E60: =IF($A$3=" "," ", IFERROR( VLOOKUP($A60,'SUPPLIER DATA BASE'!$A$2:$H$936,5,0),"")) -> 0.09 | F60: 161 | G60: 46038 | H60: 2 | I60: 13885 | J60: A S Textile 161.pdf | K60: - | L60: - | M60: =IF(G60="", "", (TODAY() - G60) & " Days") -> 150 Days | N60: =IF($A$3=" "," ", IFERROR( VLOOKUP($A60,'SUPPLIER DATA BASE'!$A$2:$O$936,11,0),"")) -> AS TEXTILE | O60: =IF($A$3=" "," ", IFERROR( VLOOKUP($A60,'SUPPLIER DATA BASE'!$A$2:$O$936,12,0),"")) -> 50200012846193 | P60: =IF($A$3=" "," ", IFERROR( VLOOKUP($A60,'SUPPLIER DATA BASE'!$A$2:$O$936,13,0),"")) -> HDFC0001249 | Q60: 12695 | R60: 46085 | S60: 1190.16 | V60: =IF(G60="","", IF(AND(G60>=DATE(2024,4,1),G60<=DATE(2025,3,31)),"FY 24-25", IF(AND(G60>=DATE(2025,4,1),G60<=DATE(2026,3,31)),"FY 25-26",IF(AND(G60>=DATE(2026,4,1),G60<=DATE(2027,3,31)),"FY 26-27","")))) -> FY 25-26
A61: GTN ENGINEERING INDIA LTD | B61: =IF($A$3=" "," ", IFERROR( VLOOKUP($A61,'SUPPLIER DATA BASE'!$A$2:$M$936,3,0),"")) -> - | C61: =IF($A$3=" "," ", IFERROR( VLOOKUP($A61,'SUPPLIER DATA BASE'!$A$2:$F$936,6,0),"")) -> - | D61: =IF($A$3=" "," ", IFERROR( VLOOKUP($A61,'SUPPLIER DATA BASE'!$A$2:$G$936,4,0),"")) -> - | E61: =IF($A$3=" "," ", IFERROR( VLOOKUP($A61,'SUPPLIER DATA BASE'!$A$2:$H$936,5,0),"")) -> - | F61: 252193/25-26 | G61: 46039 | H61: 280 | I61: 13123 | J61: GTN Engineering 252193.pdf | K61: - | L61: - | M61: =IF(G61="", "", (TODAY() - G61) & " Days") -> 149 Days | N61: =IF($A$3=" "," ", IFERROR( VLOOKUP($A61,'SUPPLIER DATA BASE'!$A$2:$O$936,11,0),"")) -> GTN ENGINEERING INDIA LTD | O61: =IF($A$3=" "," ", IFERROR( VLOOKUP($A61,'SUPPLIER DATA BASE'!$A$2:$O$936,12,0),"")) -> 4437002100000153 | P61: =IF($A$3=" "," ", IFERROR( VLOOKUP($A61,'SUPPLIER DATA BASE'!$A$2:$O$936,13,0),"")) -> PUNB0020700 | V61: =IF(G61="","", IF(AND(G61>=DATE(2024,4,1),G61<=DATE(2025,3,31)),"FY 24-25", IF(AND(G61>=DATE(2025,4,1),G61<=DATE(2026,3,31)),"FY 25-26",IF(AND(G61>=DATE(2026,4,1),G61<=DATE(2027,3,31)),"FY 26-27","")))) -> FY 25-26
A62: GTN ENGINEERING INDIA LTD | B62: =IF($A$3=" "," ", IFERROR( VLOOKUP($A62,'SUPPLIER DATA BASE'!$A$2:$M$936,3,0),"")) -> - | C62: =IF($A$3=" "," ", IFERROR( VLOOKUP($A62,'SUPPLIER DATA BASE'!$A$2:$F$936,6,0),"")) -> - | D62: =IF($A$3=" "," ", IFERROR( VLOOKUP($A62,'SUPPLIER DATA BASE'!$A$2:$G$936,4,0),"")) -> - | E62: =IF($A$3=" "," ", IFERROR( VLOOKUP($A62,'SUPPLIER DATA BASE'!$A$2:$H$936,5,0),"")) -> - | F62: 252194/25-26 | G62: 46039 | H62: 140 | I62: 8600 | J62: GTN Engineering 252194.pdf | K62: - | L62: - | M62: =IF(G62="", "", (TODAY() - G62) & " Days") -> 149 Days | N62: =IF($A$3=" "," ", IFERROR( VLOOKUP($A62,'SUPPLIER DATA BASE'!$A$2:$O$936,11,0),"")) -> GTN ENGINEERING INDIA LTD | O62: =IF($A$3=" "," ", IFERROR( VLOOKUP($A62,'SUPPLIER DATA BASE'!$A$2:$O$936,12,0),"")) -> 4437002100000153 | P62: =IF($A$3=" "," ", IFERROR( VLOOKUP($A62,'SUPPLIER DATA BASE'!$A$2:$O$936,13,0),"")) -> PUNB0020700 | V62: =IF(G62="","", IF(AND(G62>=DATE(2024,4,1),G62<=DATE(2025,3,31)),"FY 24-25", IF(AND(G62>=DATE(2025,4,1),G62<=DATE(2026,3,31)),"FY 25-26",IF(AND(G62>=DATE(2026,4,1),G62<=DATE(2027,3,31)),"FY 26-27","")))) -> FY 25-26
A63: ANAYA DESIGNER | B63: =IF($A$3=" "," ", IFERROR( VLOOKUP($A63,'SUPPLIER DATA BASE'!$A$2:$M$936,3,0),"")) -> - | C63: =IF($A$3=" "," ", IFERROR( VLOOKUP($A63,'SUPPLIER DATA BASE'!$A$2:$F$936,6,0),"")) -> SURYAM TEXTILE AGENCY | D63: =IF($A$3=" "," ", IFERROR( VLOOKUP($A63,'SUPPLIER DATA BASE'!$A$2:$G$936,4,0),"")) -> - | E63: =IF($A$3=" "," ", IFERROR( VLOOKUP($A63,'SUPPLIER DATA BASE'!$A$2:$H$936,5,0),"")) -> - | F63: 2864 | G63: 46039 | H63: 34 | I63: 108744 | J63: ANAYA DESIGNER_2864_25-26 .pdf | K63: - | L63: - | M63: =IF(G63="", "", (TODAY() - G63) & " Days") -> 149 Days | N63: =IF($A$3=" "," ", IFERROR( VLOOKUP($A63,'SUPPLIER DATA BASE'!$A$2:$O$936,11,0),"")) -> ANAYA DESIGNER | O63: =IF($A$3=" "," ", IFERROR( VLOOKUP($A63,'SUPPLIER DATA BASE'!$A$2:$O$936,12,0),"")) -> 2650415227 | P63: =IF($A$3=" "," ", IFERROR( VLOOKUP($A63,'SUPPLIER DATA BASE'!$A$2:$O$936,13,0),"")) -> KKBK0000884 | Q63: 108744 | R63: 46133 | V63: =IF(G63="","", IF(AND(G63>=DATE(2024,4,1),G63<=DATE(2025,3,31)),"FY 24-25", IF(AND(G63>=DATE(2025,4,1),G63<=DATE(2026,3,31)),"FY 25-26",IF(AND(G63>=DATE(2026,4,1),G63<=DATE(2027,3,31)),"FY 26-27","")))) -> FY 25-26
A64: ANAYA DESIGNER | B64: =IF($A$3=" "," ", IFERROR( VLOOKUP($A64,'SUPPLIER DATA BASE'!$A$2:$M$936,3,0),"")) -> - | C64: =IF($A$3=" "," ", IFERROR( VLOOKUP($A64,'SUPPLIER DATA BASE'!$A$2:$F$936,6,0),"")) -> SURYAM TEXTILE AGENCY | D64: =IF($A$3=" "," ", IFERROR( VLOOKUP($A64,'SUPPLIER DATA BASE'!$A$2:$G$936,4,0),"")) -> - | E64: =IF($A$3=" "," ", IFERROR( VLOOKUP($A64,'SUPPLIER DATA BASE'!$A$2:$H$936,5,0),"")) -> - | F64: 2865 | G64: 46039 | H64: 33 | I64: 99768 | J64: ANAYA DESIGNER_2865 _25-26.pdf | K64: - | L64: - | M64: =IF(G64="", "", (TODAY() - G64) & " Days") -> 149 Days | N64: =IF($A$3=" "," ", IFERROR( VLOOKUP($A64,'SUPPLIER DATA BASE'!$A$2:$O$936,11,0),"")) -> ANAYA DESIGNER | O64: =IF($A$3=" "," ", IFERROR( VLOOKUP($A64,'SUPPLIER DATA BASE'!$A$2:$O$936,12,0),"")) -> 2650415227 | P64: =IF($A$3=" "," ", IFERROR( VLOOKUP($A64,'SUPPLIER DATA BASE'!$A$2:$O$936,13,0),"")) -> KKBK0000884 | Q64: 93680 | R64: 46133 | S64: 3044 | U64: BILL 33 & 34 PAID TOGETHER | V64: =IF(G64="","", IF(AND(G64>=DATE(2024,4,1),G64<=DATE(2025,3,31)),"FY 24-25", IF(AND(G64>=DATE(2025,4,1),G64<=DATE(2026,3,31)),"FY 25-26",IF(AND(G64>=DATE(2026,4,1),G64<=DATE(2027,3,31)),"FY 26-27","")))) -> FY 25-26
A65: AS TEXTILE | B65: =IF($A$3=" "," ", IFERROR( VLOOKUP($A65,'SUPPLIER DATA BASE'!$A$2:$M$936,3,0),"")) -> - | C65: =IF($A$3=" "," ", IFERROR( VLOOKUP($A65,'SUPPLIER DATA BASE'!$A$2:$F$936,6,0),"")) -> SURYAM TEXTILE AGENCY | D65: =IF($A$3=" "," ", IFERROR( VLOOKUP($A65,'SUPPLIER DATA BASE'!$A$2:$G$936,4,0),"")) -> 30 | E65: =IF($A$3=" "," ", IFERROR( VLOOKUP($A65,'SUPPLIER DATA BASE'!$A$2:$H$936,5,0),"")) -> 0.09 | F65: 175 | G65: 46043 | H65: 4 | I65: 10601 | J65: A S Textile 175.pdf | K65: - | L65: - | M65: =IF(G65="", "", (TODAY() - G65) & " Days") -> 145 Days | N65: =IF($A$3=" "," ", IFERROR( VLOOKUP($A65,'SUPPLIER DATA BASE'!$A$2:$O$936,11,0),"")) -> AS TEXTILE | O65: =IF($A$3=" "," ", IFERROR( VLOOKUP($A65,'SUPPLIER DATA BASE'!$A$2:$O$936,12,0),"")) -> 50200012846193 | P65: =IF($A$3=" "," ", IFERROR( VLOOKUP($A65,'SUPPLIER DATA BASE'!$A$2:$O$936,13,0),"")) -> HDFC0001249 | V65: =IF(G65="","", IF(AND(G65>=DATE(2024,4,1),G65<=DATE(2025,3,31)),"FY 24-25", IF(AND(G65>=DATE(2025,4,1),G65<=DATE(2026,3,31)),"FY 25-26",IF(AND(G65>=DATE(2026,4,1),G65<=DATE(2027,3,31)),"FY 26-27","")))) -> FY 25-26
A66: D D SALES CO | B66: =IF($A$3=" "," ", IFERROR( VLOOKUP($A66,'SUPPLIER DATA BASE'!$A$2:$M$936,3,0),"")) -> KILLER | C66: =IF($A$3=" "," ", IFERROR( VLOOKUP($A66,'SUPPLIER DATA BASE'!$A$2:$F$936,6,0),"")) -> - | D66: =IF($A$3=" "," ", IFERROR( VLOOKUP($A66,'SUPPLIER DATA BASE'!$A$2:$G$936,4,0),"")) -> NO | E66: =IF($A$3=" "," ", IFERROR( VLOOKUP($A66,'SUPPLIER DATA BASE'!$A$2:$H$936,5,0),"")) -> - | F66: GSTN-964 | G66: 46044 | H66: 408 | I66: 682915 | J66: DD Sales GSTN 946.pdf | K66: - | L66: - | M66: =IF(G66="", "", (TODAY() - G66) & " Days") -> 144 Days | N66: =IF($A$3=" "," ", IFERROR( VLOOKUP($A66,'SUPPLIER DATA BASE'!$A$2:$O$936,11,0),"")) -> D D SALES CO | O66: =IF($A$3=" "," ", IFERROR( VLOOKUP($A66,'SUPPLIER DATA BASE'!$A$2:$O$936,12,0),"")) -> 29205007835 | P66: =IF($A$3=" "," ", IFERROR( VLOOKUP($A66,'SUPPLIER DATA BASE'!$A$2:$O$936,13,0),"")) -> ICIC0000292 | V66: =IF(G66="","", IF(AND(G66>=DATE(2024,4,1),G66<=DATE(2025,3,31)),"FY 24-25", IF(AND(G66>=DATE(2025,4,1),G66<=DATE(2026,3,31)),"FY 25-26",IF(AND(G66>=DATE(2026,4,1),G66<=DATE(2027,3,31)),"FY 26-27","")))) -> FY 25-26
A67: MUKESH AGRAWAL | B67: =IF($A$3=" "," ", IFERROR( VLOOKUP($A67,'SUPPLIER DATA BASE'!$A$2:$M$936,3,0),"")) -> - | C67: =IF($A$3=" "," ", IFERROR( VLOOKUP($A67,'SUPPLIER DATA BASE'!$A$2:$F$936,6,0),"")) -> - | D67: =IF($A$3=" "," ", IFERROR( VLOOKUP($A67,'SUPPLIER DATA BASE'!$A$2:$G$936,4,0),"")) -> - | E67: =IF($A$3=" "," ", IFERROR( VLOOKUP($A67,'SUPPLIER DATA BASE'!$A$2:$H$936,5,0),"")) -> - | F67: RE/20/25-26 | G67: 46044 | H67: 282 | I67: 28200 | J67: MUKESH AGARWAL(PETICOAT)_INVRE20_HZB_282PCS.pdf | K67: - | L67: - | M67: =IF(G67="", "", (TODAY() - G67) & " Days") -> 144 Days | N67: =IF($A$3=" "," ", IFERROR( VLOOKUP($A67,'SUPPLIER DATA BASE'!$A$2:$O$936,11,0),"")) -> MUKESH AGRAWAL | O67: =IF($A$3=" "," ", IFERROR( VLOOKUP($A67,'SUPPLIER DATA BASE'!$A$2:$O$936,12,0),"")) -> 3581044998 | P67: =IF($A$3=" "," ", IFERROR( VLOOKUP($A67,'SUPPLIER DATA BASE'!$A$2:$O$936,13,0),"")) -> CBIN0281277 | V67: =IF(G67="","", IF(AND(G67>=DATE(2024,4,1),G67<=DATE(2025,3,31)),"FY 24-25", IF(AND(G67>=DATE(2025,4,1),G67<=DATE(2026,3,31)),"FY 25-26",IF(AND(G67>=DATE(2026,4,1),G67<=DATE(2027,3,31)),"FY 26-27","")))) -> FY 25-26
A68: D APPAREL | B68: =IF($A$3=" "," ", IFERROR( VLOOKUP($A68,'SUPPLIER DATA BASE'!$A$2:$M$936,3,0),"")) -> KHUSHAL/STATUS QUO | C68: =IF($A$3=" "," ", IFERROR( VLOOKUP($A68,'SUPPLIER DATA BASE'!$A$2:$F$936,6,0),"")) -> - | D68: =IF($A$3=" "," ", IFERROR( VLOOKUP($A68,'SUPPLIER DATA BASE'!$A$2:$G$936,4,0),"")) -> - | E68: =IF($A$3=" "," ", IFERROR( VLOOKUP($A68,'SUPPLIER DATA BASE'!$A$2:$H$936,5,0),"")) -> - | F68: DA/25-26/0754 | G68: 46044 | H68: 19 | I68: 80161 | J68: D apparel 754.pdf | K68: - | L68: - | M68: =IF(G68="", "", (TODAY() - G68) & " Days") -> 144 Days | N68: =IF($A$3=" "," ", IFERROR( VLOOKUP($A68,'SUPPLIER DATA BASE'!$A$2:$O$936,11,0),"")) -> D APPAREL | O68: =IF($A$3=" "," ", IFERROR( VLOOKUP($A68,'SUPPLIER DATA BASE'!$A$2:$O$936,12,0),"")) -> 722501010050397 | P68: =IF($A$3=" "," ", IFERROR( VLOOKUP($A68,'SUPPLIER DATA BASE'!$A$2:$O$936,13,0),"")) -> UBIN0572250 | V68: =IF(G68="","", IF(AND(G68>=DATE(2024,4,1),G68<=DATE(2025,3,31)),"FY 24-25", IF(AND(G68>=DATE(2025,4,1),G68<=DATE(2026,3,31)),"FY 25-26",IF(AND(G68>=DATE(2026,4,1),G68<=DATE(2027,3,31)),"FY 26-27","")))) -> FY 25-26
A69: D D SALES CO | B69: =IF($A$3=" "," ", IFERROR( VLOOKUP($A69,'SUPPLIER DATA BASE'!$A$2:$M$936,3,0),"")) -> KILLER | C69: =IF($A$3=" "," ", IFERROR( VLOOKUP($A69,'SUPPLIER DATA BASE'!$A$2:$F$936,6,0),"")) -> - | D69: =IF($A$3=" "," ", IFERROR( VLOOKUP($A69,'SUPPLIER DATA BASE'!$A$2:$G$936,4,0),"")) -> NO | E69: =IF($A$3=" "," ", IFERROR( VLOOKUP($A69,'SUPPLIER DATA BASE'!$A$2:$H$936,5,0),"")) -> - | F69: GSTN-965 | G69: 46044 | H69: 155 | I69: 246671 | J69: DD sales 965.pdf | K69: - | L69: - | M69: =IF(G69="", "", (TODAY() - G69) & " Days") -> 144 Days | N69: =IF($A$3=" "," ", IFERROR( VLOOKUP($A69,'SUPPLIER DATA BASE'!$A$2:$O$936,11,0),"")) -> D D SALES CO | O69: =IF($A$3=" "," ", IFERROR( VLOOKUP($A69,'SUPPLIER DATA BASE'!$A$2:$O$936,12,0),"")) -> 29205007835 | P69: =IF($A$3=" "," ", IFERROR( VLOOKUP($A69,'SUPPLIER DATA BASE'!$A$2:$O$936,13,0),"")) -> ICIC0000292 | V69: =IF(G69="","", IF(AND(G69>=DATE(2024,4,1),G69<=DATE(2025,3,31)),"FY 24-25", IF(AND(G69>=DATE(2025,4,1),G69<=DATE(2026,3,31)),"FY 25-26",IF(AND(G69>=DATE(2026,4,1),G69<=DATE(2027,3,31)),"FY 26-27","")))) -> FY 25-26
A70: D D SALES CO | B70: =IF($A$3=" "," ", IFERROR( VLOOKUP($A70,'SUPPLIER DATA BASE'!$A$2:$M$936,3,0),"")) -> KILLER | C70: =IF($A$3=" "," ", IFERROR( VLOOKUP($A70,'SUPPLIER DATA BASE'!$A$2:$F$936,6,0),"")) -> - | D70: =IF($A$3=" "," ", IFERROR( VLOOKUP($A70,'SUPPLIER DATA BASE'!$A$2:$G$936,4,0),"")) -> NO | E70: =IF($A$3=" "," ", IFERROR( VLOOKUP($A70,'SUPPLIER DATA BASE'!$A$2:$H$936,5,0),"")) -> - | F70: GSTN-962 | G70: 46044 | H70: 238 | I70: 398654 | J70: D D SALES(KILLER)_GSTN962_DUMKA_238PCS.pdf | K70: - | L70: - | M70: =IF(G70="", "", (TODAY() - G70) & " Days") -> 144 Days | N70: =IF($A$3=" "," ", IFERROR( VLOOKUP($A70,'SUPPLIER DATA BASE'!$A$2:$O$936,11,0),"")) -> D D SALES CO | O70: =IF($A$3=" "," ", IFERROR( VLOOKUP($A70,'SUPPLIER DATA BASE'!$A$2:$O$936,12,0),"")) -> 29205007835 | P70: =IF($A$3=" "," ", IFERROR( VLOOKUP($A70,'SUPPLIER DATA BASE'!$A$2:$O$936,13,0),"")) -> ICIC0000292 | V70: =IF(G70="","", IF(AND(G70>=DATE(2024,4,1),G70<=DATE(2025,3,31)),"FY 24-25", IF(AND(G70>=DATE(2025,4,1),G70<=DATE(2026,3,31)),"FY 25-26",IF(AND(G70>=DATE(2026,4,1),G70<=DATE(2027,3,31)),"FY 26-27","")))) -> FY 25-26
A71: B B FASHIONS | B71: =IF($A$3=" "," ", IFERROR( VLOOKUP($A71,'SUPPLIER DATA BASE'!$A$2:$M$936,3,0),"")) -> - | C71: =IF($A$3=" "," ", IFERROR( VLOOKUP($A71,'SUPPLIER DATA BASE'!$A$2:$F$936,6,0),"")) -> - | D71: =IF($A$3=" "," ", IFERROR( VLOOKUP($A71,'SUPPLIER DATA BASE'!$A$2:$G$936,4,0),"")) -> - | E71: =IF($A$3=" "," ", IFERROR( VLOOKUP($A71,'SUPPLIER DATA BASE'!$A$2:$H$936,5,0),"")) -> - | F71: 3001 | G71: 46045 | H71: 102 | I71: 57346 | J71: B B FASHION 3001.pdf | K71: - | L71: - | M71: =IF(G71="", "", (TODAY() - G71) & " Days") -> 143 Days | N71: =IF($A$3=" "," ", IFERROR( VLOOKUP($A71,'SUPPLIER DATA BASE'!$A$2:$O$936,11,0),"")) -> B B FASHIONS | O71: =IF($A$3=" "," ", IFERROR( VLOOKUP($A71,'SUPPLIER DATA BASE'!$A$2:$O$936,12,0),"")) -> 4913058844 | P71: =IF($A$3=" "," ", IFERROR( VLOOKUP($A71,'SUPPLIER DATA BASE'!$A$2:$O$936,13,0),"")) -> KKBK0004599 | V71: =IF(G71="","", IF(AND(G71>=DATE(2024,4,1),G71<=DATE(2025,3,31)),"FY 24-25", IF(AND(G71>=DATE(2025,4,1),G71<=DATE(2026,3,31)),"FY 25-26",IF(AND(G71>=DATE(2026,4,1),G71<=DATE(2027,3,31)),"FY 26-27","")))) -> FY 25-26
A72: GAJENDRA OVERSEAS | B72: =IF($A$3=" "," ", IFERROR( VLOOKUP($A72,'SUPPLIER DATA BASE'!$A$2:$M$936,3,0),"")) -> - | C72: =IF($A$3=" "," ", IFERROR( VLOOKUP($A72,'SUPPLIER DATA BASE'!$A$2:$F$936,6,0),"")) -> SURYAM TEXTILE AGENCY | D72: =IF($A$3=" "," ", IFERROR( VLOOKUP($A72,'SUPPLIER DATA BASE'!$A$2:$G$936,4,0),"")) -> NO | E72: =IF($A$3=" "," ", IFERROR( VLOOKUP($A72,'SUPPLIER DATA BASE'!$A$2:$H$936,5,0),"")) -> - | F72: 3991 | G72: 46045 | H72: 57 | I72: 102706 | J72: Gajendra overseas 3991.pdf | K72: - | L72: - | M72: =IF(G72="", "", (TODAY() - G72) & " Days") -> 143 Days | N72: =IF($A$3=" "," ", IFERROR( VLOOKUP($A72,'SUPPLIER DATA BASE'!$A$2:$O$936,11,0),"")) -> GAJENDRA OVERSEAS | O72: =IF($A$3=" "," ", IFERROR( VLOOKUP($A72,'SUPPLIER DATA BASE'!$A$2:$O$936,12,0),"")) -> 777705312611 | P72: =IF($A$3=" "," ", IFERROR( VLOOKUP($A72,'SUPPLIER DATA BASE'!$A$2:$O$936,13,0),"")) -> ICIC0001387 | V72: =IF(G72="","", IF(AND(G72>=DATE(2024,4,1),G72<=DATE(2025,3,31)),"FY 24-25", IF(AND(G72>=DATE(2025,4,1),G72<=DATE(2026,3,31)),"FY 25-26",IF(AND(G72>=DATE(2026,4,1),G72<=DATE(2027,3,31)),"FY 26-27","")))) -> FY 25-26
A73: JAIN ADISHWAR HOSIERY WORKS LLP | B73: =IF($A$3=" "," ", IFERROR( VLOOKUP($A73,'SUPPLIER DATA BASE'!$A$2:$M$936,3,0),"")) -> - | C73: =IF($A$3=" "," ", IFERROR( VLOOKUP($A73,'SUPPLIER DATA BASE'!$A$2:$F$936,6,0),"")) -> - | D73: =IF($A$3=" "," ", IFERROR( VLOOKUP($A73,'SUPPLIER DATA BASE'!$A$2:$G$936,4,0),"")) -> - | E73: =IF($A$3=" "," ", IFERROR( VLOOKUP($A73,'SUPPLIER DATA BASE'!$A$2:$H$936,5,0),"")) -> - | F73: J/25-26/10323 | G73: 46045 | H73: 195 | I73: 606778 | J73: Jain Adishwar 10323.pdf | K73: - | L73: - | M73: =IF(G73="", "", (TODAY() - G73) & " Days") -> 143 Days | N73: =IF($A$3=" "," ", IFERROR( VLOOKUP($A73,'SUPPLIER DATA BASE'!$A$2:$O$936,11,0),"")) -> JAIN ADISHWAR HOSIERY WORKS LLP | O73: =IF($A$3=" "," ", IFERROR( VLOOKUP($A73,'SUPPLIER DATA BASE'!$A$2:$O$936,12,0),"")) -> 99917644444444 | P73: =IF($A$3=" "," ", IFERROR( VLOOKUP($A73,'SUPPLIER DATA BASE'!$A$2:$O$936,13,0),"")) -> HDFC0002063 | V73: =IF(G73="","", IF(AND(G73>=DATE(2024,4,1),G73<=DATE(2025,3,31)),"FY 24-25", IF(AND(G73>=DATE(2025,4,1),G73<=DATE(2026,3,31)),"FY 25-26",IF(AND(G73>=DATE(2026,4,1),G73<=DATE(2027,3,31)),"FY 26-27","")))) -> FY 25-26
A74: JAIN ADISHWAR HOSIERY WORKS LLP | B74: =IF($A$3=" "," ", IFERROR( VLOOKUP($A74,'SUPPLIER DATA BASE'!$A$2:$M$936,3,0),"")) -> - | C74: =IF($A$3=" "," ", IFERROR( VLOOKUP($A74,'SUPPLIER DATA BASE'!$A$2:$F$936,6,0),"")) -> - | D74: =IF($A$3=" "," ", IFERROR( VLOOKUP($A74,'SUPPLIER DATA BASE'!$A$2:$G$936,4,0),"")) -> - | E74: =IF($A$3=" "," ", IFERROR( VLOOKUP($A74,'SUPPLIER DATA BASE'!$A$2:$H$936,5,0),"")) -> - | F74: J/25-26/10335 | G74: 46046 | H74: 206 | I74: 595367 | J74: Jain Adishwar 10335.pdf | K74: - | L74: - | M74: =IF(G74="", "", (TODAY() - G74) & " Days") -> 142 Days | N74: =IF($A$3=" "," ", IFERROR( VLOOKUP($A74,'SUPPLIER DATA BASE'!$A$2:$O$936,11,0),"")) -> JAIN ADISHWAR HOSIERY WORKS LLP | O74: =IF($A$3=" "," ", IFERROR( VLOOKUP($A74,'SUPPLIER DATA BASE'!$A$2:$O$936,12,0),"")) -> 99917644444444 | P74: =IF($A$3=" "," ", IFERROR( VLOOKUP($A74,'SUPPLIER DATA BASE'!$A$2:$O$936,13,0),"")) -> HDFC0002063 | V74: =IF(G74="","", IF(AND(G74>=DATE(2024,4,1),G74<=DATE(2025,3,31)),"FY 24-25", IF(AND(G74>=DATE(2025,4,1),G74<=DATE(2026,3,31)),"FY 25-26",IF(AND(G74>=DATE(2026,4,1),G74<=DATE(2027,3,31)),"FY 26-27","")))) -> FY 25-26
A75: D D SALES CO | B75: =IF($A$3=" "," ", IFERROR( VLOOKUP($A75,'SUPPLIER DATA BASE'!$A$2:$M$936,3,0),"")) -> KILLER | C75: =IF($A$3=" "," ", IFERROR( VLOOKUP($A75,'SUPPLIER DATA BASE'!$A$2:$F$936,6,0),"")) -> - | D75: =IF($A$3=" "," ", IFERROR( VLOOKUP($A75,'SUPPLIER DATA BASE'!$A$2:$G$936,4,0),"")) -> NO | E75: =IF($A$3=" "," ", IFERROR( VLOOKUP($A75,'SUPPLIER DATA BASE'!$A$2:$H$936,5,0),"")) -> - | F75: GSTN-988 | G75: 46046 | H75: 241 | I75: 415368 | J75: D D SALES CO- 998.pdf | K75: - | L75: - | M75: =IF(G75="", "", (TODAY() - G75) & " Days") -> 142 Days | N75: =IF($A$3=" "," ", IFERROR( VLOOKUP($A75,'SUPPLIER DATA BASE'!$A$2:$O$936,11,0),"")) -> D D SALES CO | O75: =IF($A$3=" "," ", IFERROR( VLOOKUP($A75,'SUPPLIER DATA BASE'!$A$2:$O$936,12,0),"")) -> 29205007835 | P75: =IF($A$3=" "," ", IFERROR( VLOOKUP($A75,'SUPPLIER DATA BASE'!$A$2:$O$936,13,0),"")) -> ICIC0000292 | V75: =IF(G75="","", IF(AND(G75>=DATE(2024,4,1),G75<=DATE(2025,3,31)),"FY 24-25", IF(AND(G75>=DATE(2025,4,1),G75<=DATE(2026,3,31)),"FY 25-26",IF(AND(G75>=DATE(2026,4,1),G75<=DATE(2027,3,31)),"FY 26-27","")))) -> FY 25-26
A76: JAIN ADISHWAR HOSIERY WORKS LLP | B76: =IF($A$3=" "," ", IFERROR( VLOOKUP($A76,'SUPPLIER DATA BASE'!$A$2:$M$936,3,0),"")) -> - | C76: =IF($A$3=" "," ", IFERROR( VLOOKUP($A76,'SUPPLIER DATA BASE'!$A$2:$F$936,6,0),"")) -> - | D76: =IF($A$3=" "," ", IFERROR( VLOOKUP($A76,'SUPPLIER DATA BASE'!$A$2:$G$936,4,0),"")) -> - | E76: =IF($A$3=" "," ", IFERROR( VLOOKUP($A76,'SUPPLIER DATA BASE'!$A$2:$H$936,5,0),"")) -> - | F76: J/25-26/10388 | G76: 46050 | H76: 200 | I76: 633512 | J76: Jain Adishwar 10388.pdf | K76: - | L76: - | M76: =IF(G76="", "", (TODAY() - G76) & " Days") -> 138 Days | N76: =IF($A$3=" "," ", IFERROR( VLOOKUP($A76,'SUPPLIER DATA BASE'!$A$2:$O$936,11,0),"")) -> JAIN ADISHWAR HOSIERY WORKS LLP | O76: =IF($A$3=" "," ", IFERROR( VLOOKUP($A76,'SUPPLIER DATA BASE'!$A$2:$O$936,12,0),"")) -> 99917644444444 | P76: =IF($A$3=" "," ", IFERROR( VLOOKUP($A76,'SUPPLIER DATA BASE'!$A$2:$O$936,13,0),"")) -> HDFC0002063 | V76: =IF(G76="","", IF(AND(G76>=DATE(2024,4,1),G76<=DATE(2025,3,31)),"FY 24-25", IF(AND(G76>=DATE(2025,4,1),G76<=DATE(2026,3,31)),"FY 25-26",IF(AND(G76>=DATE(2026,4,1),G76<=DATE(2027,3,31)),"FY 26-27","")))) -> FY 25-26
A77: SRI RADHEY MACHING CENTER | B77: =IF($A$3=" "," ", IFERROR( VLOOKUP($A77,'SUPPLIER DATA BASE'!$A$2:$M$936,3,0),"")) -> PETTY COAT | C77: =IF($A$3=" "," ", IFERROR( VLOOKUP($A77,'SUPPLIER DATA BASE'!$A$2:$F$936,6,0),"")) -> - | D77: =IF($A$3=" "," ", IFERROR( VLOOKUP($A77,'SUPPLIER DATA BASE'!$A$2:$G$936,4,0),"")) -> - | E77: =IF($A$3=" "," ", IFERROR( VLOOKUP($A77,'SUPPLIER DATA BASE'!$A$2:$H$936,5,0),"")) -> - | F77: 597 | G77: 46050 | H77: 314 | I77: 35929 | J77: Shree radhe matching 597.pdf | K77: - | L77: - | M77: =IF(G77="", "", (TODAY() - G77) & " Days") -> 138 Days | N77: =IF($A$3=" "," ", IFERROR( VLOOKUP($A77,'SUPPLIER DATA BASE'!$A$2:$O$936,11,0),"")) -> SRI RADHEY MACHING CENTER | O77: =IF($A$3=" "," ", IFERROR( VLOOKUP($A77,'SUPPLIER DATA BASE'!$A$2:$O$936,12,0),"")) -> 3626026563 | P77: =IF($A$3=" "," ", IFERROR( VLOOKUP($A77,'SUPPLIER DATA BASE'!$A$2:$O$936,13,0),"")) -> CBIN0281393 | V77: =IF(G77="","", IF(AND(G77>=DATE(2024,4,1),G77<=DATE(2025,3,31)),"FY 24-25", IF(AND(G77>=DATE(2025,4,1),G77<=DATE(2026,3,31)),"FY 25-26",IF(AND(G77>=DATE(2026,4,1),G77<=DATE(2027,3,31)),"FY 26-27","")))) -> FY 25-26
A78: SARAOGI SUPER SALES PVT LTD | B78: =IF($A$3=" "," ", IFERROR( VLOOKUP($A78,'SUPPLIER DATA BASE'!$A$2:$M$936,3,0),"")) -> - | C78: =IF($A$3=" "," ", IFERROR( VLOOKUP($A78,'SUPPLIER DATA BASE'!$A$2:$F$936,6,0),"")) -> - | D78: =IF($A$3=" "," ", IFERROR( VLOOKUP($A78,'SUPPLIER DATA BASE'!$A$2:$G$936,4,0),"")) -> - | E78: =IF($A$3=" "," ", IFERROR( VLOOKUP($A78,'SUPPLIER DATA BASE'!$A$2:$H$936,5,0),"")) -> - | F78: 25-26/BLRS1700 | G78: 46051 | H78: 36 | I78: 29460 | J78: saraogi super sales 1700.pdf | K78: - | L78: - | M78: =IF(G78="", "", (TODAY() - G78) & " Days") -> 137 Days | N78: =IF($A$3=" "," ", IFERROR( VLOOKUP($A78,'SUPPLIER DATA BASE'!$A$2:$O$936,11,0),"")) -> SARAOGI SUPER SALES PVT LTD | O78: =IF($A$3=" "," ", IFERROR( VLOOKUP($A78,'SUPPLIER DATA BASE'!$A$2:$O$936,12,0),"")) -> SASUSP011006 | P78: =IF($A$3=" "," ", IFERROR( VLOOKUP($A78,'SUPPLIER DATA BASE'!$A$2:$O$936,13,0),"")) -> ICIC0000106 | V78: =IF(G78="","", IF(AND(G78>=DATE(2024,4,1),G78<=DATE(2025,3,31)),"FY 24-25", IF(AND(G78>=DATE(2025,4,1),G78<=DATE(2026,3,31)),"FY 25-26",IF(AND(G78>=DATE(2026,4,1),G78<=DATE(2027,3,31)),"FY 26-27","")))) -> FY 25-26
A79: ADITYA BIRLA | B79: =IF($A$3=" "," ", IFERROR( VLOOKUP($A79,'SUPPLIER DATA BASE'!$A$2:$M$936,3,0),"")) -> - | C79: =IF($A$3=" "," ", IFERROR( VLOOKUP($A79,'SUPPLIER DATA BASE'!$A$2:$F$936,6,0),"")) -> - | D79: =IF($A$3=" "," ", IFERROR( VLOOKUP($A79,'SUPPLIER DATA BASE'!$A$2:$G$936,4,0),"")) -> - | E79: =IF($A$3=" "," ", IFERROR( VLOOKUP($A79,'SUPPLIER DATA BASE'!$A$2:$H$936,5,0),"")) -> - | F79: MSF2252000027777 | G79: 46051 | H79: 18 | I79: 32845.85 | J79: MSFS2252000027777 JS HAZARIBAG.pdf | K79: - | L79: - | M79: =IF(G79="", "", (TODAY() - G79) & " Days") -> 137 Days | N79: =IF($A$3=" "," ", IFERROR( VLOOKUP($A79,'SUPPLIER DATA BASE'!$A$2:$O$936,11,0),"")) -> - | O79: =IF($A$3=" "," ", IFERROR( VLOOKUP($A79,'SUPPLIER DATA BASE'!$A$2:$O$936,12,0),"")) -> - | P79: =IF($A$3=" "," ", IFERROR( VLOOKUP($A79,'SUPPLIER DATA BASE'!$A$2:$O$936,13,0),"")) -> - | V79: =IF(G79="","", IF(AND(G79>=DATE(2024,4,1),G79<=DATE(2025,3,31)),"FY 24-25", IF(AND(G79>=DATE(2025,4,1),G79<=DATE(2026,3,31)),"FY 25-26",IF(AND(G79>=DATE(2026,4,1),G79<=DATE(2027,3,31)),"FY 26-27","")))) -> FY 25-26
A80: ADITYA BIRLA | B80: =IF($A$3=" "," ", IFERROR( VLOOKUP($A80,'SUPPLIER DATA BASE'!$A$2:$M$936,3,0),"")) -> - | C80: =IF($A$3=" "," ", IFERROR( VLOOKUP($A80,'SUPPLIER DATA BASE'!$A$2:$F$936,6,0),"")) -> - | D80: =IF($A$3=" "," ", IFERROR( VLOOKUP($A80,'SUPPLIER DATA BASE'!$A$2:$G$936,4,0),"")) -> - | E80: =IF($A$3=" "," ", IFERROR( VLOOKUP($A80,'SUPPLIER DATA BASE'!$A$2:$H$936,5,0),"")) -> - | F80: MSF2252000027759 | G80: 46051 | H80: 102 | I80: 171967.42 | J80: MSF2252000027759 JS HAZARIBAG.pdf | K80: - | L80: - | M80: =IF(G80="", "", (TODAY() - G80) & " Days") -> 137 Days | N80: =IF($A$3=" "," ", IFERROR( VLOOKUP($A80,'SUPPLIER DATA BASE'!$A$2:$O$936,11,0),"")) -> - | O80: =IF($A$3=" "," ", IFERROR( VLOOKUP($A80,'SUPPLIER DATA BASE'!$A$2:$O$936,12,0),"")) -> - | P80: =IF($A$3=" "," ", IFERROR( VLOOKUP($A80,'SUPPLIER DATA BASE'!$A$2:$O$936,13,0),"")) -> - | V80: =IF(G80="","", IF(AND(G80>=DATE(2024,4,1),G80<=DATE(2025,3,31)),"FY 24-25", IF(AND(G80>=DATE(2025,4,1),G80<=DATE(2026,3,31)),"FY 25-26",IF(AND(G80>=DATE(2026,4,1),G80<=DATE(2027,3,31)),"FY 26-27","")))) -> FY 25-26
A81: ADITYA BIRLA | B81: =IF($A$3=" "," ", IFERROR( VLOOKUP($A81,'SUPPLIER DATA BASE'!$A$2:$M$936,3,0),"")) -> - | C81: =IF($A$3=" "," ", IFERROR( VLOOKUP($A81,'SUPPLIER DATA BASE'!$A$2:$F$936,6,0),"")) -> - | D81: =IF($A$3=" "," ", IFERROR( VLOOKUP($A81,'SUPPLIER DATA BASE'!$A$2:$G$936,4,0),"")) -> - | E81: =IF($A$3=" "," ", IFERROR( VLOOKUP($A81,'SUPPLIER DATA BASE'!$A$2:$H$936,5,0),"")) -> - | F81: MSF2252000027872 | G81: 46052 | H81: 20 | I81: 19409.76 | J81: MSF2252000027872 JS HAZARIBAG.pdf | K81: - | L81: - | M81: =IF(G81="", "", (TODAY() - G81) & " Days") -> 136 Days | N81: =IF($A$3=" "," ", IFERROR( VLOOKUP($A81,'SUPPLIER DATA BASE'!$A$2:$O$936,11,0),"")) -> - | O81: =IF($A$3=" "," ", IFERROR( VLOOKUP($A81,'SUPPLIER DATA BASE'!$A$2:$O$936,12,0),"")) -> - | P81: =IF($A$3=" "," ", IFERROR( VLOOKUP($A81,'SUPPLIER DATA BASE'!$A$2:$O$936,13,0),"")) -> - | V81: =IF(G81="","", IF(AND(G81>=DATE(2024,4,1),G81<=DATE(2025,3,31)),"FY 24-25", IF(AND(G81>=DATE(2025,4,1),G81<=DATE(2026,3,31)),"FY 25-26",IF(AND(G81>=DATE(2026,4,1),G81<=DATE(2027,3,31)),"FY 26-27","")))) -> FY 25-26
A82: ADITYA BIRLA | B82: =IF($A$3=" "," ", IFERROR( VLOOKUP($A82,'SUPPLIER DATA BASE'!$A$2:$M$936,3,0),"")) -> - | C82: =IF($A$3=" "," ", IFERROR( VLOOKUP($A82,'SUPPLIER DATA BASE'!$A$2:$F$936,6,0),"")) -> - | D82: =IF($A$3=" "," ", IFERROR( VLOOKUP($A82,'SUPPLIER DATA BASE'!$A$2:$G$936,4,0),"")) -> - | E82: =IF($A$3=" "," ", IFERROR( VLOOKUP($A82,'SUPPLIER DATA BASE'!$A$2:$H$936,5,0),"")) -> - | F82: MSF2252000027910 | G82: 46052 | H82: 142 | I82: 170944.08 | J82: MSF2252000027910 JS HAZARIBAG.pdf | K82: - | L82: - | M82: =IF(G82="", "", (TODAY() - G82) & " Days") -> 136 Days | N82: =IF($A$3=" "," ", IFERROR( VLOOKUP($A82,'SUPPLIER DATA BASE'!$A$2:$O$936,11,0),"")) -> - | O82: =IF($A$3=" "," ", IFERROR( VLOOKUP($A82,'SUPPLIER DATA BASE'!$A$2:$O$936,12,0),"")) -> - | P82: =IF($A$3=" "," ", IFERROR( VLOOKUP($A82,'SUPPLIER DATA BASE'!$A$2:$O$936,13,0),"")) -> - | V82: =IF(G82="","", IF(AND(G82>=DATE(2024,4,1),G82<=DATE(2025,3,31)),"FY 24-25", IF(AND(G82>=DATE(2025,4,1),G82<=DATE(2026,3,31)),"FY 25-26",IF(AND(G82>=DATE(2026,4,1),G82<=DATE(2027,3,31)),"FY 26-27","")))) -> FY 25-26
A83: ADITYA BIRLA | B83: =IF($A$3=" "," ", IFERROR( VLOOKUP($A83,'SUPPLIER DATA BASE'!$A$2:$M$936,3,0),"")) -> - | C83: =IF($A$3=" "," ", IFERROR( VLOOKUP($A83,'SUPPLIER DATA BASE'!$A$2:$F$936,6,0),"")) -> - | D83: =IF($A$3=" "," ", IFERROR( VLOOKUP($A83,'SUPPLIER DATA BASE'!$A$2:$G$936,4,0),"")) -> - | E83: =IF($A$3=" "," ", IFERROR( VLOOKUP($A83,'SUPPLIER DATA BASE'!$A$2:$H$936,5,0),"")) -> - | F83: MSF2252000027897 | G83: 46052 | H83: 36 | I83: 70099.05 | J83: MSF2252000027897 JS HAZARIBAG.pdf | K83: - | L83: - | M83: =IF(G83="", "", (TODAY() - G83) & " Days") -> 136 Days | N83: =IF($A$3=" "," ", IFERROR( VLOOKUP($A83,'SUPPLIER DATA BASE'!$A$2:$O$936,11,0),"")) -> - | O83: =IF($A$3=" "," ", IFERROR( VLOOKUP($A83,'SUPPLIER DATA BASE'!$A$2:$O$936,12,0),"")) -> - | P83: =IF($A$3=" "," ", IFERROR( VLOOKUP($A83,'SUPPLIER DATA BASE'!$A$2:$O$936,13,0),"")) -> - | V83: =IF(G83="","", IF(AND(G83>=DATE(2024,4,1),G83<=DATE(2025,3,31)),"FY 24-25", IF(AND(G83>=DATE(2025,4,1),G83<=DATE(2026,3,31)),"FY 25-26",IF(AND(G83>=DATE(2026,4,1),G83<=DATE(2027,3,31)),"FY 26-27","")))) -> FY 25-26
A84: ADITYA BIRLA | B84: =IF($A$3=" "," ", IFERROR( VLOOKUP($A84,'SUPPLIER DATA BASE'!$A$2:$M$936,3,0),"")) -> - | C84: =IF($A$3=" "," ", IFERROR( VLOOKUP($A84,'SUPPLIER DATA BASE'!$A$2:$F$936,6,0),"")) -> - | D84: =IF($A$3=" "," ", IFERROR( VLOOKUP($A84,'SUPPLIER DATA BASE'!$A$2:$G$936,4,0),"")) -> - | E84: =IF($A$3=" "," ", IFERROR( VLOOKUP($A84,'SUPPLIER DATA BASE'!$A$2:$H$936,5,0),"")) -> - | F84: MSF2252000027883 | G84: 46052 | H84: 11 | I84: 22280.06 | J84: MSF2252000027883 JS HAZARIBAG.pdf | K84: - | L84: - | M84: =IF(G84="", "", (TODAY() - G84) & " Days") -> 136 Days | N84: =IF($A$3=" "," ", IFERROR( VLOOKUP($A84,'SUPPLIER DATA BASE'!$A$2:$O$936,11,0),"")) -> - | O84: =IF($A$3=" "," ", IFERROR( VLOOKUP($A84,'SUPPLIER DATA BASE'!$A$2:$O$936,12,0),"")) -> - | P84: =IF($A$3=" "," ", IFERROR( VLOOKUP($A84,'SUPPLIER DATA BASE'!$A$2:$O$936,13,0),"")) -> - | V84: =IF(G84="","", IF(AND(G84>=DATE(2024,4,1),G84<=DATE(2025,3,31)),"FY 24-25", IF(AND(G84>=DATE(2025,4,1),G84<=DATE(2026,3,31)),"FY 25-26",IF(AND(G84>=DATE(2026,4,1),G84<=DATE(2027,3,31)),"FY 26-27","")))) -> FY 25-26
A85: ADITYA BIRLA | B85: =IF($A$3=" "," ", IFERROR( VLOOKUP($A85,'SUPPLIER DATA BASE'!$A$2:$M$936,3,0),"")) -> - | C85: =IF($A$3=" "," ", IFERROR( VLOOKUP($A85,'SUPPLIER DATA BASE'!$A$2:$F$936,6,0),"")) -> - | D85: =IF($A$3=" "," ", IFERROR( VLOOKUP($A85,'SUPPLIER DATA BASE'!$A$2:$G$936,4,0),"")) -> - | E85: =IF($A$3=" "," ", IFERROR( VLOOKUP($A85,'SUPPLIER DATA BASE'!$A$2:$H$936,5,0),"")) -> - | F85: MSF2252000027853 | G85: 46052 | H85: 15 | I85: 21755.16 | J85: ADITYA BIRLA_MSF2252000027853_AS_S-RATU_25-26.pdf | K85: - | L85: - | M85: =IF(G85="", "", (TODAY() - G85) & " Days") -> 136 Days | N85: =IF($A$3=" "," ", IFERROR( VLOOKUP($A85,'SUPPLIER DATA BASE'!$A$2:$O$936,11,0),"")) -> - | O85: =IF($A$3=" "," ", IFERROR( VLOOKUP($A85,'SUPPLIER DATA BASE'!$A$2:$O$936,12,0),"")) -> - | P85: =IF($A$3=" "," ", IFERROR( VLOOKUP($A85,'SUPPLIER DATA BASE'!$A$2:$O$936,13,0),"")) -> - | V85: =IF(G85="","", IF(AND(G85>=DATE(2024,4,1),G85<=DATE(2025,3,31)),"FY 24-25", IF(AND(G85>=DATE(2025,4,1),G85<=DATE(2026,3,31)),"FY 25-26",IF(AND(G85>=DATE(2026,4,1),G85<=DATE(2027,3,31)),"FY 26-27","")))) -> FY 25-26
A86: SARAOGI SUPER SALES PVT LTD | B86: =IF($A$3=" "," ", IFERROR( VLOOKUP($A86,'SUPPLIER DATA BASE'!$A$2:$M$936,3,0),"")) -> - | C86: =IF($A$3=" "," ", IFERROR( VLOOKUP($A86,'SUPPLIER DATA BASE'!$A$2:$F$936,6,0),"")) -> - | D86: =IF($A$3=" "," ", IFERROR( VLOOKUP($A86,'SUPPLIER DATA BASE'!$A$2:$G$936,4,0),"")) -> - | E86: =IF($A$3=" "," ", IFERROR( VLOOKUP($A86,'SUPPLIER DATA BASE'!$A$2:$H$936,5,0),"")) -> - | F86: 25-26/BLRS1730 | G86: 46053 | H86: 22 | I86: 34304 | J86: Saraogi super sales 1730.pdf | K86: - | L86: - | M86: =IF(G86="", "", (TODAY() - G86) & " Days") -> 135 Days | N86: =IF($A$3=" "," ", IFERROR( VLOOKUP($A86,'SUPPLIER DATA BASE'!$A$2:$O$936,11,0),"")) -> SARAOGI SUPER SALES PVT LTD | O86: =IF($A$3=" "," ", IFERROR( VLOOKUP($A86,'SUPPLIER DATA BASE'!$A$2:$O$936,12,0),"")) -> SASUSP011006 | P86: =IF($A$3=" "," ", IFERROR( VLOOKUP($A86,'SUPPLIER DATA BASE'!$A$2:$O$936,13,0),"")) -> ICIC0000106 | V86: =IF(G86="","", IF(AND(G86>=DATE(2024,4,1),G86<=DATE(2025,3,31)),"FY 24-25", IF(AND(G86>=DATE(2025,4,1),G86<=DATE(2026,3,31)),"FY 25-26",IF(AND(G86>=DATE(2026,4,1),G86<=DATE(2027,3,31)),"FY 26-27","")))) -> FY 25-26
A87: ADITYA BIRLA | B87: =IF($A$3=" "," ", IFERROR( VLOOKUP($A87,'SUPPLIER DATA BASE'!$A$2:$M$936,3,0),"")) -> - | C87: =IF($A$3=" "," ", IFERROR( VLOOKUP($A87,'SUPPLIER DATA BASE'!$A$2:$F$936,6,0),"")) -> - | D87: =IF($A$3=" "," ", IFERROR( VLOOKUP($A87,'SUPPLIER DATA BASE'!$A$2:$G$936,4,0),"")) -> - | E87: =IF($A$3=" "," ", IFERROR( VLOOKUP($A87,'SUPPLIER DATA BASE'!$A$2:$H$936,5,0),"")) -> - | F87: MSF2252000027975 | G87: 46053 | H87: 14 | I87: 30443.37 | J87: MSF2252000027975 js hazaribag.pdf | K87: - | L87: - | M87: =IF(G87="", "", (TODAY() - G87) & " Days") -> 135 Days | N87: =IF($A$3=" "," ", IFERROR( VLOOKUP($A87,'SUPPLIER DATA BASE'!$A$2:$O$936,11,0),"")) -> - | O87: =IF($A$3=" "," ", IFERROR( VLOOKUP($A87,'SUPPLIER DATA BASE'!$A$2:$O$936,12,0),"")) -> - | P87: =IF($A$3=" "," ", IFERROR( VLOOKUP($A87,'SUPPLIER DATA BASE'!$A$2:$O$936,13,0),"")) -> - | V87: =IF(G87="","", IF(AND(G87>=DATE(2024,4,1),G87<=DATE(2025,3,31)),"FY 24-25", IF(AND(G87>=DATE(2025,4,1),G87<=DATE(2026,3,31)),"FY 25-26",IF(AND(G87>=DATE(2026,4,1),G87<=DATE(2027,3,31)),"FY 26-27","")))) -> FY 25-26
A88: ADITYA BIRLA | B88: =IF($A$3=" "," ", IFERROR( VLOOKUP($A88,'SUPPLIER DATA BASE'!$A$2:$M$936,3,0),"")) -> - | C88: =IF($A$3=" "," ", IFERROR( VLOOKUP($A88,'SUPPLIER DATA BASE'!$A$2:$F$936,6,0),"")) -> - | D88: =IF($A$3=" "," ", IFERROR( VLOOKUP($A88,'SUPPLIER DATA BASE'!$A$2:$G$936,4,0),"")) -> - | E88: =IF($A$3=" "," ", IFERROR( VLOOKUP($A88,'SUPPLIER DATA BASE'!$A$2:$H$936,5,0),"")) -> - | F88: MSF2252000027998 | G88: 46053 | H88: 6 | I88: 13883.16 | J88: MSF2252000027998 JS HAZARIBAG.pdf | K88: - | L88: - | M88: =IF(G88="", "", (TODAY() - G88) & " Days") -> 135 Days | N88: =IF($A$3=" "," ", IFERROR( VLOOKUP($A88,'SUPPLIER DATA BASE'!$A$2:$O$936,11,0),"")) -> - | O88: =IF($A$3=" "," ", IFERROR( VLOOKUP($A88,'SUPPLIER DATA BASE'!$A$2:$O$936,12,0),"")) -> - | P88: =IF($A$3=" "," ", IFERROR( VLOOKUP($A88,'SUPPLIER DATA BASE'!$A$2:$O$936,13,0),"")) -> - | V88: =IF(G88="","", IF(AND(G88>=DATE(2024,4,1),G88<=DATE(2025,3,31)),"FY 24-25", IF(AND(G88>=DATE(2025,4,1),G88<=DATE(2026,3,31)),"FY 25-26",IF(AND(G88>=DATE(2026,4,1),G88<=DATE(2027,3,31)),"FY 26-27","")))) -> FY 25-26
A89: ADITYA BIRLA | B89: =IF($A$3=" "," ", IFERROR( VLOOKUP($A89,'SUPPLIER DATA BASE'!$A$2:$M$936,3,0),"")) -> - | C89: =IF($A$3=" "," ", IFERROR( VLOOKUP($A89,'SUPPLIER DATA BASE'!$A$2:$F$936,6,0),"")) -> - | D89: =IF($A$3=" "," ", IFERROR( VLOOKUP($A89,'SUPPLIER DATA BASE'!$A$2:$G$936,4,0),"")) -> - | E89: =IF($A$3=" "," ", IFERROR( VLOOKUP($A89,'SUPPLIER DATA BASE'!$A$2:$H$936,5,0),"")) -> - | F89: MSF2252000027977 | G89: 46053 | H89: 1 | I89: 1790.14 | J89: MSF2252000027977 JS HAZARIBAG.pdf | K89: - | L89: - | M89: =IF(G89="", "", (TODAY() - G89) & " Days") -> 135 Days | N89: =IF($A$3=" "," ", IFERROR( VLOOKUP($A89,'SUPPLIER DATA BASE'!$A$2:$O$936,11,0),"")) -> - | O89: =IF($A$3=" "," ", IFERROR( VLOOKUP($A89,'SUPPLIER DATA BASE'!$A$2:$O$936,12,0),"")) -> - | P89: =IF($A$3=" "," ", IFERROR( VLOOKUP($A89,'SUPPLIER DATA BASE'!$A$2:$O$936,13,0),"")) -> - | V89: =IF(G89="","", IF(AND(G89>=DATE(2024,4,1),G89<=DATE(2025,3,31)),"FY 24-25", IF(AND(G89>=DATE(2025,4,1),G89<=DATE(2026,3,31)),"FY 25-26",IF(AND(G89>=DATE(2026,4,1),G89<=DATE(2027,3,31)),"FY 26-27","")))) -> FY 25-26
... A95: MEGHA DRESSES | B95: =IF($A$3=" "," ", IFERROR( VLOOKUP($A95,'SUPPLIER DATA BASE'!$A$2:$M$936,3,0),"")) -> - | C95: =IF($A$3=" "," ", IFERROR( VLOOKUP($A95,'SUPPLIER DATA BASE'!$A$2:$F$936,6,0),"")) -> RTC | D95: =IF($A$3=" "," ", IFERROR( VLOOKUP($A95,'SUPPLIER DATA BASE'!$A$2:$G$936,4,0),"")) -> - | E95: =IF($A$3=" "," ", IFERROR( VLOOKUP($A95,'SUPPLIER DATA BASE'!$A$2:$H$936,5,0),"")) -> - | F95: 25-26/3058 | G95: 46055 | H95: 64 | I95: 48047 | J95: MEGHA DRESSES_3058_SANSKAR_2025-26.pdf | K95: - | L95: - | M95: =IF(G95="", "", (TODAY() - G95) & " Days") -> 133 Days | N95: =IF($A$3=" "," ", IFERROR( VLOOKUP($A95,'SUPPLIER DATA BASE'!$A$2:$O$936,11,0),"")) -> RTC Garmentex India Pvgt LTd | O95: =IF($A$3=" "," ", IFERROR( VLOOKUP($A95,'SUPPLIER DATA BASE'!$A$2:$O$936,12,0),"")) -> 112605502571 | P95: =IF($A$3=" "," ", IFERROR( VLOOKUP($A95,'SUPPLIER DATA BASE'!$A$2:$O$936,13,0),"")) -> ICIC0001126 | V95: =IF(G95="","", IF(AND(G95>=DATE(2024,4,1),G95<=DATE(2025,3,31)),"FY 24-25", IF(AND(G95>=DATE(2025,4,1),G95<=DATE(2026,3,31)),"FY 25-26",IF(AND(G95>=DATE(2026,4,1),G95<=DATE(2027,3,31)),"FY 26-27","")))) -> FY 25-26
A96: ADITYA BIRLA | B96: =IF($A$3=" "," ", IFERROR( VLOOKUP($A96,'SUPPLIER DATA BASE'!$A$2:$M$936,3,0),"")) -> - | C96: =IF($A$3=" "," ", IFERROR( VLOOKUP($A96,'SUPPLIER DATA BASE'!$A$2:$F$936,6,0),"")) -> - | D96: =IF($A$3=" "," ", IFERROR( VLOOKUP($A96,'SUPPLIER DATA BASE'!$A$2:$G$936,4,0),"")) -> - | E96: =IF($A$3=" "," ", IFERROR( VLOOKUP($A96,'SUPPLIER DATA BASE'!$A$2:$H$936,5,0),"")) -> - | F96: MSF2252000028201 | G96: 46055 | H96: 10 | I96: 16745.56 | J96: ADITYA BIRLA_MSF2252000028201_AS_HZB_10PCS.pdf | K96: - | M96: =IF(G96="", "", (TODAY() - G96) & " Days") -> 133 Days | N96: =IF($A$3=" "," ", IFERROR( VLOOKUP($A96,'SUPPLIER DATA BASE'!$A$2:$O$936,11,0),"")) -> - | O96: =IF($A$3=" "," ", IFERROR( VLOOKUP($A96,'SUPPLIER DATA BASE'!$A$2:$O$936,12,0),"")) -> - | P96: =IF($A$3=" "," ", IFERROR( VLOOKUP($A96,'SUPPLIER DATA BASE'!$A$2:$O$936,13,0),"")) -> - | V96: =IF(G96="","", IF(AND(G96>=DATE(2024,4,1),G96<=DATE(2025,3,31)),"FY 24-25", IF(AND(G96>=DATE(2025,4,1),G96<=DATE(2026,3,31)),"FY 25-26",IF(AND(G96>=DATE(2026,4,1),G96<=DATE(2027,3,31)),"FY 26-27","")))) -> FY 25-26
A97: SARAOGI SUPER SALES PVT LTD | B97: =IF($A$3=" "," ", IFERROR( VLOOKUP($A97,'SUPPLIER DATA BASE'!$A$2:$M$936,3,0),"")) -> - | C97: =IF($A$3=" "," ", IFERROR( VLOOKUP($A97,'SUPPLIER DATA BASE'!$A$2:$F$936,6,0),"")) -> - | D97: =IF($A$3=" "," ", IFERROR( VLOOKUP($A97,'SUPPLIER DATA BASE'!$A$2:$G$936,4,0),"")) -> - | E97: =IF($A$3=" "," ", IFERROR( VLOOKUP($A97,'SUPPLIER DATA BASE'!$A$2:$H$936,5,0),"")) -> - | F97: 25-26/BLRS1755 | G97: 46056 | H97: 28 | I97: 39207 | J97: saraogi super sales 1755.pdf | K97: - | L97: - | M97: =IF(G97="", "", (TODAY() - G97) & " Days") -> 132 Days | N97: =IF($A$3=" "," ", IFERROR( VLOOKUP($A97,'SUPPLIER DATA BASE'!$A$2:$O$936,11,0),"")) -> SARAOGI SUPER SALES PVT LTD | O97: =IF($A$3=" "," ", IFERROR( VLOOKUP($A97,'SUPPLIER DATA BASE'!$A$2:$O$936,12,0),"")) -> SASUSP011006 | P97: =IF($A$3=" "," ", IFERROR( VLOOKUP($A97,'SUPPLIER DATA BASE'!$A$2:$O$936,13,0),"")) -> ICIC0000106 | V97: =IF(G97="","", IF(AND(G97>=DATE(2024,4,1),G97<=DATE(2025,3,31)),"FY 24-25", IF(AND(G97>=DATE(2025,4,1),G97<=DATE(2026,3,31)),"FY 25-26",IF(AND(G97>=DATE(2026,4,1),G97<=DATE(2027,3,31)),"FY 26-27","")))) -> FY 25-26
A98: SARAOGI SUPER SALES PVT LTD | B98: =IF($A$3=" "," ", IFERROR( VLOOKUP($A98,'SUPPLIER DATA BASE'!$A$2:$M$936,3,0),"")) -> - | C98: =IF($A$3=" "," ", IFERROR( VLOOKUP($A98,'SUPPLIER DATA BASE'!$A$2:$F$936,6,0),"")) -> - | D98: =IF($A$3=" "," ", IFERROR( VLOOKUP($A98,'SUPPLIER DATA BASE'!$A$2:$G$936,4,0),"")) -> - | E98: =IF($A$3=" "," ", IFERROR( VLOOKUP($A98,'SUPPLIER DATA BASE'!$A$2:$H$936,5,0),"")) -> - | F98: 25-26/BLRS1753 | G98: 46056 | H98: 17 | I98: 36575 | J98: saraogi super sales 1753.pdf | K98: - | L98: - | M98: =IF(G98="", "", (TODAY() - G98) & " Days") -> 132 Days | N98: =IF($A$3=" "," ", IFERROR( VLOOKUP($A98,'SUPPLIER DATA BASE'!$A$2:$O$936,11,0),"")) -> SARAOGI SUPER SALES PVT LTD | O98: =IF($A$3=" "," ", IFERROR( VLOOKUP($A98,'SUPPLIER DATA BASE'!$A$2:$O$936,12,0),"")) -> SASUSP011006 | P98: =IF($A$3=" "," ", IFERROR( VLOOKUP($A98,'SUPPLIER DATA BASE'!$A$2:$O$936,13,0),"")) -> ICIC0000106 | V98: =IF(G98="","", IF(AND(G98>=DATE(2024,4,1),G98<=DATE(2025,3,31)),"FY 24-25", IF(AND(G98>=DATE(2025,4,1),G98<=DATE(2026,3,31)),"FY 25-26",IF(AND(G98>=DATE(2026,4,1),G98<=DATE(2027,3,31)),"FY 26-27","")))) -> FY 25-26
A99: ADITYA BIRLA | B99: =IF($A$3=" "," ", IFERROR( VLOOKUP($A99,'SUPPLIER DATA BASE'!$A$2:$M$936,3,0),"")) -> - | C99: =IF($A$3=" "," ", IFERROR( VLOOKUP($A99,'SUPPLIER DATA BASE'!$A$2:$F$936,6,0),"")) -> - | D99: =IF($A$3=" "," ", IFERROR( VLOOKUP($A99,'SUPPLIER DATA BASE'!$A$2:$G$936,4,0),"")) -> - | E99: =IF($A$3=" "," ", IFERROR( VLOOKUP($A99,'SUPPLIER DATA BASE'!$A$2:$H$936,5,0),"")) -> - | F99: MSF2252000028299 | G99: 46056 | H99: 10 | I99: 24903.4 | J99: VSN DEO MSF 2252000028299.pdf | K99: - | L99: - | M99: =IF(G99="", "", (TODAY() - G99) & " Days") -> 132 Days | N99: =IF($A$3=" "," ", IFERROR( VLOOKUP($A99,'SUPPLIER DATA BASE'!$A$2:$O$936,11,0),"")) -> - | O99: =IF($A$3=" "," ", IFERROR( VLOOKUP($A99,'SUPPLIER DATA BASE'!$A$2:$O$936,12,0),"")) -> - | P99: =IF($A$3=" "," ", IFERROR( VLOOKUP($A99,'SUPPLIER DATA BASE'!$A$2:$O$936,13,0),"")) -> - | V99: =IF(G99="","", IF(AND(G99>=DATE(2024,4,1),G99<=DATE(2025,3,31)),"FY 24-25", IF(AND(G99>=DATE(2025,4,1),G99<=DATE(2026,3,31)),"FY 25-26",IF(AND(G99>=DATE(2026,4,1),G99<=DATE(2027,3,31)),"FY 26-27","")))) -> FY 25-26
A100: SHUBH SHRI CLOTHING PVT LTD | B100: =IF($A$3=" "," ", IFERROR( VLOOKUP($A100,'SUPPLIER DATA BASE'!$A$2:$M$936,3,0),"")) -> MINELLI | C100: =IF($A$3=" "," ", IFERROR( VLOOKUP($A100,'SUPPLIER DATA BASE'!$A$2:$F$936,6,0),"")) -> - | D100: =IF($A$3=" "," ", IFERROR( VLOOKUP($A100,'SUPPLIER DATA BASE'!$A$2:$G$936,4,0),"")) -> 45 | E100: =IF($A$3=" "," ", IFERROR( VLOOKUP($A100,'SUPPLIER DATA BASE'!$A$2:$H$936,5,0),"")) -> 0.1 | F100: SS/25-26/04989 | G100: 46056 | I100: 75079 | M100: =IF(G100="", "", (TODAY() - G100) & " Days") -> 132 Days | N100: =IF($A$3=" "," ", IFERROR( VLOOKUP($A100,'SUPPLIER DATA BASE'!$A$2:$O$936,11,0),"")) -> SHUBH SHRI CLOTHING PVT LTD | O100: =IF($A$3=" "," ", IFERROR( VLOOKUP($A100,'SUPPLIER DATA BASE'!$A$2:$O$936,12,0),"")) -> 002225010000006 | P100: =IF($A$3=" "," ", IFERROR( VLOOKUP($A100,'SUPPLIER DATA BASE'!$A$2:$O$936,13,0),"")) -> UBIN0900222 | Q100: 75079 | R100: 46134 | U100: BILL PAY - 04989/05247/05364 | V100: =IF(G100="","", IF(AND(G100>=DATE(2024,4,1),G100<=DATE(2025,3,31)),"FY 24-25", IF(AND(G100>=DATE(2025,4,1),G100<=DATE(2026,3,31)),"FY 25-26",IF(AND(G100>=DATE(2026,4,1),G100<=DATE(2027,3,31)),"FY 26-27","")))) -> FY 25-26
A101: ADITYA BIRLA | B101: =IF($A$3=" "," ", IFERROR( VLOOKUP($A101,'SUPPLIER DATA BASE'!$A$2:$M$936,3,0),"")) -> - | C101: =IF($A$3=" "," ", IFERROR( VLOOKUP($A101,'SUPPLIER DATA BASE'!$A$2:$F$936,6,0),"")) -> - | D101: =IF($A$3=" "," ", IFERROR( VLOOKUP($A101,'SUPPLIER DATA BASE'!$A$2:$G$936,4,0),"")) -> - | E101: =IF($A$3=" "," ", IFERROR( VLOOKUP($A101,'SUPPLIER DATA BASE'!$A$2:$H$936,5,0),"")) -> - | F101: MSF2252000028380 | G101: 46057 | H101: 6 | I101: 10848.3 | J101: MSF2252000028380 SAHEBGANJ.pdf | K101: - | L101: - | M101: =IF(G101="", "", (TODAY() - G101) & " Days") -> 131 Days | N101: =IF($A$3=" "," ", IFERROR( VLOOKUP($A101,'SUPPLIER DATA BASE'!$A$2:$O$936,11,0),"")) -> - | O101: =IF($A$3=" "," ", IFERROR( VLOOKUP($A101,'SUPPLIER DATA BASE'!$A$2:$O$936,12,0),"")) -> - | P101: =IF($A$3=" "," ", IFERROR( VLOOKUP($A101,'SUPPLIER DATA BASE'!$A$2:$O$936,13,0),"")) -> - | V101: =IF(G101="","", IF(AND(G101>=DATE(2024,4,1),G101<=DATE(2025,3,31)),"FY 24-25", IF(AND(G101>=DATE(2025,4,1),G101<=DATE(2026,3,31)),"FY 25-26",IF(AND(G101>=DATE(2026,4,1),G101<=DATE(2027,3,31)),"FY 26-27","")))) -> FY 25-26
A102: SARAOGI SUPER SALES PVT LTD | B102: =IF($A$3=" "," ", IFERROR( VLOOKUP($A102,'SUPPLIER DATA BASE'!$A$2:$M$936,3,0),"")) -> - | C102: =IF($A$3=" "," ", IFERROR( VLOOKUP($A102,'SUPPLIER DATA BASE'!$A$2:$F$936,6,0),"")) -> - | D102: =IF($A$3=" "," ", IFERROR( VLOOKUP($A102,'SUPPLIER DATA BASE'!$A$2:$G$936,4,0),"")) -> - | E102: =IF($A$3=" "," ", IFERROR( VLOOKUP($A102,'SUPPLIER DATA BASE'!$A$2:$H$936,5,0),"")) -> - | F102: 25-26/MUMS6190 | G102: 46057 | H102: 209 | I102: 106282 | J102: saraogi super sales 6190.pdf | K102: - | L102: - | M102: =IF(G102="", "", (TODAY() - G102) & " Days") -> 131 Days | N102: =IF($A$3=" "," ", IFERROR( VLOOKUP($A102,'SUPPLIER DATA BASE'!$A$2:$O$936,11,0),"")) -> SARAOGI SUPER SALES PVT LTD | O102: =IF($A$3=" "," ", IFERROR( VLOOKUP($A102,'SUPPLIER DATA BASE'!$A$2:$O$936,12,0),"")) -> SASUSP011006 | P102: =IF($A$3=" "," ", IFERROR( VLOOKUP($A102,'SUPPLIER DATA BASE'!$A$2:$O$936,13,0),"")) -> ICIC0000106 | V102: =IF(G102="","", IF(AND(G102>=DATE(2024,4,1),G102<=DATE(2025,3,31)),"FY 24-25", IF(AND(G102>=DATE(2025,4,1),G102<=DATE(2026,3,31)),"FY 25-26",IF(AND(G102>=DATE(2026,4,1),G102<=DATE(2027,3,31)),"FY 26-27","")))) -> FY 25-26
A103: SARAOGI SUPER SALES PVT LTD | B103: =IF($A$3=" "," ", IFERROR( VLOOKUP($A103,'SUPPLIER DATA BASE'!$A$2:$M$936,3,0),"")) -> - | C103: =IF($A$3=" "," ", IFERROR( VLOOKUP($A103,'SUPPLIER DATA BASE'!$A$2:$F$936,6,0),"")) -> - | D103: =IF($A$3=" "," ", IFERROR( VLOOKUP($A103,'SUPPLIER DATA BASE'!$A$2:$G$936,4,0),"")) -> - | E103: =IF($A$3=" "," ", IFERROR( VLOOKUP($A103,'SUPPLIER DATA BASE'!$A$2:$H$936,5,0),"")) -> - | F103: 25-26/MUMS6191 | G103: 46057 | H103: 213 | I103: 118079 | J103: saraogi super sales 6191.pdf | K103: - | L103: - | M103: =IF(G103="", "", (TODAY() - G103) & " Days") -> 131 Days | N103: =IF($A$3=" "," ", IFERROR( VLOOKUP($A103,'SUPPLIER DATA BASE'!$A$2:$O$936,11,0),"")) -> SARAOGI SUPER SALES PVT LTD | O103: =IF($A$3=" "," ", IFERROR( VLOOKUP($A103,'SUPPLIER DATA BASE'!$A$2:$O$936,12,0),"")) -> SASUSP011006 | P103: =IF($A$3=" "," ", IFERROR( VLOOKUP($A103,'SUPPLIER DATA BASE'!$A$2:$O$936,13,0),"")) -> ICIC0000106 | V103: =IF(G103="","", IF(AND(G103>=DATE(2024,4,1),G103<=DATE(2025,3,31)),"FY 24-25", IF(AND(G103>=DATE(2025,4,1),G103<=DATE(2026,3,31)),"FY 25-26",IF(AND(G103>=DATE(2026,4,1),G103<=DATE(2027,3,31)),"FY 26-27","")))) -> FY 25-26
A104: SARAOGI SUPER SALES PVT LTD | B104: =IF($A$3=" "," ", IFERROR( VLOOKUP($A104,'SUPPLIER DATA BASE'!$A$2:$M$936,3,0),"")) -> - | C104: =IF($A$3=" "," ", IFERROR( VLOOKUP($A104,'SUPPLIER DATA BASE'!$A$2:$F$936,6,0),"")) -> - | D104: =IF($A$3=" "," ", IFERROR( VLOOKUP($A104,'SUPPLIER DATA BASE'!$A$2:$G$936,4,0),"")) -> - | E104: =IF($A$3=" "," ", IFERROR( VLOOKUP($A104,'SUPPLIER DATA BASE'!$A$2:$H$936,5,0),"")) -> - | F104: 25-26/MUMS6192 | G104: 46057 | H104: 101 | I104: 65597 | J104: saraogi super sales 6192.pdf | K104: - | L104: - | M104: =IF(G104="", "", (TODAY() - G104) & " Days") -> 131 Days | N104: =IF($A$3=" "," ", IFERROR( VLOOKUP($A104,'SUPPLIER DATA BASE'!$A$2:$O$936,11,0),"")) -> SARAOGI SUPER SALES PVT LTD | O104: =IF($A$3=" "," ", IFERROR( VLOOKUP($A104,'SUPPLIER DATA BASE'!$A$2:$O$936,12,0),"")) -> SASUSP011006 | P104: =IF($A$3=" "," ", IFERROR( VLOOKUP($A104,'SUPPLIER DATA BASE'!$A$2:$O$936,13,0),"")) -> ICIC0000106 | V104: =IF(G104="","", IF(AND(G104>=DATE(2024,4,1),G104<=DATE(2025,3,31)),"FY 24-25", IF(AND(G104>=DATE(2025,4,1),G104<=DATE(2026,3,31)),"FY 25-26",IF(AND(G104>=DATE(2026,4,1),G104<=DATE(2027,3,31)),"FY 26-27","")))) -> FY 25-26
A105: SARAOGI SUPER SALES PVT LTD | B105: =IF($A$3=" "," ", IFERROR( VLOOKUP($A105,'SUPPLIER DATA BASE'!$A$2:$M$936,3,0),"")) -> - | C105: =IF($A$3=" "," ", IFERROR( VLOOKUP($A105,'SUPPLIER DATA BASE'!$A$2:$F$936,6,0),"")) -> - | D105: =IF($A$3=" "," ", IFERROR( VLOOKUP($A105,'SUPPLIER DATA BASE'!$A$2:$G$936,4,0),"")) -> - | E105: =IF($A$3=" "," ", IFERROR( VLOOKUP($A105,'SUPPLIER DATA BASE'!$A$2:$H$936,5,0),"")) -> - | F105: 25-26/MUMS6194 | G105: 46057 | H105: 167 | I105: 106209 | J105: saraogi super sales 6194.pdf | K105: - | L105: - | M105: =IF(G105="", "", (TODAY() - G105) & " Days") -> 131 Days | N105: =IF($A$3=" "," ", IFERROR( VLOOKUP($A105,'SUPPLIER DATA BASE'!$A$2:$O$936,11,0),"")) -> SARAOGI SUPER SALES PVT LTD | O105: =IF($A$3=" "," ", IFERROR( VLOOKUP($A105,'SUPPLIER DATA BASE'!$A$2:$O$936,12,0),"")) -> SASUSP011006 | P105: =IF($A$3=" "," ", IFERROR( VLOOKUP($A105,'SUPPLIER DATA BASE'!$A$2:$O$936,13,0),"")) -> ICIC0000106 | V105: =IF(G105="","", IF(AND(G105>=DATE(2024,4,1),G105<=DATE(2025,3,31)),"FY 24-25", IF(AND(G105>=DATE(2025,4,1),G105<=DATE(2026,3,31)),"FY 25-26",IF(AND(G105>=DATE(2026,4,1),G105<=DATE(2027,3,31)),"FY 26-27","")))) -> FY 25-26
A106: SARAOGI SUPER SALES PVT LTD | B106: =IF($A$3=" "," ", IFERROR( VLOOKUP($A106,'SUPPLIER DATA BASE'!$A$2:$M$936,3,0),"")) -> - | C106: =IF($A$3=" "," ", IFERROR( VLOOKUP($A106,'SUPPLIER DATA BASE'!$A$2:$F$936,6,0),"")) -> - | D106: =IF($A$3=" "," ", IFERROR( VLOOKUP($A106,'SUPPLIER DATA BASE'!$A$2:$G$936,4,0),"")) -> - | E106: =IF($A$3=" "," ", IFERROR( VLOOKUP($A106,'SUPPLIER DATA BASE'!$A$2:$H$936,5,0),"")) -> - | F106: 25-26/MUMS6196 | G106: 46057 | H106: 192 | I106: 101280 | J106: saraogi super sales 6196.pdf | K106: - | L106: - | M106: =IF(G106="", "", (TODAY() - G106) & " Days") -> 131 Days | N106: =IF($A$3=" "," ", IFERROR( VLOOKUP($A106,'SUPPLIER DATA BASE'!$A$2:$O$936,11,0),"")) -> SARAOGI SUPER SALES PVT LTD | O106: =IF($A$3=" "," ", IFERROR( VLOOKUP($A106,'SUPPLIER DATA BASE'!$A$2:$O$936,12,0),"")) -> SASUSP011006 | P106: =IF($A$3=" "," ", IFERROR( VLOOKUP($A106,'SUPPLIER DATA BASE'!$A$2:$O$936,13,0),"")) -> ICIC0000106 | V106: =IF(G106="","", IF(AND(G106>=DATE(2024,4,1),G106<=DATE(2025,3,31)),"FY 24-25", IF(AND(G106>=DATE(2025,4,1),G106<=DATE(2026,3,31)),"FY 25-26",IF(AND(G106>=DATE(2026,4,1),G106<=DATE(2027,3,31)),"FY 26-27","")))) -> FY 25-26
A107: SARAOGI SUPER SALES PVT LTD | B107: =IF($A$3=" "," ", IFERROR( VLOOKUP($A107,'SUPPLIER DATA BASE'!$A$2:$M$936,3,0),"")) -> - | C107: =IF($A$3=" "," ", IFERROR( VLOOKUP($A107,'SUPPLIER DATA BASE'!$A$2:$F$936,6,0),"")) -> - | D107: =IF($A$3=" "," ", IFERROR( VLOOKUP($A107,'SUPPLIER DATA BASE'!$A$2:$G$936,4,0),"")) -> - | E107: =IF($A$3=" "," ", IFERROR( VLOOKUP($A107,'SUPPLIER DATA BASE'!$A$2:$H$936,5,0),"")) -> - | F107: 25-26/MUMS6195 | G107: 46057 | H107: 168 | I107: 91583 | J107: saraogi super sales 6195.pdf | K107: - | L107: - | M107: =IF(G107="", "", (TODAY() - G107) & " Days") -> 131 Days | N107: =IF($A$3=" "," ", IFERROR( VLOOKUP($A107,'SUPPLIER DATA BASE'!$A$2:$O$936,11,0),"")) -> SARAOGI SUPER SALES PVT LTD | O107: =IF($A$3=" "," ", IFERROR( VLOOKUP($A107,'SUPPLIER DATA BASE'!$A$2:$O$936,12,0),"")) -> SASUSP011006 | P107: =IF($A$3=" "," ", IFERROR( VLOOKUP($A107,'SUPPLIER DATA BASE'!$A$2:$O$936,13,0),"")) -> ICIC0000106 | V107: =IF(G107="","", IF(AND(G107>=DATE(2024,4,1),G107<=DATE(2025,3,31)),"FY 24-25", IF(AND(G107>=DATE(2025,4,1),G107<=DATE(2026,3,31)),"FY 25-26",IF(AND(G107>=DATE(2026,4,1),G107<=DATE(2027,3,31)),"FY 26-27","")))) -> FY 25-26
A108: SARAOGI SUPER SALES PVT LTD | B108: =IF($A$3=" "," ", IFERROR( VLOOKUP($A108,'SUPPLIER DATA BASE'!$A$2:$M$936,3,0),"")) -> - | C108: =IF($A$3=" "," ", IFERROR( VLOOKUP($A108,'SUPPLIER DATA BASE'!$A$2:$F$936,6,0),"")) -> - | D108: =IF($A$3=" "," ", IFERROR( VLOOKUP($A108,'SUPPLIER DATA BASE'!$A$2:$G$936,4,0),"")) -> - | E108: =IF($A$3=" "," ", IFERROR( VLOOKUP($A108,'SUPPLIER DATA BASE'!$A$2:$H$936,5,0),"")) -> - | F108: 25-26/MUMS6193 | G108: 46057 | H108: 113 | I108: 62848 | J108: saraogi super sales 6193.pdf | K108: - | L108: - | M108: =IF(G108="", "", (TODAY() - G108) & " Days") -> 131 Days | N108: =IF($A$3=" "," ", IFERROR( VLOOKUP($A108,'SUPPLIER DATA BASE'!$A$2:$O$936,11,0),"")) -> SARAOGI SUPER SALES PVT LTD | O108: =IF($A$3=" "," ", IFERROR( VLOOKUP($A108,'SUPPLIER DATA BASE'!$A$2:$O$936,12,0),"")) -> SASUSP011006 | P108: =IF($A$3=" "," ", IFERROR( VLOOKUP($A108,'SUPPLIER DATA BASE'!$A$2:$O$936,13,0),"")) -> ICIC0000106 | V108: =IF(G108="","", IF(AND(G108>=DATE(2024,4,1),G108<=DATE(2025,3,31)),"FY 24-25", IF(AND(G108>=DATE(2025,4,1),G108<=DATE(2026,3,31)),"FY 25-26",IF(AND(G108>=DATE(2026,4,1),G108<=DATE(2027,3,31)),"FY 26-27","")))) -> FY 25-26
...

Sheet COMPILED PT FILE
A3: INVOICE NUMBER | B3: INVOICE DATE | C3: BRAND | D3: COLOR | E3: GENDER | F3: SUB CATEGORY | G3: TYPE | H3: ITEM | I3: FIT | J3: SIZE | K3: BARCODE | L3: DESIGN | M3: HSN | N3: QTY | O3: MRP | P3: BASIC | Q3: P RATE | R3: INPUT TAX | S3: OUTPUT TAX | T3: NAG | U3: MARGIN | V3: MONTH
A4: PMS/26-27/786 | B4: =IFERROR( VLOOKUP($A4,'INVOICE DETAILS.'!$F$3:$G$1994,2,0)," ") -> 46174 | C4: PMS | D4: PREMIUM | E4: FEMALE | F4: CASUAL WEAR | G4: BOTTOM WEAR | H4: JEANS | I4: REGULAR | J4: 28 | L4: PMS-762 | M4: 620349 | N4: 1 | O4: 1199 | P4: 762 | Q4: 838.2 | R4: 5 | S4: 5 | T4: 1 | U4: 30 | V4: =UPPER( IFERROR( TEXT($B4,"MMMM")," ")) -> JUNE
A5: PMS/26-27/786 | B5: =IFERROR( VLOOKUP($A5,'INVOICE DETAILS.'!$F$3:$G$1994,2,0)," ") -> 46174 | C5: PMS | D5: PREMIUM | E5: FEMALE | F5: CASUAL WEAR | G5: BOTTOM WEAR | H5: JEANS | I5: REGULAR | J5: 30 | L5: PMS-762 | M5: 620349 | N5: 1 | O5: 1199 | P5: 762 | Q5: 838.2 | R5: 5 | S5: 5 | T5: 1 | U5: 30 | V5: =UPPER( IFERROR( TEXT($B5,"MMMM")," ")) -> JUNE
A6: PMS/26-27/786 | B6: =IFERROR( VLOOKUP($A6,'INVOICE DETAILS.'!$F$3:$G$1994,2,0)," ") -> 46174 | C6: PMS | D6: PREMIUM | E6: FEMALE | F6: CASUAL WEAR | G6: BOTTOM WEAR | H6: JEANS | I6: REGULAR | J6: 32 | L6: PMS-762 | M6: 620349 | N6: 1 | O6: 1199 | P6: 762 | Q6: 838.2 | R6: 5 | S6: 5 | T6: 1 | U6: 30 | V6: =UPPER( IFERROR( TEXT($B6,"MMMM")," ")) -> JUNE
A7: PMS/26-27/786 | B7: =IFERROR( VLOOKUP($A7,'INVOICE DETAILS.'!$F$3:$G$1994,2,0)," ") -> 46174 | C7: PMS | D7: PREMIUM | E7: FEMALE | F7: CASUAL WEAR | G7: BOTTOM WEAR | H7: JEANS | I7: REGULAR | J7: 34 | L7: PMS-762 | M7: 620349 | N7: 1 | O7: 1199 | P7: 762 | Q7: 838.2 | R7: 5 | S7: 5 | T7: 1 | U7: 30 | V7: =UPPER( IFERROR( TEXT($B7,"MMMM")," ")) -> JUNE
A8: PMS/26-27/786 | B8: =IFERROR( VLOOKUP($A8,'INVOICE DETAILS.'!$F$3:$G$1994,2,0)," ") -> 46174 | C8: PMS | D8: PREMIUM | E8: FEMALE | F8: CASUAL WEAR | G8: BOTTOM WEAR | H8: JEANS | I8: REGULAR | J8: 28 | L8: PMS-612 | M8: 620349 | N8: 2 | O8: 949 | P8: 612 | Q8: 673.2 | R8: 5 | S8: 5 | T8: 2 | U8: 29 | V8: =UPPER( IFERROR( TEXT($B8,"MMMM")," ")) -> JUNE
A9: PMS/26-27/786 | B9: =IFERROR( VLOOKUP($A9,'INVOICE DETAILS.'!$F$3:$G$1994,2,0)," ") -> 46174 | C9: PMS | D9: PREMIUM | E9: FEMALE | F9: CASUAL WEAR | G9: BOTTOM WEAR | H9: JEANS | I9: REGULAR | J9: 30 | L9: PMS-612 | M9: 620349 | N9: 1 | O9: 949 | P9: 612 | Q9: 673.2 | R9: 5 | S9: 5 | T9: 1 | U9: 29 | V9: =UPPER( IFERROR( TEXT($B9,"MMMM")," ")) -> JUNE
A10: PMS/26-27/786 | B10: =IFERROR( VLOOKUP($A10,'INVOICE DETAILS.'!$F$3:$G$1994,2,0)," ") -> 46174 | C10: PMS | D10: PREMIUM | E10: FEMALE | F10: CASUAL WEAR | G10: BOTTOM WEAR | H10: JEANS | I10: REGULAR | J10: 32 | L10: PMS-612 | M10: 620349 | N10: 1 | O10: 949 | P10: 612 | Q10: 673.2 | R10: 5 | S10: 5 | T10: 1 | U10: 29 | V10: =UPPER( IFERROR( TEXT($B10,"MMMM")," ")) -> JUNE
A11: PECRS26/625 | B11: =IFERROR( VLOOKUP($A11,'INVOICE DETAILS.'!$F$3:$G$1994,2,0)," ") -> 46174 | C11: JOCKEY | D11: PREMIUM | E11: MALE | F11: INNERWEAR | G11: ACCESSORIES | H11: BRIEF | I11: REGULAR | J11: M | K11: US07M279 | L11: US07-0110-ASSTD | M11: 61071990 | N11: 10 | O11: 279 | P11: 194.82 | Q11: 233.78 | R11: 5 | S11: 5 | T11: 10 | U11: 16 | V11: =UPPER( IFERROR( TEXT($B11,"MMMM")," ")) -> JUNE
A12: MDCRS26/680 | B12: =IFERROR( VLOOKUP($A12,'INVOICE DETAILS.'!$F$3:$G$1994,2,0)," ") -> 46174 | C12: JOCKEY | D12: PREMIUM | E12: MALE | F12: INNERWEAR | G12: ACCESSORIES | H12: VEST | I12: REGULAR | J12: S | K12: 8820S259 | L12: 8820-0110-WHITE | M12: 61091000 | N12: 20 | O12: 259 | P12: 187.58 | Q12: 225.1 | R12: 5 | S12: 5 | T12: 20 | U12: 13 | V12: =UPPER( IFERROR( TEXT($B12,"MMMM")," ")) -> JUNE
A13: MDCRS26/680 | B13: =IFERROR( VLOOKUP($A13,'INVOICE DETAILS.'!$F$3:$G$1994,2,0)," ") -> 46174 | C13: JOCKEY | D13: PREMIUM | E13: MALE | F13: INNERWEAR | G13: ACCESSORIES | H13: VEST | I13: REGULAR | J13: M | K13: 8820M249 | L13: 8820-0110-WHITE | M13: 61091000 | N13: 40 | O13: 249 | P13: 180.33 | Q13: 216.4 | R13: 5 | S13: 5 | T13: 40 | U13: 13 | V13: =UPPER( IFERROR( TEXT($B13,"MMMM")," ")) -> JUNE
A14: MDCRS26/680 | B14: =IFERROR( VLOOKUP($A14,'INVOICE DETAILS.'!$F$3:$G$1994,2,0)," ") -> 46174 | C14: JOCKEY | D14: PREMIUM | E14: MALE | F14: INNERWEAR | G14: ACCESSORIES | H14: VEST | I14: REGULAR | J14: L | K14: 8820L249 | L14: 8820-0110-WHITE | M14: 61091000 | N14: 20 | O14: 249 | P14: 180.33 | Q14: 216.4 | R14: 5 | S14: 5 | T14: 20 | U14: 13 | V14: =UPPER( IFERROR( TEXT($B14,"MMMM")," ")) -> JUNE
A15: MDCRS26/680 | B15: =IFERROR( VLOOKUP($A15,'INVOICE DETAILS.'!$F$3:$G$1994,2,0)," ") -> 46174 | C15: JOCKEY | D15: PREMIUM | E15: MALE | F15: INNERWEAR | G15: ACCESSORIES | H15: VEST | I15: REGULAR | J15: M | K15: 8820M669 | L15: 8820-0310-WHITE | M15: 61091000 | N15: 10 | O15: 669 | P15: 484.51 | Q15: 581.41 | R15: 5 | S15: 5 | T15: 10 | U15: 13 | V15: =UPPER( IFERROR( TEXT($B15,"MMMM")," ")) -> JUNE
B16: =IFERROR( VLOOKUP($A16,'INVOICE DETAILS.'!$F$3:$G$1994,2,0)," ") | V16: =UPPER( IFERROR( TEXT($B16,"MMMM")," "))
B17: =IFERROR( VLOOKUP($A17,'INVOICE DETAILS.'!$F$3:$G$1994,2,0)," ") | V17: =UPPER( IFERROR( TEXT($B17,"MMMM")," "))
B18: =IFERROR( VLOOKUP($A18,'INVOICE DETAILS.'!$F$3:$G$1994,2,0)," ") | V18: =UPPER( IFERROR( TEXT($B18,"MMMM")," "))
B19: =IFERROR( VLOOKUP($A19,'INVOICE DETAILS.'!$F$3:$G$1994,2,0)," ") | V19: =UPPER( IFERROR( TEXT($B19,"MMMM")," "))
B20: =IFERROR( VLOOKUP($A20,'INVOICE DETAILS.'!$F$3:$G$1994,2,0)," ") | V20: =UPPER( IFERROR( TEXT($B20,"MMMM")," "))
B21: =IFERROR( VLOOKUP($A21,'INVOICE DETAILS.'!$F$3:$G$1994,2,0)," ") | V21: =UPPER( IFERROR( TEXT($B21,"MMMM")," "))
B22: =IFERROR( VLOOKUP($A22,'INVOICE DETAILS.'!$F$3:$G$1994,2,0)," ") | V22: =UPPER( IFERROR( TEXT($B22,"MMMM")," "))
B23: =IFERROR( VLOOKUP($A23,'INVOICE DETAILS.'!$F$3:$G$1994,2,0)," ") | V23: =UPPER( IFERROR( TEXT($B23,"MMMM")," "))
B24: =IFERROR( VLOOKUP($A24,'INVOICE DETAILS.'!$F$3:$G$1994,2,0)," ") | V24: =UPPER( IFERROR( TEXT($B24,"MMMM")," "))
B25: =IFERROR( VLOOKUP($A25,'INVOICE DETAILS.'!$F$3:$G$1994,2,0)," ") | V25: =UPPER( IFERROR( TEXT($B25,"MMMM")," "))
B26: =IFERROR( VLOOKUP($A26,'INVOICE DETAILS.'!$F$3:$G$1994,2,0)," ") | V26: =UPPER( IFERROR( TEXT($B26,"MMMM")," "))
B27: =IFERROR( VLOOKUP($A27,'INVOICE DETAILS.'!$F$3:$G$1994,2,0)," ") | V27: =UPPER( IFERROR( TEXT($B27,"MMMM")," "))
... B1000: =IFERROR( VLOOKUP($A1000,'INVOICE DETAILS.'!$F$3:$G$1994,2,0)," ") | V1000: =UPPER( IFERROR( TEXT($B1000,"MMMM")," "))

Sheet SUMMARY
A1: KDPS PARTY LEDGER SUMMARY | B1: =IF(SUBTOTAL(9,B3:B1001)=0," ",SUBTOTAL(9,B3:B1001)) -> 67763896 | C1: =IF(SUBTOTAL(9,C3:C1001)=0," ",SUBTOTAL(9,C3:C1001)) | D1: =IF(SUBTOTAL(9,D3:D1001)=0," ",SUBTOTAL(9,D3:D1001)) -> 22888 | E1: =IF(SUBTOTAL(9,E3:E1001)=0," ",SUBTOTAL(9,E3:E1001)) -> 16674 | F1: =IF(SUBTOTAL(9,F3:F1001)=0," ",SUBTOTAL(9,F3:F1001)) -> 488269 | G1: =IF(SUBTOTAL(9,G3:G1001)=0," ",SUBTOTAL(9,G3:G1001)) -> 459 | H1: =IF(SUBTOTAL(9,H3:H1001)=0," ",SUBTOTAL(9,H3:H1001)) -> 67235606
C2: Opening Balance | D2: CD Amount | E2: GR Value | F2: Payment Amount | G2: Interest If Any | H2: Due As On
H3: =IF(SUM(B3:C3)-(SUM(D3:F3))+G3=0," ",SUM(B3:C3)-(SUM(D3:F3)+G3)) -> 1361055
H4: =IF(SUM(B4:C4)-(SUM(D4:F4))+G4=0," ",SUM(B4:C4)-(SUM(D4:F4)+G4)) -> 119652
H5: =IF(SUM(B5:C5)-(SUM(D5:F5))+G5=0," ",SUM(B5:C5)-(SUM(D5:F5)+G5)) -> 24640
H6: =IF(SUM(B6:C6)-(SUM(D6:F6))+G6=0," ",SUM(B6:C6)-(SUM(D6:F6)+G6))
H7: =IF(SUM(B7:C7)-(SUM(D7:F7))+G7=0," ",SUM(B7:C7)-(SUM(D7:F7)+G7)) -> 17281790
H8: =IF(SUM(B8:C8)-(SUM(D8:F8))+G8=0," ",SUM(B8:C8)-(SUM(D8:F8)+G8))
H9: =IF(SUM(B9:C9)-(SUM(D9:F9))+G9=0," ",SUM(B9:C9)-(SUM(D9:F9)+G9)) -> 42450
H10: =IF(SUM(B10:C10)-(SUM(D10:F10))+G10=0," ",SUM(B10:C10)-(SUM(D10:F10)+G10)) -> 208512
H11: =IF(SUM(B11:C11)-(SUM(D11:F11))+G11=0," ",SUM(B11:C11)-(SUM(D11:F11)+G11)) -> 130982
D12: =20706+2182 -> 22888 | E12: =16674 -> 16674 | F12: =209836+23270+55163+200000 -> 488269 | G12: =459 -> 459 | H12: =IF(SUM(B12:C12)-(SUM(D12:F12))+G12=0," ",SUM(B12:C12)-(SUM(D12:F12)+G12)) -> 57936
H13: =IF(SUM(B13:C13)-(SUM(D13:F13))+G13=0," ",SUM(B13:C13)-(SUM(D13:F13)+G13)) -> 159070
H14: =IF(SUM(B14:C14)-(SUM(D14:F14))+G14=0," ",SUM(B14:C14)-(SUM(D14:F14)+G14)) -> 57346
H15: =IF(SUM(B15:C15)-(SUM(D15:F15))+G15=0," ",SUM(B15:C15)-(SUM(D15:F15)+G15)) -> 17266
H16: =IF(SUM(B16:C16)-(SUM(D16:F16))+G16=0," ",SUM(B16:C16)-(SUM(D16:F16)+G16))
H17: =IF(SUM(B17:C17)-(SUM(D17:F17))+G17=0," ",SUM(B17:C17)-(SUM(D17:F17)+G17))
H18: =IF(SUM(B18:C18)-(SUM(D18:F18))+G18=0," ",SUM(B18:C18)-(SUM(D18:F18)+G18)) -> 320569
H19: =IF(SUM(B19:C19)-(SUM(D19:F19))+G19=0," ",SUM(B19:C19)-(SUM(D19:F19)+G19)) -> 174636
H20: =IF(SUM(B20:C20)-(SUM(D20:F20))+G20=0," ",SUM(B20:C20)-(SUM(D20:F20)+G20)) -> 1784598
H21: =IF(SUM(B21:C21)-(SUM(D21:F21))+G21=0," ",SUM(B21:C21)-(SUM(D21:F21)+G21)) -> 343788
H22: =IF(SUM(B22:C22)-(SUM(D22:F22))+G22=0," ",SUM(B22:C22)-(SUM(D22:F22)+G22)) -> 24253
H23: =IF(SUM(B23:C23)-(SUM(D23:F23))+G23=0," ",SUM(B23:C23)-(SUM(D23:F23)+G23)) -> 4780218
H24: =IF(SUM(B24:C24)-(SUM(D24:F24))+G24=0," ",SUM(B24:C24)-(SUM(D24:F24)+G24)) -> 682521
... H1001: =IF(SUM(B1001:C1001)-(SUM(D1001:F1001))+G1001=0," ",SUM(B1001:C1001)-(SUM(D1001:F1001)+G1001))
